Compiled from "Activity.kt"
public final class org.fossify.commons.extensions.ActivityKt {
  public static final void appLaunched(android.app.Activity, java.lang.String);
    Code:
         0: aload_0
         1: ldc           #9                  // String <this>
         3: invokestatic  #15                 // Method kotlin/jvm/internal/Intrinsics.checkNotNullParameter:(Ljava/lang/Object;Ljava/lang/String;)V
         6: aload_1
         7: ldc           #17                 // String appId
         9: invokestatic  #15                 // Method kotlin/jvm/internal/Intrinsics.checkNotNullParameter:(Ljava/lang/Object;Ljava/lang/String;)V
        12: aload_0
        13: checkcast     #19                 // class android/content/Context
        16: invokestatic  #25                 // Method org/fossify/commons/extensions/ContextKt.getBaseConfig:(Landroid/content/Context;)Lorg/fossify/commons/helpers/BaseConfig;
        19: aload_0
        20: checkcast     #19                 // class android/content/Context
        23: invokestatic  #31                 // Method org/fossify/commons/extensions/Context_storageKt.getInternalStoragePath:(Landroid/content/Context;)Ljava/lang/String;
        26: invokevirtual #37                 // Method org/fossify/commons/helpers/BaseConfig.setInternalStoragePath:(Ljava/lang/String;)V
        29: aload_0
        30: checkcast     #19                 // class android/content/Context
        33: invokestatic  #41                 // Method org/fossify/commons/extensions/ContextKt.updateSDCardPath:(Landroid/content/Context;)V
        36: aload_0
        37: checkcast     #19                 // class android/content/Context
        40: invokestatic  #25                 // Method org/fossify/commons/extensions/ContextKt.getBaseConfig:(Landroid/content/Context;)Lorg/fossify/commons/helpers/BaseConfig;
        43: aload_1
        44: invokevirtual #44                 // Method org/fossify/commons/helpers/BaseConfig.setAppId:(Ljava/lang/String;)V
        47: aload_0
        48: checkcast     #19                 // class android/content/Context
        51: invokestatic  #25                 // Method org/fossify/commons/extensions/ContextKt.getBaseConfig:(Landroid/content/Context;)Lorg/fossify/commons/helpers/BaseConfig;
        54: invokevirtual #48                 // Method org/fossify/commons/helpers/BaseConfig.getAppRunCount:()I
        57: ifne          81
        60: aload_0
        61: checkcast     #19                 // class android/content/Context
        64: invokestatic  #25                 // Method org/fossify/commons/extensions/ContextKt.getBaseConfig:(Landroid/content/Context;)Lorg/fossify/commons/helpers/BaseConfig;
        67: iconst_1
        68: invokevirtual #52                 // Method org/fossify/commons/helpers/BaseConfig.setWasOrangeIconChecked:(Z)V
        71: aload_0
        72: checkcast     #19                 // class android/content/Context
        75: invokestatic  #57                 // Method org/fossify/commons/extensions/Context_stylingKt.checkAppIconColor:(Landroid/content/Context;)V
        78: goto          351
        81: aload_0
        82: checkcast     #19                 // class android/content/Context
        85: invokestatic  #25                 // Method org/fossify/commons/extensions/ContextKt.getBaseConfig:(Landroid/content/Context;)Lorg/fossify/commons/helpers/BaseConfig;
        88: invokevirtual #61                 // Method org/fossify/commons/helpers/BaseConfig.getWasOrangeIconChecked:()Z
        91: ifne          351
        94: aload_0
        95: checkcast     #19                 // class android/content/Context
        98: invokestatic  #25                 // Method org/fossify/commons/extensions/ContextKt.getBaseConfig:(Landroid/content/Context;)Lorg/fossify/commons/helpers/BaseConfig;
       101: iconst_1
       102: invokevirtual #52                 // Method org/fossify/commons/helpers/BaseConfig.setWasOrangeIconChecked:(Z)V
       105: aload_0
       106: invokevirtual #67                 // Method android/app/Activity.getResources:()Landroid/content/res/Resources;
       109: getstatic     #73                 // Field org/fossify/commons/R$color.color_primary:I
       112: invokevirtual #79                 // Method android/content/res/Resources.getColor:(I)I
       115: istore_2
       116: aload_0
       117: checkcast     #19                 // class android/content/Context
       120: invokestatic  #25                 // Method org/fossify/commons/extensions/ContextKt.getBaseConfig:(Landroid/content/Context;)Lorg/fossify/commons/helpers/BaseConfig;
       123: invokevirtual #82                 // Method org/fossify/commons/helpers/BaseConfig.getAppIconColor:()I
       126: iload_2
       127: if_icmpeq     351
       130: aload_0
       131: checkcast     #19                 // class android/content/Context
       134: invokestatic  #86                 // Method org/fossify/commons/extensions/Context_stylingKt.getAppIconColors:(Landroid/content/Context;)Ljava/util/ArrayList;
       137: checkcast     #88                 // class java/lang/Iterable
       140: astore_3
       141: iconst_0
       142: istore        4
       144: iconst_0
       145: istore        5
       147: aload_3
       148: invokeinterface #92,  1           // InterfaceMethod java/lang/Iterable.iterator:()Ljava/util/Iterator;
       153: astore        6
       155: aload         6
       157: invokeinterface #97,  1           // InterfaceMethod java/util/Iterator.hasNext:()Z
       162: ifeq          224
       165: aload         6
       167: invokeinterface #101,  1          // InterfaceMethod java/util/Iterator.next:()Ljava/lang/Object;
       172: astore        7
       174: iload         5
       176: iinc          5, 1
       179: istore        8
       181: iload         8
       183: ifge          189
       186: invokestatic  #107                // Method kotlin/collections/CollectionsKt.throwIndexOverflow:()V
       189: iload         8
       191: aload         7
       193: checkcast     #109                // class java/lang/Number
       196: invokevirtual #112                // Method java/lang/Number.intValue:()I
       199: istore        9
       201: istore        10
       203: iconst_0
       204: istore        11
       206: aload_0
       207: checkcast     #19                 // class android/content/Context
       210: aload_1
       211: iload         10
       213: iload         9
       215: iconst_0
       216: invokestatic  #116                // Method org/fossify/commons/extensions/Context_stylingKt.toggleAppIconColor:(Landroid/content/Context;Ljava/lang/String;IIZ)V
       219: nop
       220: nop
       221: goto          155
       224: nop
       225: aload_0
       226: checkcast     #19                 // class android/content/Context
       229: invokestatic  #25                 // Method org/fossify/commons/extensions/ContextKt.getBaseConfig:(Landroid/content/Context;)Lorg/fossify/commons/helpers/BaseConfig;
       232: invokevirtual #120                // Method org/fossify/commons/helpers/BaseConfig.getAppId:()Ljava/lang/String;
       235: ldc           #122                // String .debug
       237: checkcast     #124                // class java/lang/CharSequence
       240: invokestatic  #130                // Method kotlin/text/StringsKt.removeSuffix:(Ljava/lang/String;Ljava/lang/CharSequence;)Ljava/lang/String;
       243: invokedynamic #142,  0            // InvokeDynamic #0:makeConcatWithConstants:(Ljava/lang/String;)Ljava/lang/String;
       248: astore_3
       249: aload_0
       250: invokevirtual #146                // Method android/app/Activity.getPackageManager:()Landroid/content/pm/PackageManager;
       253: new           #148                // class android/content/ComponentName
       256: dup
       257: aload_0
       258: checkcast     #19                 // class android/content/Context
       261: invokestatic  #25                 // Method org/fossify/commons/extensions/ContextKt.getBaseConfig:(Landroid/content/Context;)Lorg/fossify/commons/helpers/BaseConfig;
       264: invokevirtual #120                // Method org/fossify/commons/helpers/BaseConfig.getAppId:()Ljava/lang/String;
       267: aload_3
       268: invokespecial #152                // Method android/content/ComponentName."<init>":(Ljava/lang/String;Ljava/lang/String;)V
       271: iconst_0
       272: iconst_1
       273: invokevirtual #158                // Method android/content/pm/PackageManager.setComponentEnabledSetting:(Landroid/content/ComponentName;II)V
       276: aload_0
       277: checkcast     #19                 // class android/content/Context
       280: invokestatic  #25                 // Method org/fossify/commons/extensions/ContextKt.getBaseConfig:(Landroid/content/Context;)Lorg/fossify/commons/helpers/BaseConfig;
       283: invokevirtual #120                // Method org/fossify/commons/helpers/BaseConfig.getAppId:()Ljava/lang/String;
       286: ldc           #122                // String .debug
       288: checkcast     #124                // class java/lang/CharSequence
       291: invokestatic  #130                // Method kotlin/text/StringsKt.removeSuffix:(Ljava/lang/String;Ljava/lang/CharSequence;)Ljava/lang/String;
       294: invokedynamic #161,  0            // InvokeDynamic #1:makeConcatWithConstants:(Ljava/lang/String;)Ljava/lang/String;
       299: astore        4
       301: aload_0
       302: invokevirtual #146                // Method android/app/Activity.getPackageManager:()Landroid/content/pm/PackageManager;
       305: new           #148                // class android/content/ComponentName
       308: dup
       309: aload_0
       310: checkcast     #19                 // class android/content/Context
       313: invokestatic  #25                 // Method org/fossify/commons/extensions/ContextKt.getBaseConfig:(Landroid/content/Context;)Lorg/fossify/commons/helpers/BaseConfig;
       316: invokevirtual #120                // Method org/fossify/commons/helpers/BaseConfig.getAppId:()Ljava/lang/String;
       319: aload         4
       321: invokespecial #152                // Method android/content/ComponentName."<init>":(Ljava/lang/String;Ljava/lang/String;)V
       324: iconst_1
       325: iconst_1
       326: invokevirtual #158                // Method android/content/pm/PackageManager.setComponentEnabledSetting:(Landroid/content/ComponentName;II)V
       329: aload_0
       330: checkcast     #19                 // class android/content/Context
       333: invokestatic  #25                 // Method org/fossify/commons/extensions/ContextKt.getBaseConfig:(Landroid/content/Context;)Lorg/fossify/commons/helpers/BaseConfig;
       336: iload_2
       337: invokevirtual #165                // Method org/fossify/commons/helpers/BaseConfig.setAppIconColor:(I)V
       340: aload_0
       341: checkcast     #19                 // class android/content/Context
       344: invokestatic  #25                 // Method org/fossify/commons/extensions/ContextKt.getBaseConfig:(Landroid/content/Context;)Lorg/fossify/commons/helpers/BaseConfig;
       347: iload_2
       348: invokevirtual #168                // Method org/fossify/commons/helpers/BaseConfig.setLastIconColor:(I)V
       351: aload_0
       352: checkcast     #19                 // class android/content/Context
       355: invokestatic  #25                 // Method org/fossify/commons/extensions/ContextKt.getBaseConfig:(Landroid/content/Context;)Lorg/fossify/commons/helpers/BaseConfig;
       358: astore_2
       359: aload_2
       360: invokevirtual #48                 // Method org/fossify/commons/helpers/BaseConfig.getAppRunCount:()I
       363: istore_3
       364: aload_2
       365: iload_3
       366: iconst_1
       367: iadd
       368: invokevirtual #171                // Method org/fossify/commons/helpers/BaseConfig.setAppRunCount:(I)V
       371: aload_0
       372: checkcast     #19                 // class android/content/Context
       375: invokestatic  #25                 // Method org/fossify/commons/extensions/ContextKt.getBaseConfig:(Landroid/content/Context;)Lorg/fossify/commons/helpers/BaseConfig;
       378: invokevirtual #48                 // Method org/fossify/commons/helpers/BaseConfig.getAppRunCount:()I
       381: bipush        30
       383: irem
       384: ifne          414
       387: aload_0
       388: checkcast     #19                 // class android/content/Context
       391: invokestatic  #175                // Method org/fossify/commons/extensions/ContextKt.isAProApp:(Landroid/content/Context;)Z
       394: ifne          414
       397: aload_0
       398: invokevirtual #67                 // Method android/app/Activity.getResources:()Landroid/content/res/Resources;
       401: getstatic     #180                // Field org/fossify/commons/R$bool.hide_google_relations:I
       404: invokevirtual #184                // Method android/content/res/Resources.getBoolean:(I)Z
       407: ifne          414
       410: aload_0
       411: invokestatic  #188                // Method showDonateOrUpgradeDialog:(Landroid/app/Activity;)V
       414: return

  public static final void showDonateOrUpgradeDialog(android.app.Activity);
    Code:
         0: aload_0
         1: ldc           #9                  // String <this>
         3: invokestatic  #15                 // Method kotlin/jvm/internal/Intrinsics.checkNotNullParameter:(Ljava/lang/Object;Ljava/lang/String;)V
         6: aload_0
         7: checkcast     #19                 // class android/content/Context
        10: invokestatic  #208                // Method org/fossify/commons/extensions/ContextKt.getCanAppBeUpgraded:(Landroid/content/Context;)Z
        13: ifeq          28
        16: new           #210                // class org/fossify/commons/dialogs/UpgradeToProDialog
        19: dup
        20: aload_0
        21: invokespecial #212                // Method org/fossify/commons/dialogs/UpgradeToProDialog."<init>":(Landroid/app/Activity;)V
        24: pop
        25: goto          50
        28: aload_0
        29: checkcast     #19                 // class android/content/Context
        32: iconst_0
        33: iconst_1
        34: aconst_null
        35: invokestatic  #216                // Method org/fossify/commons/extensions/ContextKt.isOrWasThankYouInstalled$default:(Landroid/content/Context;ZILjava/lang/Object;)Z
        38: ifne          50
        41: new           #218                // class org/fossify/commons/dialogs/DonateDialog
        44: dup
        45: aload_0
        46: invokespecial #219                // Method org/fossify/commons/dialogs/DonateDialog."<init>":(Landroid/app/Activity;)V
        49: pop
        50: return

  public static final boolean isAppInstalledOnSDCard(android.app.Activity);
    Code:
         0: aload_0
         1: ldc           #9                  // String <this>
         3: invokestatic  #15                 // Method kotlin/jvm/internal/Intrinsics.checkNotNullParameter:(Ljava/lang/Object;Ljava/lang/String;)V
         6: nop
         7: aload_0
         8: invokevirtual #146                // Method android/app/Activity.getPackageManager:()Landroid/content/pm/PackageManager;
        11: aload_0
        12: invokevirtual #227                // Method android/app/Activity.getPackageName:()Ljava/lang/String;
        15: iconst_0
        16: invokevirtual #231                // Method android/content/pm/PackageManager.getPackageInfo:(Ljava/lang/String;I)Landroid/content/pm/PackageInfo;
        19: getfield      #237                // Field android/content/pm/PackageInfo.applicationInfo:Landroid/content/pm/ApplicationInfo;
        22: astore_1
        23: aload_1
        24: ifnull        47
        27: aload_1
        28: getfield      #242                // Field android/content/pm/ApplicationInfo.flags:I
        31: ldc           #243                // int 262144
        33: iand
        34: ldc           #243                // int 262144
        36: if_icmpne     43
        39: iconst_1
        40: goto          48
        43: iconst_0
        44: goto          48
        47: iconst_0
        48: istore_1
        49: goto          55
        52: astore_2
        53: iconst_0
        54: istore_1
        55: iload_1
        56: ireturn
      Exception table:
         from    to  target type
             6    49    52   Class java/lang/Exception

  public static final boolean isShowingSAFDialog(org.fossify.commons.activities.BaseSimpleActivity, java.lang.String);
    Code:
         0: aload_0
         1: ldc           #9                  // String <this>
         3: invokestatic  #15                 // Method kotlin/jvm/internal/Intrinsics.checkNotNullParameter:(Ljava/lang/Object;Ljava/lang/String;)V
         6: aload_1
         7: ldc           #251                // String path
         9: invokestatic  #15                 // Method kotlin/jvm/internal/Intrinsics.checkNotNullParameter:(Ljava/lang/Object;Ljava/lang/String;)V
        12: invokestatic  #256                // Method org/fossify/commons/helpers/ConstantsKt.isRPlus:()Z
        15: ifne          94
        18: aload_0
        19: checkcast     #19                 // class android/content/Context
        22: aload_1
        23: invokestatic  #260                // Method org/fossify/commons/extensions/Context_storageKt.isPathOnSD:(Landroid/content/Context;Ljava/lang/String;)Z
        26: ifeq          94
        29: aload_0
        30: checkcast     #19                 // class android/content/Context
        33: invokestatic  #263                // Method org/fossify/commons/extensions/Context_storageKt.isSDCardSetAsDefaultStorage:(Landroid/content/Context;)Z
        36: ifne          94
        39: aload_0
        40: checkcast     #19                 // class android/content/Context
        43: invokestatic  #25                 // Method org/fossify/commons/extensions/ContextKt.getBaseConfig:(Landroid/content/Context;)Lorg/fossify/commons/helpers/BaseConfig;
        46: invokevirtual #266                // Method org/fossify/commons/helpers/BaseConfig.getSdTreeUri:()Ljava/lang/String;
        49: checkcast     #124                // class java/lang/CharSequence
        52: invokeinterface #269,  1          // InterfaceMethod java/lang/CharSequence.length:()I
        57: ifne          64
        60: iconst_1
        61: goto          65
        64: iconst_0
        65: ifne          79
        68: aload_0
        69: checkcast     #19                 // class android/content/Context
        72: iconst_0
        73: invokestatic  #273                // Method org/fossify/commons/extensions/Context_storageKt.hasProperStoredTreeUri:(Landroid/content/Context;Z)Z
        76: ifne          94
        79: aload_0
        80: aload_0
        81: aload_1
        82: invokedynamic #290,  0            // InvokeDynamic #2:run:(Lorg/fossify/commons/activities/BaseSimpleActivity;Ljava/lang/String;)Ljava/lang/Runnable;
        87: invokevirtual #296                // Method org/fossify/commons/activities/BaseSimpleActivity.runOnUiThread:(Ljava/lang/Runnable;)V
        90: iconst_1
        91: goto          95
        94: iconst_0
        95: ireturn

  public static final boolean isShowingSAFDialogSdk30(org.fossify.commons.activities.BaseSimpleActivity, java.lang.String, boolean);
    Code:
         0: aload_0
         1: ldc           #9                  // String <this>
         3: invokestatic  #15                 // Method kotlin/jvm/internal/Intrinsics.checkNotNullParameter:(Ljava/lang/Object;Ljava/lang/String;)V
         6: aload_1
         7: ldc           #251                // String path
         9: invokestatic  #15                 // Method kotlin/jvm/internal/Intrinsics.checkNotNullParameter:(Ljava/lang/Object;Ljava/lang/String;)V
        12: aload_0
        13: checkcast     #19                 // class android/content/Context
        16: aload_1
        17: invokestatic  #308                // Method org/fossify/commons/extensions/Context_storage_sdk30Kt.isAccessibleWithSAFSdk30:(Landroid/content/Context;Ljava/lang/String;)Z
        20: ifeq          50
        23: aload_0
        24: checkcast     #19                 // class android/content/Context
        27: aload_1
        28: invokestatic  #311                // Method org/fossify/commons/extensions/Context_storage_sdk30Kt.hasProperStoredFirstParentUri:(Landroid/content/Context;Ljava/lang/String;)Z
        31: ifne          50
        34: aload_0
        35: aload_0
        36: iload_2
        37: aload_1
        38: invokedynamic #319,  0            // InvokeDynamic #3:run:(Lorg/fossify/commons/activities/BaseSimpleActivity;ZLjava/lang/String;)Ljava/lang/Runnable;
        43: invokevirtual #296                // Method org/fossify/commons/activities/BaseSimpleActivity.runOnUiThread:(Ljava/lang/Runnable;)V
        46: iconst_1
        47: goto          51
        50: iconst_0
        51: ireturn

  public static boolean isShowingSAFDialogSdk30$default(org.fossify.commons.activities.BaseSimpleActivity, java.lang.String, boolean, int, java.lang.Object);
    Code:
         0: iload_3
         1: iconst_2
         2: iand
         3: ifeq          8
         6: iconst_1
         7: istore_2
         8: aload_0
         9: aload_1
        10: iload_2
        11: invokestatic  #326                // Method isShowingSAFDialogSdk30:(Lorg/fossify/commons/activities/BaseSimpleActivity;Ljava/lang/String;Z)Z
        14: ireturn

  public static final boolean isShowingSAFCreateDocumentDialogSdk30(org.fossify.commons.activities.BaseSimpleActivity, java.lang.String);
    Code:
         0: aload_0
         1: ldc           #9                  // String <this>
         3: invokestatic  #15                 // Method kotlin/jvm/internal/Intrinsics.checkNotNullParameter:(Ljava/lang/Object;Ljava/lang/String;)V
         6: aload_1
         7: ldc           #251                // String path
         9: invokestatic  #15                 // Method kotlin/jvm/internal/Intrinsics.checkNotNullParameter:(Ljava/lang/Object;Ljava/lang/String;)V
        12: aload_0
        13: checkcast     #19                 // class android/content/Context
        16: aload_1
        17: invokestatic  #392                // Method org/fossify/commons/extensions/Context_storage_sdk30Kt.hasProperStoredDocumentUriSdk30:(Landroid/content/Context;Ljava/lang/String;)Z
        20: ifne          38
        23: aload_0
        24: aload_0
        25: aload_1
        26: invokedynamic #397,  0            // InvokeDynamic #4:run:(Lorg/fossify/commons/activities/BaseSimpleActivity;Ljava/lang/String;)Ljava/lang/Runnable;
        31: invokevirtual #296                // Method org/fossify/commons/activities/BaseSimpleActivity.runOnUiThread:(Ljava/lang/Runnable;)V
        34: iconst_1
        35: goto          39
        38: iconst_0
        39: ireturn

  public static final boolean isShowingAndroidSAFDialog(org.fossify.commons.activities.BaseSimpleActivity, java.lang.String, boolean);
    Code:
         0: aload_0
         1: ldc           #9                  // String <this>
         3: invokestatic  #15                 // Method kotlin/jvm/internal/Intrinsics.checkNotNullParameter:(Ljava/lang/Object;Ljava/lang/String;)V
         6: aload_1
         7: ldc           #251                // String path
         9: invokestatic  #15                 // Method kotlin/jvm/internal/Intrinsics.checkNotNullParameter:(Ljava/lang/Object;Ljava/lang/String;)V
        12: aload_0
        13: checkcast     #19                 // class android/content/Context
        16: aload_1
        17: invokestatic  #402                // Method org/fossify/commons/extensions/Context_storageKt.isRestrictedSAFOnlyRoot:(Landroid/content/Context;Ljava/lang/String;)Z
        20: ifeq          77
        23: aload_0
        24: checkcast     #19                 // class android/content/Context
        27: aload_1
        28: invokestatic  #406                // Method org/fossify/commons/extensions/Context_storageKt.getAndroidTreeUri:(Landroid/content/Context;Ljava/lang/String;)Ljava/lang/String;
        31: checkcast     #124                // class java/lang/CharSequence
        34: invokeinterface #269,  1          // InterfaceMethod java/lang/CharSequence.length:()I
        39: ifne          46
        42: iconst_1
        43: goto          47
        46: iconst_0
        47: ifne          61
        50: aload_0
        51: checkcast     #19                 // class android/content/Context
        54: aload_1
        55: invokestatic  #409                // Method org/fossify/commons/extensions/Context_storageKt.hasProperStoredAndroidTreeUri:(Landroid/content/Context;Ljava/lang/String;)Z
        58: ifne          77
        61: aload_0
        62: aload_0
        63: iload_2
        64: aload_1
        65: invokedynamic #414,  0            // InvokeDynamic #5:run:(Lorg/fossify/commons/activities/BaseSimpleActivity;ZLjava/lang/String;)Ljava/lang/Runnable;
        70: invokevirtual #296                // Method org/fossify/commons/activities/BaseSimpleActivity.runOnUiThread:(Ljava/lang/Runnable;)V
        73: iconst_1
        74: goto          78
        77: iconst_0
        78: ireturn

  public static boolean isShowingAndroidSAFDialog$default(org.fossify.commons.activities.BaseSimpleActivity, java.lang.String, boolean, int, java.lang.Object);
    Code:
         0: iload_3
         1: iconst_2
         2: iand
         3: ifeq          8
         6: iconst_0
         7: istore_2
         8: aload_0
         9: aload_1
        10: iload_2
        11: invokestatic  #419                // Method isShowingAndroidSAFDialog:(Lorg/fossify/commons/activities/BaseSimpleActivity;Ljava/lang/String;Z)Z
        14: ireturn

  public static final void launchSystemFileManager(org.fossify.commons.activities.BaseSimpleActivity, android.net.Uri);
    Code:
         0: aload_0
         1: ldc           #9                  // String <this>
         3: invokestatic  #15                 // Method kotlin/jvm/internal/Intrinsics.checkNotNullParameter:(Ljava/lang/Object;Ljava/lang/String;)V
         6: aload_1
         7: ldc_w         #423                // String uri
        10: invokestatic  #15                 // Method kotlin/jvm/internal/Intrinsics.checkNotNullParameter:(Ljava/lang/Object;Ljava/lang/String;)V
        13: aload_0
        14: aload_1
        15: ldc_w         #425                // String android.intent.action.VIEW
        18: new           #148                // class android/content/ComponentName
        21: dup
        22: ldc_w         #427                // String com.google.android.documentsui
        25: ldc_w         #429                // String com.android.documentsui.files.FilesActivity
        28: invokespecial #152                // Method android/content/ComponentName."<init>":(Ljava/lang/String;Ljava/lang/String;)V
        31: invokestatic  #433                // Method startIntentForUriAction:(Lorg/fossify/commons/activities/BaseSimpleActivity;Landroid/net/Uri;Ljava/lang/String;Landroid/content/ComponentName;)Z
        34: ifne          121
        37: aload_0
        38: aload_1
        39: ldc_w         #425                // String android.intent.action.VIEW
        42: new           #148                // class android/content/ComponentName
        45: dup
        46: ldc_w         #435                // String com.android.documentsui
        49: ldc_w         #429                // String com.android.documentsui.files.FilesActivity
        52: invokespecial #152                // Method android/content/ComponentName."<init>":(Ljava/lang/String;Ljava/lang/String;)V
        55: invokestatic  #433                // Method startIntentForUriAction:(Lorg/fossify/commons/activities/BaseSimpleActivity;Landroid/net/Uri;Ljava/lang/String;Landroid/content/ComponentName;)Z
        58: ifne          121
        61: aload_0
        62: aload_1
        63: ldc_w         #425                // String android.intent.action.VIEW
        66: new           #148                // class android/content/ComponentName
        69: dup
        70: ldc_w         #435                // String com.android.documentsui
        73: ldc_w         #437                // String com.android.documentsui.FilesActivity
        76: invokespecial #152                // Method android/content/ComponentName."<init>":(Ljava/lang/String;Ljava/lang/String;)V
        79: invokestatic  #433                // Method startIntentForUriAction:(Lorg/fossify/commons/activities/BaseSimpleActivity;Landroid/net/Uri;Ljava/lang/String;Landroid/content/ComponentName;)Z
        82: ifne          121
        85: aload_0
        86: aload_1
        87: ldc_w         #425                // String android.intent.action.VIEW
        90: aconst_null
        91: invokestatic  #433                // Method startIntentForUriAction:(Lorg/fossify/commons/activities/BaseSimpleActivity;Landroid/net/Uri;Ljava/lang/String;Landroid/content/ComponentName;)Z
        94: ifne          121
        97: aload_0
        98: aload_1
        99: ldc_w         #439                // String android.provider.action.BROWSE
       102: aconst_null
       103: invokestatic  #433                // Method startIntentForUriAction:(Lorg/fossify/commons/activities/BaseSimpleActivity;Landroid/net/Uri;Ljava/lang/String;Landroid/content/ComponentName;)Z
       106: ifne          121
       109: aload_0
       110: aload_1
       111: ldc_w         #441                // String android.provider.action.BROWSE_DOCUMENT_ROOT
       114: aconst_null
       115: invokestatic  #433                // Method startIntentForUriAction:(Lorg/fossify/commons/activities/BaseSimpleActivity;Landroid/net/Uri;Ljava/lang/String;Landroid/content/ComponentName;)Z
       118: ifeq          122
       121: return
       122: aload_0
       123: checkcast     #19                 // class android/content/Context
       126: getstatic     #444                // Field org/fossify/commons/R$string.confirm_storage_access_restricted_text_not_found:I
       129: iconst_0
       130: iconst_2
       131: aconst_null
       132: invokestatic  #383                // Method org/fossify/commons/extensions/ContextKt.toast$default:(Landroid/content/Context;IIILjava/lang/Object;)V
       135: return

  public static final boolean startIntentForUriAction(org.fossify.commons.activities.BaseSimpleActivity, android.net.Uri, java.lang.String, android.content.ComponentName);
    Code:
         0: aload_0
         1: ldc           #9                  // String <this>
         3: invokestatic  #15                 // Method kotlin/jvm/internal/Intrinsics.checkNotNullParameter:(Ljava/lang/Object;Ljava/lang/String;)V
         6: aload_1
         7: ldc_w         #423                // String uri
        10: invokestatic  #15                 // Method kotlin/jvm/internal/Intrinsics.checkNotNullParameter:(Ljava/lang/Object;Ljava/lang/String;)V
        13: aload_2
        14: ldc_w         #449                // String action
        17: invokestatic  #15                 // Method kotlin/jvm/internal/Intrinsics.checkNotNullParameter:(Ljava/lang/Object;Ljava/lang/String;)V
        20: new           #333                // class android/content/Intent
        23: dup
        24: aload_2
        25: aload_1
        26: invokespecial #452                // Method android/content/Intent."<init>":(Ljava/lang/String;Landroid/net/Uri;)V
        29: astore        4
        31: aload_3
        32: ifnull        42
        35: aload         4
        37: aload_3
        38: invokevirtual #456                // Method android/content/Intent.setComponent:(Landroid/content/ComponentName;)Landroid/content/Intent;
        41: pop
        42: aload         4
        44: ldc_w         #457                // int 268435456
        47: invokevirtual #461                // Method android/content/Intent.addFlags:(I)Landroid/content/Intent;
        50: pop
        51: nop
        52: aload_0
        53: aload         4
        55: invokevirtual #465                // Method org/fossify/commons/activities/BaseSimpleActivity.startActivity:(Landroid/content/Intent;)V
        58: iconst_1
        59: istore        5
        61: goto          74
        64: astore        6
        66: aload         6
        68: invokevirtual #468                // Method java/lang/Exception.printStackTrace:()V
        71: iconst_0
        72: istore        5
        74: iload         5
        76: ireturn
      Exception table:
         from    to  target type
            51    61    64   Class java/lang/Exception

  public static final boolean isShowingOTGDialog(org.fossify.commons.activities.BaseSimpleActivity, java.lang.String);
    Code:
         0: aload_0
         1: ldc           #9                  // String <this>
         3: invokestatic  #15                 // Method kotlin/jvm/internal/Intrinsics.checkNotNullParameter:(Ljava/lang/Object;Ljava/lang/String;)V
         6: aload_1
         7: ldc           #251                // String path
         9: invokestatic  #15                 // Method kotlin/jvm/internal/Intrinsics.checkNotNullParameter:(Ljava/lang/Object;Ljava/lang/String;)V
        12: invokestatic  #256                // Method org/fossify/commons/helpers/ConstantsKt.isRPlus:()Z
        15: ifne          78
        18: aload_0
        19: checkcast     #19                 // class android/content/Context
        22: aload_1
        23: invokestatic  #476                // Method org/fossify/commons/extensions/Context_storageKt.isPathOnOTG:(Landroid/content/Context;Ljava/lang/String;)Z
        26: ifeq          78
        29: aload_0
        30: checkcast     #19                 // class android/content/Context
        33: invokestatic  #25                 // Method org/fossify/commons/extensions/ContextKt.getBaseConfig:(Landroid/content/Context;)Lorg/fossify/commons/helpers/BaseConfig;
        36: invokevirtual #479                // Method org/fossify/commons/helpers/BaseConfig.getOTGTreeUri:()Ljava/lang/String;
        39: checkcast     #124                // class java/lang/CharSequence
        42: invokeinterface #269,  1          // InterfaceMethod java/lang/CharSequence.length:()I
        47: ifne          54
        50: iconst_1
        51: goto          55
        54: iconst_0
        55: ifne          69
        58: aload_0
        59: checkcast     #19                 // class android/content/Context
        62: iconst_1
        63: invokestatic  #273                // Method org/fossify/commons/extensions/Context_storageKt.hasProperStoredTreeUri:(Landroid/content/Context;Z)Z
        66: ifne          78
        69: aload_0
        70: aload_1
        71: invokestatic  #482                // Method showOTGPermissionDialog:(Lorg/fossify/commons/activities/BaseSimpleActivity;Ljava/lang/String;)V
        74: iconst_1
        75: goto          79
        78: iconst_0
        79: ireturn

  public static final void showOTGPermissionDialog(org.fossify.commons.activities.BaseSimpleActivity, java.lang.String);
    Code:
         0: aload_0
         1: ldc           #9                  // String <this>
         3: invokestatic  #15                 // Method kotlin/jvm/internal/Intrinsics.checkNotNullParameter:(Ljava/lang/Object;Ljava/lang/String;)V
         6: aload_1
         7: ldc           #251                // String path
         9: invokestatic  #15                 // Method kotlin/jvm/internal/Intrinsics.checkNotNullParameter:(Ljava/lang/Object;Ljava/lang/String;)V
        12: aload_0
        13: aload_0
        14: aload_1
        15: invokedynamic #488,  0            // InvokeDynamic #6:run:(Lorg/fossify/commons/activities/BaseSimpleActivity;Ljava/lang/String;)Ljava/lang/Runnable;
        20: invokevirtual #296                // Method org/fossify/commons/activities/BaseSimpleActivity.runOnUiThread:(Ljava/lang/Runnable;)V
        23: return

  public static final void launchPurchaseThankYouIntent(android.app.Activity);
    Code:
         0: aload_0
         1: ldc           #9                  // String <this>
         3: invokestatic  #15                 // Method kotlin/jvm/internal/Intrinsics.checkNotNullParameter:(Ljava/lang/Object;Ljava/lang/String;)V
         6: aload_0
         7: invokestatic  #493                // Method hideKeyboard:(Landroid/app/Activity;)V
        10: aload_0
        11: aload_0
        12: getstatic     #496                // Field org/fossify/commons/R$string.thank_you_url:I
        15: invokevirtual #500                // Method android/app/Activity.getString:(I)Ljava/lang/String;
        18: dup
        19: ldc_w         #502                // String getString(...)
        22: invokestatic  #505                // Method kotlin/jvm/internal/Intrinsics.checkNotNullExpressionValue:(Ljava/lang/Object;Ljava/lang/String;)V
        25: invokestatic  #508                // Method launchViewIntent:(Landroid/app/Activity;Ljava/lang/String;)V
        28: return

  public static final void launchUpgradeToProIntent(android.app.Activity);
    Code:
         0: aload_0
         1: ldc           #9                  // String <this>
         3: invokestatic  #15                 // Method kotlin/jvm/internal/Intrinsics.checkNotNullParameter:(Ljava/lang/Object;Ljava/lang/String;)V
         6: aload_0
         7: invokestatic  #493                // Method hideKeyboard:(Landroid/app/Activity;)V
        10: nop
        11: aload_0
        12: aload_0
        13: checkcast     #19                 // class android/content/Context
        16: invokestatic  #25                 // Method org/fossify/commons/extensions/ContextKt.getBaseConfig:(Landroid/content/Context;)Lorg/fossify/commons/helpers/BaseConfig;
        19: invokevirtual #120                // Method org/fossify/commons/helpers/BaseConfig.getAppId:()Ljava/lang/String;
        22: ldc           #122                // String .debug
        24: checkcast     #124                // class java/lang/CharSequence
        27: invokestatic  #130                // Method kotlin/text/StringsKt.removeSuffix:(Ljava/lang/String;Ljava/lang/CharSequence;)Ljava/lang/String;
        30: invokedynamic #513,  0            // InvokeDynamic #7:makeConcatWithConstants:(Ljava/lang/String;)Ljava/lang/String;
        35: invokestatic  #508                // Method launchViewIntent:(Landroid/app/Activity;Ljava/lang/String;)V
        38: goto          53
        41: astore_1
        42: aload_0
        43: aload_0
        44: checkcast     #19                 // class android/content/Context
        47: invokestatic  #516                // Method org/fossify/commons/extensions/ContextKt.getStoreUrl:(Landroid/content/Context;)Ljava/lang/String;
        50: invokestatic  #508                // Method launchViewIntent:(Landroid/app/Activity;Ljava/lang/String;)V
        53: return
      Exception table:
         from    to  target type
            10    38    41   Class java/lang/Exception

  public static final void launchMoreAppsFromUsIntent(android.app.Activity);
    Code:
         0: aload_0
         1: ldc           #9                  // String <this>
         3: invokestatic  #15                 // Method kotlin/jvm/internal/Intrinsics.checkNotNullParameter:(Ljava/lang/Object;Ljava/lang/String;)V
         6: aload_0
         7: ldc_w         #521                // String https://play.google.com/store/apps/dev?id=7297838378654322558
        10: invokestatic  #508                // Method launchViewIntent:(Landroid/app/Activity;Ljava/lang/String;)V
        13: return

  public static final void launchViewIntent(android.app.Activity, int);
    Code:
         0: aload_0
         1: ldc           #9                  // String <this>
         3: invokestatic  #15                 // Method kotlin/jvm/internal/Intrinsics.checkNotNullParameter:(Ljava/lang/Object;Ljava/lang/String;)V
         6: aload_0
         7: aload_0
         8: iload_1
         9: invokevirtual #500                // Method android/app/Activity.getString:(I)Ljava/lang/String;
        12: dup
        13: ldc_w         #502                // String getString(...)
        16: invokestatic  #505                // Method kotlin/jvm/internal/Intrinsics.checkNotNullExpressionValue:(Ljava/lang/Object;Ljava/lang/String;)V
        19: invokestatic  #508                // Method launchViewIntent:(Landroid/app/Activity;Ljava/lang/String;)V
        22: return

  public static final void launchViewIntent(android.app.Activity, java.lang.String);
    Code:
         0: aload_0
         1: ldc           #9                  // String <this>
         3: invokestatic  #15                 // Method kotlin/jvm/internal/Intrinsics.checkNotNullParameter:(Ljava/lang/Object;Ljava/lang/String;)V
         6: aload_1
         7: ldc_w         #527                // String url
        10: invokestatic  #15                 // Method kotlin/jvm/internal/Intrinsics.checkNotNullParameter:(Ljava/lang/Object;Ljava/lang/String;)V
        13: aload_0
        14: invokestatic  #493                // Method hideKeyboard:(Landroid/app/Activity;)V
        17: aload_1
        18: aload_0
        19: invokedynamic #539,  0            // InvokeDynamic #8:invoke:(Ljava/lang/String;Landroid/app/Activity;)Lkotlin/jvm/functions/Function0;
        24: invokestatic  #543                // Method org/fossify/commons/helpers/ConstantsKt.ensureBackgroundThread:(Lkotlin/jvm/functions/Function0;)V
        27: return

  public static final void launchAppRatingPage(android.app.Activity);
    Code:
         0: aload_0
         1: ldc           #9                  // String <this>
         3: invokestatic  #15                 // Method kotlin/jvm/internal/Intrinsics.checkNotNullParameter:(Ljava/lang/Object;Ljava/lang/String;)V
         6: aload_0
         7: invokestatic  #493                // Method hideKeyboard:(Landroid/app/Activity;)V
        10: nop
        11: aload_0
        12: aload_0
        13: invokevirtual #227                // Method android/app/Activity.getPackageName:()Ljava/lang/String;
        16: dup
        17: ldc_w         #546                // String getPackageName(...)
        20: invokestatic  #505                // Method kotlin/jvm/internal/Intrinsics.checkNotNullExpressionValue:(Ljava/lang/Object;Ljava/lang/String;)V
        23: ldc           #122                // String .debug
        25: checkcast     #124                // class java/lang/CharSequence
        28: invokestatic  #130                // Method kotlin/text/StringsKt.removeSuffix:(Ljava/lang/String;Ljava/lang/CharSequence;)Ljava/lang/String;
        31: invokedynamic #549,  0            // InvokeDynamic #9:makeConcatWithConstants:(Ljava/lang/String;)Ljava/lang/String;
        36: invokestatic  #508                // Method launchViewIntent:(Landroid/app/Activity;Ljava/lang/String;)V
        39: goto          54
        42: astore_1
        43: aload_0
        44: aload_0
        45: checkcast     #19                 // class android/content/Context
        48: invokestatic  #516                // Method org/fossify/commons/extensions/ContextKt.getStoreUrl:(Landroid/content/Context;)Ljava/lang/String;
        51: invokestatic  #508                // Method launchViewIntent:(Landroid/app/Activity;Ljava/lang/String;)V
        54: return
      Exception table:
         from    to  target type
            10    39    42   Class android/content/ActivityNotFoundException

  public static final void sharePathIntent(android.app.Activity, java.lang.String, java.lang.String);
    Code:
         0: aload_0
         1: ldc           #9                  // String <this>
         3: invokestatic  #15                 // Method kotlin/jvm/internal/Intrinsics.checkNotNullParameter:(Ljava/lang/Object;Ljava/lang/String;)V
         6: aload_1
         7: ldc           #251                // String path
         9: invokestatic  #15                 // Method kotlin/jvm/internal/Intrinsics.checkNotNullParameter:(Ljava/lang/Object;Ljava/lang/String;)V
        12: aload_2
        13: ldc_w         #554                // String applicationId
        16: invokestatic  #15                 // Method kotlin/jvm/internal/Intrinsics.checkNotNullParameter:(Ljava/lang/Object;Ljava/lang/String;)V
        19: aload_0
        20: aload_1
        21: aload_2
        22: invokedynamic #562,  0            // InvokeDynamic #10:invoke:(Landroid/app/Activity;Ljava/lang/String;Ljava/lang/String;)Lkotlin/jvm/functions/Function0;
        27: invokestatic  #543                // Method org/fossify/commons/helpers/ConstantsKt.ensureBackgroundThread:(Lkotlin/jvm/functions/Function0;)V
        30: return

  public static final void sharePathsIntent(android.app.Activity, java.util.List<java.lang.String>, java.lang.String);
    Code:
         0: aload_0
         1: ldc           #9                  // String <this>
         3: invokestatic  #15                 // Method kotlin/jvm/internal/Intrinsics.checkNotNullParameter:(Ljava/lang/Object;Ljava/lang/String;)V
         6: aload_1
         7: ldc_w         #568                // String paths
        10: invokestatic  #15                 // Method kotlin/jvm/internal/Intrinsics.checkNotNullParameter:(Ljava/lang/Object;Ljava/lang/String;)V
        13: aload_2
        14: ldc_w         #554                // String applicationId
        17: invokestatic  #15                 // Method kotlin/jvm/internal/Intrinsics.checkNotNullParameter:(Ljava/lang/Object;Ljava/lang/String;)V
        20: aload_1
        21: aload_0
        22: aload_2
        23: invokedynamic #576,  0            // InvokeDynamic #11:invoke:(Ljava/util/List;Landroid/app/Activity;Ljava/lang/String;)Lkotlin/jvm/functions/Function0;
        28: invokestatic  #543                // Method org/fossify/commons/helpers/ConstantsKt.ensureBackgroundThread:(Lkotlin/jvm/functions/Function0;)V
        31: return

  public static final void setAsIntent(android.app.Activity, java.lang.String, java.lang.String);
    Code:
         0: aload_0
         1: ldc           #9                  // String <this>
         3: invokestatic  #15                 // Method kotlin/jvm/internal/Intrinsics.checkNotNullParameter:(Ljava/lang/Object;Ljava/lang/String;)V
         6: aload_1
         7: ldc           #251                // String path
         9: invokestatic  #15                 // Method kotlin/jvm/internal/Intrinsics.checkNotNullParameter:(Ljava/lang/Object;Ljava/lang/String;)V
        12: aload_2
        13: ldc_w         #554                // String applicationId
        16: invokestatic  #15                 // Method kotlin/jvm/internal/Intrinsics.checkNotNullParameter:(Ljava/lang/Object;Ljava/lang/String;)V
        19: aload_0
        20: aload_1
        21: aload_2
        22: invokedynamic #584,  0            // InvokeDynamic #12:invoke:(Landroid/app/Activity;Ljava/lang/String;Ljava/lang/String;)Lkotlin/jvm/functions/Function0;
        27: invokestatic  #543                // Method org/fossify/commons/helpers/ConstantsKt.ensureBackgroundThread:(Lkotlin/jvm/functions/Function0;)V
        30: return

  public static final void shareTextIntent(android.app.Activity, java.lang.String);
    Code:
         0: aload_0
         1: ldc           #9                  // String <this>
         3: invokestatic  #15                 // Method kotlin/jvm/internal/Intrinsics.checkNotNullParameter:(Ljava/lang/Object;Ljava/lang/String;)V
         6: aload_1
         7: ldc_w         #588                // String text
        10: invokestatic  #15                 // Method kotlin/jvm/internal/Intrinsics.checkNotNullParameter:(Ljava/lang/Object;Ljava/lang/String;)V
        13: aload_1
        14: aload_0
        15: invokedynamic #593,  0            // InvokeDynamic #13:invoke:(Ljava/lang/String;Landroid/app/Activity;)Lkotlin/jvm/functions/Function0;
        20: invokestatic  #543                // Method org/fossify/commons/helpers/ConstantsKt.ensureBackgroundThread:(Lkotlin/jvm/functions/Function0;)V
        23: return

  public static final void openEditorIntent(android.app.Activity, java.lang.String, boolean, java.lang.String);
    Code:
         0: aload_0
         1: ldc           #9                  // String <this>
         3: invokestatic  #15                 // Method kotlin/jvm/internal/Intrinsics.checkNotNullParameter:(Ljava/lang/Object;Ljava/lang/String;)V
         6: aload_1
         7: ldc           #251                // String path
         9: invokestatic  #15                 // Method kotlin/jvm/internal/Intrinsics.checkNotNullParameter:(Ljava/lang/Object;Ljava/lang/String;)V
        12: aload_3
        13: ldc_w         #554                // String applicationId
        16: invokestatic  #15                 // Method kotlin/jvm/internal/Intrinsics.checkNotNullParameter:(Ljava/lang/Object;Ljava/lang/String;)V
        19: aload_0
        20: aload_1
        21: aload_3
        22: iload_2
        23: invokedynamic #604,  0            // InvokeDynamic #14:invoke:(Landroid/app/Activity;Ljava/lang/String;Ljava/lang/String;Z)Lkotlin/jvm/functions/Function0;
        28: invokestatic  #543                // Method org/fossify/commons/helpers/ConstantsKt.ensureBackgroundThread:(Lkotlin/jvm/functions/Function0;)V
        31: return

  public static final void openPathIntent(android.app.Activity, java.lang.String, boolean, java.lang.String, java.lang.String, java.util.HashMap<java.lang.String, java.lang.Boolean>);
    Code:
         0: aload_0
         1: ldc           #9                  // String <this>
         3: invokestatic  #15                 // Method kotlin/jvm/internal/Intrinsics.checkNotNullParameter:(Ljava/lang/Object;Ljava/lang/String;)V
         6: aload_1
         7: ldc           #251                // String path
         9: invokestatic  #15                 // Method kotlin/jvm/internal/Intrinsics.checkNotNullParameter:(Ljava/lang/Object;Ljava/lang/String;)V
        12: aload_3
        13: ldc_w         #554                // String applicationId
        16: invokestatic  #15                 // Method kotlin/jvm/internal/Intrinsics.checkNotNullParameter:(Ljava/lang/Object;Ljava/lang/String;)V
        19: aload         4
        21: ldc_w         #611                // String forceMimeType
        24: invokestatic  #15                 // Method kotlin/jvm/internal/Intrinsics.checkNotNullParameter:(Ljava/lang/Object;Ljava/lang/String;)V
        27: aload         5
        29: ldc_w         #613                // String extras
        32: invokestatic  #15                 // Method kotlin/jvm/internal/Intrinsics.checkNotNullParameter:(Ljava/lang/Object;Ljava/lang/String;)V
        35: aload_0
        36: aload_1
        37: aload_3
        38: aload         4
        40: aload         5
        42: iload_2
        43: invokedynamic #621,  0            // InvokeDynamic #15:invoke:(Landroid/app/Activity;Ljava/lang/String;Ljava/lang/String;Ljava/lang/String;Ljava/util/HashMap;Z)Lkotlin/jvm/functions/Function0;
        48: invokestatic  #543                // Method org/fossify/commons/helpers/ConstantsKt.ensureBackgroundThread:(Lkotlin/jvm/functions/Function0;)V
        51: return

  public static void openPathIntent$default(android.app.Activity, java.lang.String, boolean, java.lang.String, java.lang.String, java.util.HashMap, int, java.lang.Object);
    Code:
         0: iload         6
         2: bipush        8
         4: iand
         5: ifeq          13
         8: ldc_w         #627                // String
        11: astore        4
        13: iload         6
        15: bipush        16
        17: iand
        18: ifeq          30
        21: new           #629                // class java/util/HashMap
        24: dup
        25: invokespecial #631                // Method java/util/HashMap."<init>":()V
        28: astore        5
        30: aload_0
        31: aload_1
        32: iload_2
        33: aload_3
        34: aload         4
        36: aload         5
        38: invokestatic  #633                // Method openPathIntent:(Landroid/app/Activity;Ljava/lang/String;ZLjava/lang/String;Ljava/lang/String;Ljava/util/HashMap;)V
        41: return

  public static final void launchViewContactIntent(android.app.Activity, android.net.Uri);
    Code:
         0: aload_0
         1: ldc           #9                  // String <this>
         3: invokestatic  #15                 // Method kotlin/jvm/internal/Intrinsics.checkNotNullParameter:(Ljava/lang/Object;Ljava/lang/String;)V
         6: aload_1
         7: ldc_w         #423                // String uri
        10: invokestatic  #15                 // Method kotlin/jvm/internal/Intrinsics.checkNotNullParameter:(Ljava/lang/Object;Ljava/lang/String;)V
        13: new           #333                // class android/content/Intent
        16: dup
        17: invokespecial #636                // Method android/content/Intent."<init>":()V
        20: astore_2
        21: aload_2
        22: astore_3
        23: iconst_0
        24: istore        4
        26: aload_3
        27: ldc_w         #638                // String android.provider.action.QUICK_CONTACT
        30: invokevirtual #641                // Method android/content/Intent.setAction:(Ljava/lang/String;)Landroid/content/Intent;
        33: pop
        34: aload_3
        35: aload_1
        36: invokevirtual #645                // Method android/content/Intent.setData:(Landroid/net/Uri;)Landroid/content/Intent;
        39: pop
        40: aload_0
        41: checkcast     #19                 // class android/content/Context
        44: aload_3
        45: invokestatic  #649                // Method org/fossify/commons/extensions/ContextKt.launchActivityIntent:(Landroid/content/Context;Landroid/content/Intent;)V
        48: nop
        49: nop
        50: return

  public static final void launchCallIntent(org.fossify.commons.activities.BaseSimpleActivity, java.lang.String, android.telecom.PhoneAccountHandle);
    Code:
         0: aload_0
         1: ldc           #9                  // String <this>
         3: invokestatic  #15                 // Method kotlin/jvm/internal/Intrinsics.checkNotNullParameter:(Ljava/lang/Object;Ljava/lang/String;)V
         6: aload_1
         7: ldc_w         #656                // String recipient
        10: invokestatic  #15                 // Method kotlin/jvm/internal/Intrinsics.checkNotNullParameter:(Ljava/lang/Object;Ljava/lang/String;)V
        13: aload_0
        14: bipush        9
        16: aload_1
        17: aload_2
        18: aload_0
        19: invokedynamic #668,  0            // InvokeDynamic #16:invoke:(Ljava/lang/String;Landroid/telecom/PhoneAccountHandle;Lorg/fossify/commons/activities/BaseSimpleActivity;)Lkotlin/jvm/functions/Function1;
        24: invokevirtual #672                // Method org/fossify/commons/activities/BaseSimpleActivity.handlePermission:(ILkotlin/jvm/functions/Function1;)V
        27: return

  public static void launchCallIntent$default(org.fossify.commons.activities.BaseSimpleActivity, java.lang.String, android.telecom.PhoneAccountHandle, int, java.lang.Object);
    Code:
         0: iload_3
         1: iconst_2
         2: iand
         3: ifeq          8
         6: aconst_null
         7: astore_2
         8: aload_0
         9: aload_1
        10: aload_2
        11: invokestatic  #679                // Method launchCallIntent:(Lorg/fossify/commons/activities/BaseSimpleActivity;Ljava/lang/String;Landroid/telecom/PhoneAccountHandle;)V
        14: return

  public static final void launchSendSMSIntent(android.app.Activity, java.lang.String);
    Code:
         0: aload_0
         1: ldc           #9                  // String <this>
         3: invokestatic  #15                 // Method kotlin/jvm/internal/Intrinsics.checkNotNullParameter:(Ljava/lang/Object;Ljava/lang/String;)V
         6: aload_1
         7: ldc_w         #656                // String recipient
        10: invokestatic  #15                 // Method kotlin/jvm/internal/Intrinsics.checkNotNullParameter:(Ljava/lang/Object;Ljava/lang/String;)V
        13: new           #333                // class android/content/Intent
        16: dup
        17: ldc_w         #682                // String android.intent.action.SENDTO
        20: invokespecial #337                // Method android/content/Intent."<init>":(Ljava/lang/String;)V
        23: astore_2
        24: aload_2
        25: astore_3
        26: iconst_0
        27: istore        4
        29: aload_3
        30: ldc_w         #684                // String smsto
        33: aload_1
        34: aconst_null
        35: invokestatic  #690                // Method android/net/Uri.fromParts:(Ljava/lang/String;Ljava/lang/String;Ljava/lang/String;)Landroid/net/Uri;
        38: invokevirtual #645                // Method android/content/Intent.setData:(Landroid/net/Uri;)Landroid/content/Intent;
        41: pop
        42: aload_0
        43: checkcast     #19                 // class android/content/Context
        46: aload_3
        47: invokestatic  #649                // Method org/fossify/commons/extensions/ContextKt.launchActivityIntent:(Landroid/content/Context;Landroid/content/Intent;)V
        50: nop
        51: nop
        52: return

  public static final void showLocationOnMap(android.app.Activity, java.lang.String);
    Code:
         0: aload_0
         1: ldc           #9                  // String <this>
         3: invokestatic  #15                 // Method kotlin/jvm/internal/Intrinsics.checkNotNullParameter:(Ljava/lang/Object;Ljava/lang/String;)V
         6: aload_1
         7: ldc_w         #696                // String coordinates
        10: invokestatic  #15                 // Method kotlin/jvm/internal/Intrinsics.checkNotNullParameter:(Ljava/lang/Object;Ljava/lang/String;)V
        13: aload_1
        14: ldc_w         #698                // String
        17: ldc_w         #627                // String
        20: iconst_0
        21: iconst_4
        22: aconst_null
        23: invokestatic  #702                // Method kotlin/text/StringsKt.replace$default:(Ljava/lang/String;Ljava/lang/String;Ljava/lang/String;ZILjava/lang/Object;)Ljava/lang/String;
        26: invokedynamic #705,  0            // InvokeDynamic #17:makeConcatWithConstants:(Ljava/lang/String;)Ljava/lang/String;
        31: astore_2
        32: aload_1
        33: invokestatic  #708                // Method android/net/Uri.encode:(Ljava/lang/String;)Ljava/lang/String;
        36: astore_3
        37: aload_2
        38: aload_3
        39: invokedynamic #713,  0            // InvokeDynamic #18:makeConcatWithConstants:(Ljava/lang/String;Ljava/lang/String;)Ljava/lang/String;
        44: astore        4
        46: new           #333                // class android/content/Intent
        49: dup
        50: ldc_w         #425                // String android.intent.action.VIEW
        53: aload         4
        55: invokestatic  #717                // Method android/net/Uri.parse:(Ljava/lang/String;)Landroid/net/Uri;
        58: invokespecial #452                // Method android/content/Intent."<init>":(Ljava/lang/String;Landroid/net/Uri;)V
        61: astore        5
        63: aload_0
        64: checkcast     #19                 // class android/content/Context
        67: aload         5
        69: invokestatic  #649                // Method org/fossify/commons/extensions/ContextKt.launchActivityIntent:(Landroid/content/Context;Landroid/content/Intent;)V
        72: return

  public static final android.net.Uri getFinalUriFromPath(android.app.Activity, java.lang.String, java.lang.String);
    Code:
         0: aload_0
         1: ldc           #9                  // String <this>
         3: invokestatic  #15                 // Method kotlin/jvm/internal/Intrinsics.checkNotNullParameter:(Ljava/lang/Object;Ljava/lang/String;)V
         6: aload_1
         7: ldc           #251                // String path
         9: invokestatic  #15                 // Method kotlin/jvm/internal/Intrinsics.checkNotNullParameter:(Ljava/lang/Object;Ljava/lang/String;)V
        12: aload_2
        13: ldc_w         #554                // String applicationId
        16: invokestatic  #15                 // Method kotlin/jvm/internal/Intrinsics.checkNotNullParameter:(Ljava/lang/Object;Ljava/lang/String;)V
        19: nop
        20: aload_0
        21: checkcast     #19                 // class android/content/Context
        24: aload_1
        25: aload_2
        26: invokestatic  #727                // Method org/fossify/commons/extensions/ContextKt.ensurePublicUri:(Landroid/content/Context;Ljava/lang/String;Ljava/lang/String;)Landroid/net/Uri;
        29: astore        4
        31: goto          50
        34: astore        5
        36: aload_0
        37: checkcast     #19                 // class android/content/Context
        40: aload         5
        42: iconst_0
        43: iconst_2
        44: aconst_null
        45: invokestatic  #731                // Method org/fossify/commons/extensions/ContextKt.showErrorToast$default:(Landroid/content/Context;Ljava/lang/Exception;IILjava/lang/Object;)V
        48: aconst_null
        49: areturn
        50: aload         4
        52: astore_3
        53: aload_3
        54: ifnonnull     72
        57: aload_0
        58: checkcast     #19                 // class android/content/Context
        61: getstatic     #379                // Field org/fossify/commons/R$string.unknown_error_occurred:I
        64: iconst_0
        65: iconst_2
        66: aconst_null
        67: invokestatic  #383                // Method org/fossify/commons/extensions/ContextKt.toast$default:(Landroid/content/Context;IIILjava/lang/Object;)V
        70: aconst_null
        71: areturn
        72: aload_3
        73: areturn
      Exception table:
         from    to  target type
            19    31    34   Class java/lang/Exception

  public static final boolean tryGenericMimeType(android.app.Activity, android.content.Intent, java.lang.String, android.net.Uri);
    Code:
         0: aload_0
         1: ldc           #9                  // String <this>
         3: invokestatic  #15                 // Method kotlin/jvm/internal/Intrinsics.checkNotNullParameter:(Ljava/lang/Object;Ljava/lang/String;)V
         6: aload_1
         7: ldc_w         #735                // String intent
        10: invokestatic  #15                 // Method kotlin/jvm/internal/Intrinsics.checkNotNullParameter:(Ljava/lang/Object;Ljava/lang/String;)V
        13: aload_2
        14: ldc_w         #737                // String mimeType
        17: invokestatic  #15                 // Method kotlin/jvm/internal/Intrinsics.checkNotNullParameter:(Ljava/lang/Object;Ljava/lang/String;)V
        20: aload_3
        21: ldc_w         #423                // String uri
        24: invokestatic  #15                 // Method kotlin/jvm/internal/Intrinsics.checkNotNullParameter:(Ljava/lang/Object;Ljava/lang/String;)V
        27: aload_2
        28: invokestatic  #742                // Method org/fossify/commons/extensions/StringKt.getGenericMimeType:(Ljava/lang/String;)Ljava/lang/String;
        31: astore        4
        33: aload         4
        35: checkcast     #124                // class java/lang/CharSequence
        38: invokeinterface #269,  1          // InterfaceMethod java/lang/CharSequence.length:()I
        43: ifne          50
        46: iconst_1
        47: goto          51
        50: iconst_0
        51: ifeq          59
        54: ldc_w         #363                // String */*
        57: astore        4
        59: aload_1
        60: aload_3
        61: aload         4
        63: invokevirtual #746                // Method android/content/Intent.setDataAndType:(Landroid/net/Uri;Ljava/lang/String;)Landroid/content/Intent;
        66: pop
        67: nop
        68: aload_0
        69: aload_1
        70: invokevirtual #747                // Method android/app/Activity.startActivity:(Landroid/content/Intent;)V
        73: iconst_1
        74: istore        5
        76: goto          84
        79: astore        6
        81: iconst_0
        82: istore        5
        84: iload         5
        86: ireturn
      Exception table:
         from    to  target type
            67    76    79   Class java/lang/Exception

  public static final void checkWhatsNew(org.fossify.commons.activities.BaseSimpleActivity, java.util.List<org.fossify.commons.models.Release>, int);
    Code:
         0: aload_0
         1: ldc           #9                  // String <this>
         3: invokestatic  #15                 // Method kotlin/jvm/internal/Intrinsics.checkNotNullParameter:(Ljava/lang/Object;Ljava/lang/String;)V
         6: aload_1
         7: ldc_w         #754                // String releases
        10: invokestatic  #15                 // Method kotlin/jvm/internal/Intrinsics.checkNotNullParameter:(Ljava/lang/Object;Ljava/lang/String;)V
        13: aload_0
        14: checkcast     #19                 // class android/content/Context
        17: invokestatic  #25                 // Method org/fossify/commons/extensions/ContextKt.getBaseConfig:(Landroid/content/Context;)Lorg/fossify/commons/helpers/BaseConfig;
        20: invokevirtual #757                // Method org/fossify/commons/helpers/BaseConfig.getLastVersion:()I
        23: ifne          38
        26: aload_0
        27: checkcast     #19                 // class android/content/Context
        30: invokestatic  #25                 // Method org/fossify/commons/extensions/ContextKt.getBaseConfig:(Landroid/content/Context;)Lorg/fossify/commons/helpers/BaseConfig;
        33: iload_2
        34: invokevirtual #760                // Method org/fossify/commons/helpers/BaseConfig.setLastVersion:(I)V
        37: return
        38: new           #762                // class java/util/ArrayList
        41: dup
        42: invokespecial #763                // Method java/util/ArrayList."<init>":()V
        45: astore_3
        46: aload_1
        47: checkcast     #88                 // class java/lang/Iterable
        50: astore        4
        52: aload_3
        53: checkcast     #765                // class java/util/Collection
        56: astore        5
        58: iconst_0
        59: istore        6
        61: aload         4
        63: invokeinterface #92,  1           // InterfaceMethod java/lang/Iterable.iterator:()Ljava/util/Iterator;
        68: astore        7
        70: aload         7
        72: invokeinterface #97,  1           // InterfaceMethod java/util/Iterator.hasNext:()Z
        77: ifeq          138
        80: aload         7
        82: invokeinterface #101,  1          // InterfaceMethod java/util/Iterator.next:()Ljava/lang/Object;
        87: astore        8
        89: aload         8
        91: checkcast     #767                // class org/fossify/commons/models/Release
        94: astore        9
        96: iconst_0
        97: istore        10
        99: aload         9
       101: invokevirtual #770                // Method org/fossify/commons/models/Release.getId:()I
       104: aload_0
       105: checkcast     #19                 // class android/content/Context
       108: invokestatic  #25                 // Method org/fossify/commons/extensions/ContextKt.getBaseConfig:(Landroid/content/Context;)Lorg/fossify/commons/helpers/BaseConfig;
       111: invokevirtual #757                // Method org/fossify/commons/helpers/BaseConfig.getLastVersion:()I
       114: if_icmple     121
       117: iconst_1
       118: goto          122
       121: iconst_0
       122: ifeq          70
       125: aload         5
       127: aload         8
       129: invokeinterface #774,  2          // InterfaceMethod java/util/Collection.add:(Ljava/lang/Object;)Z
       134: pop
       135: goto          70
       138: nop
       139: aload_3
       140: checkcast     #765                // class java/util/Collection
       143: invokeinterface #777,  1          // InterfaceMethod java/util/Collection.isEmpty:()Z
       148: ifne          155
       151: iconst_1
       152: goto          156
       155: iconst_0
       156: ifeq          175
       159: new           #779                // class org/fossify/commons/dialogs/WhatsNewDialog
       162: dup
       163: aload_0
       164: checkcast     #63                 // class android/app/Activity
       167: aload_3
       168: checkcast     #781                // class java/util/List
       171: invokespecial #784                // Method org/fossify/commons/dialogs/WhatsNewDialog."<init>":(Landroid/app/Activity;Ljava/util/List;)V
       174: pop
       175: aload_0
       176: checkcast     #19                 // class android/content/Context
       179: invokestatic  #25                 // Method org/fossify/commons/extensions/ContextKt.getBaseConfig:(Landroid/content/Context;)Lorg/fossify/commons/helpers/BaseConfig;
       182: iload_2
       183: invokevirtual #760                // Method org/fossify/commons/helpers/BaseConfig.setLastVersion:(I)V
       186: return

  public static final void deleteFolders(org.fossify.commons.activities.BaseSimpleActivity, java.util.List<? extends org.fossify.commons.models.FileDirItem>, boolean, kotlin.jvm.functions.Function1<? super java.lang.Boolean, kotlin.Unit>);
    Code:
         0: aload_0
         1: ldc           #9                  // String <this>
         3: invokestatic  #15                 // Method kotlin/jvm/internal/Intrinsics.checkNotNullParameter:(Ljava/lang/Object;Ljava/lang/String;)V
         6: aload_1
         7: ldc_w         #801                // String folders
        10: invokestatic  #15                 // Method kotlin/jvm/internal/Intrinsics.checkNotNullParameter:(Ljava/lang/Object;Ljava/lang/String;)V
        13: aload_0
        14: aload_1
        15: iload_2
        16: aload_3
        17: invokedynamic #809,  0            // InvokeDynamic #19:invoke:(Lorg/fossify/commons/activities/BaseSimpleActivity;Ljava/util/List;ZLkotlin/jvm/functions/Function1;)Lkotlin/jvm/functions/Function0;
        22: invokestatic  #543                // Method org/fossify/commons/helpers/ConstantsKt.ensureBackgroundThread:(Lkotlin/jvm/functions/Function0;)V
        25: return

  public static void deleteFolders$default(org.fossify.commons.activities.BaseSimpleActivity, java.util.List, boolean, kotlin.jvm.functions.Function1, int, java.lang.Object);
    Code:
         0: iload         4
         2: iconst_2
         3: iand
         4: ifeq          9
         7: iconst_1
         8: istore_2
         9: iload         4
        11: iconst_4
        12: iand
        13: ifeq          18
        16: aconst_null
        17: astore_3
        18: aload_0
        19: aload_1
        20: iload_2
        21: aload_3
        22: invokestatic  #817                // Method deleteFolders:(Lorg/fossify/commons/activities/BaseSimpleActivity;Ljava/util/List;ZLkotlin/jvm/functions/Function1;)V
        25: return

  public static final void deleteFoldersBg(org.fossify.commons.activities.BaseSimpleActivity, java.util.List<? extends org.fossify.commons.models.FileDirItem>, boolean, kotlin.jvm.functions.Function1<? super java.lang.Boolean, kotlin.Unit>);
    Code:
         0: aload_0
         1: ldc           #9                  // String <this>
         3: invokestatic  #15                 // Method kotlin/jvm/internal/Intrinsics.checkNotNullParameter:(Ljava/lang/Object;Ljava/lang/String;)V
         6: aload_1
         7: ldc_w         #801                // String folders
        10: invokestatic  #15                 // Method kotlin/jvm/internal/Intrinsics.checkNotNullParameter:(Ljava/lang/Object;Ljava/lang/String;)V
        13: new           #820                // class kotlin/jvm/internal/Ref$BooleanRef
        16: dup
        17: invokespecial #821                // Method kotlin/jvm/internal/Ref$BooleanRef."<init>":()V
        20: astore        4
        22: ldc_w         #627                // String
        25: astore        5
        27: aload_1
        28: invokeinterface #822,  1          // InterfaceMethod java/util/List.iterator:()Ljava/util/Iterator;
        33: astore        6
        35: aload         6
        37: invokeinterface #97,  1           // InterfaceMethod java/util/Iterator.hasNext:()Z
        42: ifeq          111
        45: aload         6
        47: invokeinterface #101,  1          // InterfaceMethod java/util/Iterator.next:()Ljava/lang/Object;
        52: checkcast     #824                // class org/fossify/commons/models/FileDirItem
        55: astore        7
        57: aload_0
        58: checkcast     #19                 // class android/content/Context
        61: aload         7
        63: invokevirtual #827                // Method org/fossify/commons/models/FileDirItem.getPath:()Ljava/lang/String;
        66: invokestatic  #830                // Method org/fossify/commons/extensions/Context_storageKt.needsStupidWritePermissions:(Landroid/content/Context;Ljava/lang/String;)Z
        69: ifeq          35
        72: aload_0
        73: checkcast     #19                 // class android/content/Context
        76: invokestatic  #25                 // Method org/fossify/commons/extensions/ContextKt.getBaseConfig:(Landroid/content/Context;)Lorg/fossify/commons/helpers/BaseConfig;
        79: invokevirtual #266                // Method org/fossify/commons/helpers/BaseConfig.getSdTreeUri:()Ljava/lang/String;
        82: checkcast     #124                // class java/lang/CharSequence
        85: invokeinterface #269,  1          // InterfaceMethod java/lang/CharSequence.length:()I
        90: ifne          97
        93: iconst_1
        94: goto          98
        97: iconst_0
        98: ifeq          35
       101: aload         7
       103: invokevirtual #827                // Method org/fossify/commons/models/FileDirItem.getPath:()Ljava/lang/String;
       106: astore        5
       108: goto          111
       111: aload_0
       112: aload         5
       114: aload_1
       115: aload_0
       116: iload_2
       117: aload         4
       119: aload_3
       120: invokedynamic #838,  0            // InvokeDynamic #20:invoke:(Ljava/util/List;Lorg/fossify/commons/activities/BaseSimpleActivity;ZLkotlin/jvm/internal/Ref$BooleanRef;Lkotlin/jvm/functions/Function1;)Lkotlin/jvm/functions/Function1;
       125: invokevirtual #842                // Method org/fossify/commons/activities/BaseSimpleActivity.handleSAFDialog:(Ljava/lang/String;Lkotlin/jvm/functions/Function1;)Z
       128: pop
       129: return

  public static void deleteFoldersBg$default(org.fossify.commons.activities.BaseSimpleActivity, java.util.List, boolean, kotlin.jvm.functions.Function1, int, java.lang.Object);
    Code:
         0: iload         4
         2: iconst_2
         3: iand
         4: ifeq          9
         7: iconst_1
         8: istore_2
         9: iload         4
        11: iconst_4
        12: iand
        13: ifeq          18
        16: aconst_null
        17: astore_3
        18: aload_0
        19: aload_1
        20: iload_2
        21: aload_3
        22: invokestatic  #851                // Method deleteFoldersBg:(Lorg/fossify/commons/activities/BaseSimpleActivity;Ljava/util/List;ZLkotlin/jvm/functions/Function1;)V
        25: return

  public static final void deleteFolder(org.fossify.commons.activities.BaseSimpleActivity, org.fossify.commons.models.FileDirItem, boolean, kotlin.jvm.functions.Function1<? super java.lang.Boolean, kotlin.Unit>);
    Code:
         0: aload_0
         1: ldc           #9                  // String <this>
         3: invokestatic  #15                 // Method kotlin/jvm/internal/Intrinsics.checkNotNullParameter:(Ljava/lang/Object;Ljava/lang/String;)V
         6: aload_1
         7: ldc_w         #855                // String folder
        10: invokestatic  #15                 // Method kotlin/jvm/internal/Intrinsics.checkNotNullParameter:(Ljava/lang/Object;Ljava/lang/String;)V
        13: aload_0
        14: aload_1
        15: iload_2
        16: aload_3
        17: invokedynamic #863,  0            // InvokeDynamic #21:invoke:(Lorg/fossify/commons/activities/BaseSimpleActivity;Lorg/fossify/commons/models/FileDirItem;ZLkotlin/jvm/functions/Function1;)Lkotlin/jvm/functions/Function0;
        22: invokestatic  #543                // Method org/fossify/commons/helpers/ConstantsKt.ensureBackgroundThread:(Lkotlin/jvm/functions/Function0;)V
        25: return

  public static void deleteFolder$default(org.fossify.commons.activities.BaseSimpleActivity, org.fossify.commons.models.FileDirItem, boolean, kotlin.jvm.functions.Function1, int, java.lang.Object);
    Code:
         0: iload         4
         2: iconst_2
         3: iand
         4: ifeq          9
         7: iconst_1
         8: istore_2
         9: iload         4
        11: iconst_4
        12: iand
        13: ifeq          18
        16: aconst_null
        17: astore_3
        18: aload_0
        19: aload_1
        20: iload_2
        21: aload_3
        22: invokestatic  #868                // Method deleteFolder:(Lorg/fossify/commons/activities/BaseSimpleActivity;Lorg/fossify/commons/models/FileDirItem;ZLkotlin/jvm/functions/Function1;)V
        25: return

  public static final void deleteFolderBg(org.fossify.commons.activities.BaseSimpleActivity, org.fossify.commons.models.FileDirItem, boolean, kotlin.jvm.functions.Function1<? super java.lang.Boolean, kotlin.Unit>);
    Code:
         0: aload_0
         1: ldc           #9                  // String <this>
         3: invokestatic  #15                 // Method kotlin/jvm/internal/Intrinsics.checkNotNullParameter:(Ljava/lang/Object;Ljava/lang/String;)V
         6: aload_1
         7: ldc_w         #871                // String fileDirItem
        10: invokestatic  #15                 // Method kotlin/jvm/internal/Intrinsics.checkNotNullParameter:(Ljava/lang/Object;Ljava/lang/String;)V
        13: new           #873                // class java/io/File
        16: dup
        17: aload_1
        18: invokevirtual #827                // Method org/fossify/commons/models/FileDirItem.getPath:()Ljava/lang/String;
        21: invokespecial #874                // Method java/io/File."<init>":(Ljava/lang/String;)V
        24: astore        4
        26: aload         4
        28: invokevirtual #877                // Method java/io/File.exists:()Z
        31: ifeq          286
        34: aload         4
        36: invokevirtual #881                // Method java/io/File.listFiles:()[Ljava/io/File;
        39: astore        5
        41: aload         5
        43: ifnonnull     57
        46: aload_0
        47: aload_3
        48: invokedynamic #889,  0            // InvokeDynamic #22:run:(Lkotlin/jvm/functions/Function1;)Ljava/lang/Runnable;
        53: invokevirtual #296                // Method org/fossify/commons/activities/BaseSimpleActivity.runOnUiThread:(Ljava/lang/Runnable;)V
        56: return
        57: aload         5
        59: invokestatic  #895                // Method kotlin/collections/ArraysKt.toMutableList:([Ljava/lang/Object;)Ljava/util/List;
        62: checkcast     #88                 // class java/lang/Iterable
        65: astore        7
        67: iconst_0
        68: istore        8
        70: aload         7
        72: astore        9
        74: new           #762                // class java/util/ArrayList
        77: dup
        78: invokespecial #763                // Method java/util/ArrayList."<init>":()V
        81: checkcast     #765                // class java/util/Collection
        84: astore        10
        86: iconst_0
        87: istore        11
        89: aload         9
        91: invokeinterface #92,  1           // InterfaceMethod java/lang/Iterable.iterator:()Ljava/util/Iterator;
        96: astore        12
        98: aload         12
       100: invokeinterface #97,  1           // InterfaceMethod java/util/Iterator.hasNext:()Z
       105: ifeq          165
       108: aload         12
       110: invokeinterface #101,  1          // InterfaceMethod java/util/Iterator.next:()Ljava/lang/Object;
       115: astore        13
       117: aload         13
       119: checkcast     #873                // class java/io/File
       122: astore        14
       124: iconst_0
       125: istore        15
       127: iload_2
       128: ifeq          144
       131: aload         14
       133: invokestatic  #899                // Method kotlin/jvm/internal/Intrinsics.checkNotNull:(Ljava/lang/Object;)V
       136: aload         14
       138: invokestatic  #905                // Method org/fossify/commons/extensions/FileKt.isMediaFile:(Ljava/io/File;)Z
       141: ifeq          148
       144: iconst_1
       145: goto          149
       148: iconst_0
       149: ifeq          98
       152: aload         10
       154: aload         13
       156: invokeinterface #774,  2          // InterfaceMethod java/util/Collection.add:(Ljava/lang/Object;)Z
       161: pop
       162: goto          98
       165: aload         10
       167: checkcast     #781                // class java/util/List
       170: nop
       171: astore        6
       173: aload         6
       175: invokeinterface #822,  1          // InterfaceMethod java/util/List.iterator:()Ljava/util/Iterator;
       180: astore        7
       182: aload         7
       184: invokeinterface #97,  1           // InterfaceMethod java/util/Iterator.hasNext:()Z
       189: ifeq          239
       192: aload         7
       194: invokeinterface #101,  1          // InterfaceMethod java/util/Iterator.next:()Ljava/lang/Object;
       199: checkcast     #873                // class java/io/File
       202: astore        8
       204: aload_0
       205: aload         8
       207: invokestatic  #899                // Method kotlin/jvm/internal/Intrinsics.checkNotNull:(Ljava/lang/Object;)V
       210: aload         8
       212: aload_0
       213: invokevirtual #909                // Method org/fossify/commons/activities/BaseSimpleActivity.getApplicationContext:()Landroid/content/Context;
       216: dup
       217: ldc_w         #911                // String getApplicationContext(...)
       220: invokestatic  #505                // Method kotlin/jvm/internal/Intrinsics.checkNotNullExpressionValue:(Ljava/lang/Object;Ljava/lang/String;)V
       223: invokestatic  #915                // Method org/fossify/commons/extensions/FileKt.toFileDirItem:(Ljava/io/File;Landroid/content/Context;)Lorg/fossify/commons/models/FileDirItem;
       226: iconst_0
       227: iconst_0
       228: invokedynamic #923,  0            // InvokeDynamic #23:invoke:()Lkotlin/jvm/functions/Function1;
       233: invokestatic  #927                // Method deleteFileBg:(Lorg/fossify/commons/activities/BaseSimpleActivity;Lorg/fossify/commons/models/FileDirItem;ZZLkotlin/jvm/functions/Function1;)V
       236: goto          182
       239: aload         4
       241: invokevirtual #881                // Method java/io/File.listFiles:()[Ljava/io/File;
       244: dup
       245: ifnull        269
       248: arraylength
       249: ifne          256
       252: iconst_1
       253: goto          257
       256: iconst_0
       257: iconst_1
       258: if_icmpne     265
       261: iconst_1
       262: goto          271
       265: iconst_0
       266: goto          271
       269: pop
       270: iconst_0
       271: ifeq          286
       274: aload_0
       275: aload_1
       276: iconst_1
       277: iconst_0
       278: invokedynamic #932,  0            // InvokeDynamic #24:invoke:()Lkotlin/jvm/functions/Function1;
       283: invokestatic  #927                // Method deleteFileBg:(Lorg/fossify/commons/activities/BaseSimpleActivity;Lorg/fossify/commons/models/FileDirItem;ZZLkotlin/jvm/functions/Function1;)V
       286: aload_0
       287: aload_3
       288: invokedynamic #937,  0            // InvokeDynamic #25:run:(Lkotlin/jvm/functions/Function1;)Ljava/lang/Runnable;
       293: invokevirtual #296                // Method org/fossify/commons/activities/BaseSimpleActivity.runOnUiThread:(Ljava/lang/Runnable;)V
       296: return

  public static void deleteFolderBg$default(org.fossify.commons.activities.BaseSimpleActivity, org.fossify.commons.models.FileDirItem, boolean, kotlin.jvm.functions.Function1, int, java.lang.Object);
    Code:
         0: iload         4
         2: iconst_2
         3: iand
         4: ifeq          9
         7: iconst_1
         8: istore_2
         9: iload         4
        11: iconst_4
        12: iand
        13: ifeq          18
        16: aconst_null
        17: astore_3
        18: aload_0
        19: aload_1
        20: iload_2
        21: aload_3
        22: invokestatic  #955                // Method deleteFolderBg:(Lorg/fossify/commons/activities/BaseSimpleActivity;Lorg/fossify/commons/models/FileDirItem;ZLkotlin/jvm/functions/Function1;)V
        25: return

  public static final void deleteFile(org.fossify.commons.activities.BaseSimpleActivity, org.fossify.commons.models.FileDirItem, boolean, kotlin.jvm.functions.Function1<? super java.lang.Boolean, kotlin.Unit>);
    Code:
         0: aload_0
         1: ldc           #9                  // String <this>
         3: invokestatic  #15                 // Method kotlin/jvm/internal/Intrinsics.checkNotNullParameter:(Ljava/lang/Object;Ljava/lang/String;)V
         6: aload_1
         7: ldc_w         #957                // String file
        10: invokestatic  #15                 // Method kotlin/jvm/internal/Intrinsics.checkNotNullParameter:(Ljava/lang/Object;Ljava/lang/String;)V
        13: aload_0
        14: iconst_1
        15: anewarray     #824                // class org/fossify/commons/models/FileDirItem
        18: astore        4
        20: aload         4
        22: iconst_0
        23: aload_1
        24: aastore
        25: aload         4
        27: invokestatic  #961                // Method kotlin/collections/CollectionsKt.arrayListOf:([Ljava/lang/Object;)Ljava/util/ArrayList;
        30: checkcast     #781                // class java/util/List
        33: iload_2
        34: aload_3
        35: invokestatic  #964                // Method deleteFiles:(Lorg/fossify/commons/activities/BaseSimpleActivity;Ljava/util/List;ZLkotlin/jvm/functions/Function1;)V
        38: return

  public static void deleteFile$default(org.fossify.commons.activities.BaseSimpleActivity, org.fossify.commons.models.FileDirItem, boolean, kotlin.jvm.functions.Function1, int, java.lang.Object);
    Code:
         0: iload         4
         2: iconst_2
         3: iand
         4: ifeq          9
         7: iconst_0
         8: istore_2
         9: iload         4
        11: iconst_4
        12: iand
        13: ifeq          18
        16: aconst_null
        17: astore_3
        18: aload_0
        19: aload_1
        20: iload_2
        21: aload_3
        22: invokestatic  #969                // Method deleteFile:(Lorg/fossify/commons/activities/BaseSimpleActivity;Lorg/fossify/commons/models/FileDirItem;ZLkotlin/jvm/functions/Function1;)V
        25: return

  public static final void deleteFiles(org.fossify.commons.activities.BaseSimpleActivity, java.util.List<? extends org.fossify.commons.models.FileDirItem>, boolean, kotlin.jvm.functions.Function1<? super java.lang.Boolean, kotlin.Unit>);
    Code:
         0: aload_0
         1: ldc           #9                  // String <this>
         3: invokestatic  #15                 // Method kotlin/jvm/internal/Intrinsics.checkNotNullParameter:(Ljava/lang/Object;Ljava/lang/String;)V
         6: aload_1
         7: ldc_w         #970                // String files
        10: invokestatic  #15                 // Method kotlin/jvm/internal/Intrinsics.checkNotNullParameter:(Ljava/lang/Object;Ljava/lang/String;)V
        13: aload_0
        14: aload_1
        15: iload_2
        16: aload_3
        17: invokedynamic #975,  0            // InvokeDynamic #26:invoke:(Lorg/fossify/commons/activities/BaseSimpleActivity;Ljava/util/List;ZLkotlin/jvm/functions/Function1;)Lkotlin/jvm/functions/Function0;
        22: invokestatic  #543                // Method org/fossify/commons/helpers/ConstantsKt.ensureBackgroundThread:(Lkotlin/jvm/functions/Function0;)V
        25: return

  public static void deleteFiles$default(org.fossify.commons.activities.BaseSimpleActivity, java.util.List, boolean, kotlin.jvm.functions.Function1, int, java.lang.Object);
    Code:
         0: iload         4
         2: iconst_2
         3: iand
         4: ifeq          9
         7: iconst_0
         8: istore_2
         9: iload         4
        11: iconst_4
        12: iand
        13: ifeq          18
        16: aconst_null
        17: astore_3
        18: aload_0
        19: aload_1
        20: iload_2
        21: aload_3
        22: invokestatic  #964                // Method deleteFiles:(Lorg/fossify/commons/activities/BaseSimpleActivity;Ljava/util/List;ZLkotlin/jvm/functions/Function1;)V
        25: return

  public static final void deleteFilesBg(org.fossify.commons.activities.BaseSimpleActivity, java.util.List<? extends org.fossify.commons.models.FileDirItem>, boolean, kotlin.jvm.functions.Function1<? super java.lang.Boolean, kotlin.Unit>);
    Code:
         0: aload_0
         1: ldc           #9                  // String <this>
         3: invokestatic  #15                 // Method kotlin/jvm/internal/Intrinsics.checkNotNullParameter:(Ljava/lang/Object;Ljava/lang/String;)V
         6: aload_1
         7: ldc_w         #970                // String files
        10: invokestatic  #15                 // Method kotlin/jvm/internal/Intrinsics.checkNotNullParameter:(Ljava/lang/Object;Ljava/lang/String;)V
        13: aload_1
        14: invokeinterface #979,  1          // InterfaceMethod java/util/List.isEmpty:()Z
        19: ifeq          33
        22: aload_0
        23: aload_3
        24: invokedynamic #984,  0            // InvokeDynamic #27:run:(Lkotlin/jvm/functions/Function1;)Ljava/lang/Runnable;
        29: invokevirtual #296                // Method org/fossify/commons/activities/BaseSimpleActivity.runOnUiThread:(Ljava/lang/Runnable;)V
        32: return
        33: aload_1
        34: invokestatic  #988                // Method kotlin/collections/CollectionsKt.first:(Ljava/util/List;)Ljava/lang/Object;
        37: checkcast     #824                // class org/fossify/commons/models/FileDirItem
        40: astore        4
        42: aload         4
        44: invokevirtual #827                // Method org/fossify/commons/models/FileDirItem.getPath:()Ljava/lang/String;
        47: astore        5
        49: aload_0
        50: aload         5
        52: aload_0
        53: aload         5
        55: aload         4
        57: aload_1
        58: iload_2
        59: aload_3
        60: invokedynamic #996,  0            // InvokeDynamic #28:invoke:(Lorg/fossify/commons/activities/BaseSimpleActivity;Ljava/lang/String;Lorg/fossify/commons/models/FileDirItem;Ljava/util/List;ZLkotlin/jvm/functions/Function1;)Lkotlin/jvm/functions/Function1;
        65: invokevirtual #842                // Method org/fossify/commons/activities/BaseSimpleActivity.handleSAFDialog:(Ljava/lang/String;Lkotlin/jvm/functions/Function1;)Z
        68: pop
        69: return

  public static void deleteFilesBg$default(org.fossify.commons.activities.BaseSimpleActivity, java.util.List, boolean, kotlin.jvm.functions.Function1, int, java.lang.Object);
    Code:
         0: iload         4
         2: iconst_2
         3: iand
         4: ifeq          9
         7: iconst_0
         8: istore_2
         9: iload         4
        11: iconst_4
        12: iand
        13: ifeq          18
        16: aconst_null
        17: astore_3
        18: aload_0
        19: aload_1
        20: iload_2
        21: aload_3
        22: invokestatic  #1002               // Method deleteFilesBg:(Lorg/fossify/commons/activities/BaseSimpleActivity;Ljava/util/List;ZLkotlin/jvm/functions/Function1;)V
        25: return

  static void deleteFilesCasual$default(org.fossify.commons.activities.BaseSimpleActivity, java.util.List, boolean, kotlin.jvm.functions.Function1, int, java.lang.Object);
    Code:
         0: iload         4
         2: iconst_2
         3: iand
         4: ifeq          9
         7: iconst_0
         8: istore_2
         9: iload         4
        11: iconst_4
        12: iand
        13: ifeq          18
        16: aconst_null
        17: astore_3
        18: aload_0
        19: aload_1
        20: iload_2
        21: aload_3
        22: invokestatic  #1017               // Method deleteFilesCasual:(Lorg/fossify/commons/activities/BaseSimpleActivity;Ljava/util/List;ZLkotlin/jvm/functions/Function1;)V
        25: return

  public static final void deleteFile(org.fossify.commons.activities.BaseSimpleActivity, org.fossify.commons.models.FileDirItem, boolean, boolean, kotlin.jvm.functions.Function1<? super java.lang.Boolean, kotlin.Unit>);
    Code:
         0: aload_0
         1: ldc           #9                  // String <this>
         3: invokestatic  #15                 // Method kotlin/jvm/internal/Intrinsics.checkNotNullParameter:(Ljava/lang/Object;Ljava/lang/String;)V
         6: aload_1
         7: ldc_w         #871                // String fileDirItem
        10: invokestatic  #15                 // Method kotlin/jvm/internal/Intrinsics.checkNotNullParameter:(Ljava/lang/Object;Ljava/lang/String;)V
        13: aload_0
        14: aload_1
        15: iload_2
        16: iload_3
        17: aload         4
        19: invokedynamic #1026,  0           // InvokeDynamic #30:invoke:(Lorg/fossify/commons/activities/BaseSimpleActivity;Lorg/fossify/commons/models/FileDirItem;ZZLkotlin/jvm/functions/Function1;)Lkotlin/jvm/functions/Function0;
        24: invokestatic  #543                // Method org/fossify/commons/helpers/ConstantsKt.ensureBackgroundThread:(Lkotlin/jvm/functions/Function0;)V
        27: return

  public static void deleteFile$default(org.fossify.commons.activities.BaseSimpleActivity, org.fossify.commons.models.FileDirItem, boolean, boolean, kotlin.jvm.functions.Function1, int, java.lang.Object);
    Code:
         0: iload         5
         2: iconst_2
         3: iand
         4: ifeq          9
         7: iconst_0
         8: istore_2
         9: iload         5
        11: bipush        8
        13: iand
        14: ifeq          20
        17: aconst_null
        18: astore        4
        20: aload_0
        21: aload_1
        22: iload_2
        23: iload_3
        24: aload         4
        26: invokestatic  #1030               // Method deleteFile:(Lorg/fossify/commons/activities/BaseSimpleActivity;Lorg/fossify/commons/models/FileDirItem;ZZLkotlin/jvm/functions/Function1;)V
        29: return

  public static final void deleteFileBg(org.fossify.commons.activities.BaseSimpleActivity, org.fossify.commons.models.FileDirItem, boolean, boolean, kotlin.jvm.functions.Function1<? super java.lang.Boolean, kotlin.Unit>);
    Code:
         0: aload_0
         1: ldc           #9                  // String <this>
         3: invokestatic  #15                 // Method kotlin/jvm/internal/Intrinsics.checkNotNullParameter:(Ljava/lang/Object;Ljava/lang/String;)V
         6: aload_1
         7: ldc_w         #871                // String fileDirItem
        10: invokestatic  #15                 // Method kotlin/jvm/internal/Intrinsics.checkNotNullParameter:(Ljava/lang/Object;Ljava/lang/String;)V
        13: aload_1
        14: invokevirtual #827                // Method org/fossify/commons/models/FileDirItem.getPath:()Ljava/lang/String;
        17: astore        5
        19: aload_0
        20: checkcast     #19                 // class android/content/Context
        23: aload         5
        25: invokestatic  #402                // Method org/fossify/commons/extensions/Context_storageKt.isRestrictedSAFOnlyRoot:(Landroid/content/Context;Ljava/lang/String;)Z
        28: ifeq          46
        31: aload_0
        32: checkcast     #19                 // class android/content/Context
        35: aload         5
        37: iload_2
        38: aload         4
        40: invokestatic  #1034               // Method org/fossify/commons/extensions/Context_storageKt.deleteAndroidSAFDirectory:(Landroid/content/Context;Ljava/lang/String;ZLkotlin/jvm/functions/Function1;)V
        43: goto          361
        46: new           #873                // class java/io/File
        49: dup
        50: aload         5
        52: invokespecial #874                // Method java/io/File."<init>":(Ljava/lang/String;)V
        55: astore        6
        57: invokestatic  #256                // Method org/fossify/commons/helpers/ConstantsKt.isRPlus:()Z
        60: ifne          120
        63: aload         6
        65: invokevirtual #1037               // Method java/io/File.getAbsolutePath:()Ljava/lang/String;
        68: dup
        69: ldc_w         #1039               // String getAbsolutePath(...)
        72: invokestatic  #505                // Method kotlin/jvm/internal/Intrinsics.checkNotNullExpressionValue:(Ljava/lang/Object;Ljava/lang/String;)V
        75: aload_0
        76: checkcast     #19                 // class android/content/Context
        79: invokestatic  #1040               // Method org/fossify/commons/extensions/ContextKt.getInternalStoragePath:(Landroid/content/Context;)Ljava/lang/String;
        82: iconst_0
        83: iconst_2
        84: aconst_null
        85: invokestatic  #1044               // Method kotlin/text/StringsKt.startsWith$default:(Ljava/lang/String;Ljava/lang/String;ZILjava/lang/Object;)Z
        88: ifeq          120
        91: aload         6
        93: invokevirtual #1047               // Method java/io/File.canWrite:()Z
        96: ifne          120
        99: aload         4
       101: dup
       102: ifnull        118
       105: iconst_0
       106: invokestatic  #1053               // Method java/lang/Boolean.valueOf:(Z)Ljava/lang/Boolean;
       109: invokeinterface #1055,  2         // InterfaceMethod kotlin/jvm/functions/Function1.invoke:(Ljava/lang/Object;)Ljava/lang/Object;
       114: pop
       115: goto          119
       118: pop
       119: return
       120: aload_0
       121: checkcast     #19                 // class android/content/Context
       124: aload         5
       126: invokestatic  #476                // Method org/fossify/commons/extensions/Context_storageKt.isPathOnOTG:(Landroid/content/Context;Ljava/lang/String;)Z
       129: ifne          162
       132: aload         6
       134: invokevirtual #877                // Method java/io/File.exists:()Z
       137: ifne          150
       140: aload         6
       142: invokevirtual #1058               // Method java/io/File.length:()J
       145: lconst_0
       146: lcmp
       147: ifeq          158
       150: aload         6
       152: invokevirtual #1061               // Method java/io/File.delete:()Z
       155: ifeq          162
       158: iconst_1
       159: goto          163
       162: iconst_0
       163: istore        7
       165: iload         7
       167: ifeq          192
       170: aload_0
       171: checkcast     #19                 // class android/content/Context
       174: aload         5
       176: aload_0
       177: aload         5
       179: aload         4
       181: invokedynamic #1069,  0           // InvokeDynamic #31:invoke:(Lorg/fossify/commons/activities/BaseSimpleActivity;Ljava/lang/String;Lkotlin/jvm/functions/Function1;)Lkotlin/jvm/functions/Function1;
       186: invokestatic  #1073               // Method org/fossify/commons/extensions/Context_storageKt.deleteFromMediaStore:(Landroid/content/Context;Ljava/lang/String;Lkotlin/jvm/functions/Function1;)V
       189: goto          361
       192: aload_0
       193: checkcast     #19                 // class android/content/Context
       196: aload         6
       198: invokevirtual #1037               // Method java/io/File.getAbsolutePath:()Ljava/lang/String;
       201: dup
       202: ldc_w         #1039               // String getAbsolutePath(...)
       205: invokestatic  #505                // Method kotlin/jvm/internal/Intrinsics.checkNotNullExpressionValue:(Ljava/lang/Object;Ljava/lang/String;)V
       208: invokestatic  #1076               // Method org/fossify/commons/extensions/Context_storageKt.getIsPathDirectory:(Landroid/content/Context;Ljava/lang/String;)Z
       211: ifeq          229
       214: iload_2
       215: ifeq          229
       218: aload         6
       220: aload_0
       221: checkcast     #19                 // class android/content/Context
       224: invokestatic  #1080               // Method deleteRecursively:(Ljava/io/File;Landroid/content/Context;)Z
       227: istore        7
       229: iload         7
       231: ifne          361
       234: aload_0
       235: checkcast     #19                 // class android/content/Context
       238: aload         5
       240: invokestatic  #830                // Method org/fossify/commons/extensions/Context_storageKt.needsStupidWritePermissions:(Landroid/content/Context;Ljava/lang/String;)Z
       243: ifeq          266
       246: aload_0
       247: aload         5
       249: aload_0
       250: aload_1
       251: iload_2
       252: aload         4
       254: invokedynamic #1088,  0           // InvokeDynamic #32:invoke:(Lorg/fossify/commons/activities/BaseSimpleActivity;Lorg/fossify/commons/models/FileDirItem;ZLkotlin/jvm/functions/Function1;)Lkotlin/jvm/functions/Function1;
       259: invokevirtual #842                // Method org/fossify/commons/activities/BaseSimpleActivity.handleSAFDialog:(Ljava/lang/String;Lkotlin/jvm/functions/Function1;)Z
       262: pop
       263: goto          361
       266: aload_0
       267: checkcast     #19                 // class android/content/Context
       270: aload         5
       272: invokestatic  #308                // Method org/fossify/commons/extensions/Context_storage_sdk30Kt.isAccessibleWithSAFSdk30:(Landroid/content/Context;Ljava/lang/String;)Z
       275: ifeq          321
       278: aload_0
       279: checkcast     #19                 // class android/content/Context
       282: invokestatic  #1091               // Method org/fossify/commons/extensions/Context_storage_sdk30Kt.canManageMedia:(Landroid/content/Context;)Z
       285: ifeq          298
       288: aload_0
       289: aload_1
       290: aload         4
       292: invokestatic  #1095               // Method deleteSdk30:(Lorg/fossify/commons/activities/BaseSimpleActivity;Lorg/fossify/commons/models/FileDirItem;Lkotlin/jvm/functions/Function1;)V
       295: goto          361
       298: aload_0
       299: aload         5
       301: iconst_0
       302: aload_0
       303: aload_1
       304: iload_2
       305: aload         4
       307: invokedynamic #1100,  0           // InvokeDynamic #33:invoke:(Lorg/fossify/commons/activities/BaseSimpleActivity;Lorg/fossify/commons/models/FileDirItem;ZLkotlin/jvm/functions/Function1;)Lkotlin/jvm/functions/Function1;
       312: iconst_2
       313: aconst_null
       314: invokestatic  #1104               // Method org/fossify/commons/activities/BaseSimpleActivity.handleSAFDialogSdk30$default:(Lorg/fossify/commons/activities/BaseSimpleActivity;Ljava/lang/String;ZLkotlin/jvm/functions/Function1;ILjava/lang/Object;)Z
       317: pop
       318: goto          361
       321: invokestatic  #256                // Method org/fossify/commons/helpers/ConstantsKt.isRPlus:()Z
       324: ifeq          341
       327: iload_3
       328: ifne          341
       331: aload_0
       332: aload_1
       333: aload         4
       335: invokestatic  #1095               // Method deleteSdk30:(Lorg/fossify/commons/activities/BaseSimpleActivity;Lorg/fossify/commons/models/FileDirItem;Lkotlin/jvm/functions/Function1;)V
       338: goto          361
       341: aload         4
       343: dup
       344: ifnull        360
       347: iconst_0
       348: invokestatic  #1053               // Method java/lang/Boolean.valueOf:(Z)Ljava/lang/Boolean;
       351: invokeinterface #1055,  2         // InterfaceMethod kotlin/jvm/functions/Function1.invoke:(Ljava/lang/Object;)Ljava/lang/Object;
       356: pop
       357: goto          361
       360: pop
       361: return

  public static void deleteFileBg$default(org.fossify.commons.activities.BaseSimpleActivity, org.fossify.commons.models.FileDirItem, boolean, boolean, kotlin.jvm.functions.Function1, int, java.lang.Object);
    Code:
         0: iload         5
         2: iconst_2
         3: iand
         4: ifeq          9
         7: iconst_0
         8: istore_2
         9: iload         5
        11: bipush        8
        13: iand
        14: ifeq          20
        17: aconst_null
        18: astore        4
        20: aload_0
        21: aload_1
        22: iload_2
        23: iload_3
        24: aload         4
        26: invokestatic  #927                // Method deleteFileBg:(Lorg/fossify/commons/activities/BaseSimpleActivity;Lorg/fossify/commons/models/FileDirItem;ZZLkotlin/jvm/functions/Function1;)V
        29: return

  public static final void scanFileRecursively(android.app.Activity, java.io.File, kotlin.jvm.functions.Function0<kotlin.Unit>);
    Code:
         0: aload_0
         1: ldc           #9                  // String <this>
         3: invokestatic  #15                 // Method kotlin/jvm/internal/Intrinsics.checkNotNullParameter:(Ljava/lang/Object;Ljava/lang/String;)V
         6: aload_1
         7: ldc_w         #957                // String file
        10: invokestatic  #15                 // Method kotlin/jvm/internal/Intrinsics.checkNotNullParameter:(Ljava/lang/Object;Ljava/lang/String;)V
        13: aload_0
        14: invokevirtual #1141               // Method android/app/Activity.getApplicationContext:()Landroid/content/Context;
        17: dup
        18: ldc_w         #911                // String getApplicationContext(...)
        21: invokestatic  #505                // Method kotlin/jvm/internal/Intrinsics.checkNotNullExpressionValue:(Ljava/lang/Object;Ljava/lang/String;)V
        24: aload_1
        25: aload_2
        26: invokestatic  #1144               // Method org/fossify/commons/extensions/Context_storageKt.scanFileRecursively:(Landroid/content/Context;Ljava/io/File;Lkotlin/jvm/functions/Function0;)V
        29: return

  public static void scanFileRecursively$default(android.app.Activity, java.io.File, kotlin.jvm.functions.Function0, int, java.lang.Object);
    Code:
         0: iload_3
         1: iconst_2
         2: iand
         3: ifeq          8
         6: aconst_null
         7: astore_2
         8: aload_0
         9: aload_1
        10: aload_2
        11: invokestatic  #1150               // Method scanFileRecursively:(Landroid/app/Activity;Ljava/io/File;Lkotlin/jvm/functions/Function0;)V
        14: return

  public static final void scanPathRecursively(android.app.Activity, java.lang.String, kotlin.jvm.functions.Function0<kotlin.Unit>);
    Code:
         0: aload_0
         1: ldc           #9                  // String <this>
         3: invokestatic  #15                 // Method kotlin/jvm/internal/Intrinsics.checkNotNullParameter:(Ljava/lang/Object;Ljava/lang/String;)V
         6: aload_1
         7: ldc           #251                // String path
         9: invokestatic  #15                 // Method kotlin/jvm/internal/Intrinsics.checkNotNullParameter:(Ljava/lang/Object;Ljava/lang/String;)V
        12: aload_0
        13: invokevirtual #1141               // Method android/app/Activity.getApplicationContext:()Landroid/content/Context;
        16: dup
        17: ldc_w         #911                // String getApplicationContext(...)
        20: invokestatic  #505                // Method kotlin/jvm/internal/Intrinsics.checkNotNullExpressionValue:(Ljava/lang/Object;Ljava/lang/String;)V
        23: aload_1
        24: aload_2
        25: invokestatic  #1156               // Method org/fossify/commons/extensions/Context_storageKt.scanPathRecursively:(Landroid/content/Context;Ljava/lang/String;Lkotlin/jvm/functions/Function0;)V
        28: return

  public static void scanPathRecursively$default(android.app.Activity, java.lang.String, kotlin.jvm.functions.Function0, int, java.lang.Object);
    Code:
         0: iload_3
         1: iconst_2
         2: iand
         3: ifeq          8
         6: aconst_null
         7: astore_2
         8: aload_0
         9: aload_1
        10: aload_2
        11: invokestatic  #1161               // Method scanPathRecursively:(Landroid/app/Activity;Ljava/lang/String;Lkotlin/jvm/functions/Function0;)V
        14: return

  public static final void scanFilesRecursively(android.app.Activity, java.util.List<? extends java.io.File>, kotlin.jvm.functions.Function0<kotlin.Unit>);
    Code:
         0: aload_0
         1: ldc           #9                  // String <this>
         3: invokestatic  #15                 // Method kotlin/jvm/internal/Intrinsics.checkNotNullParameter:(Ljava/lang/Object;Ljava/lang/String;)V
         6: aload_1
         7: ldc_w         #970                // String files
        10: invokestatic  #15                 // Method kotlin/jvm/internal/Intrinsics.checkNotNullParameter:(Ljava/lang/Object;Ljava/lang/String;)V
        13: aload_0
        14: invokevirtual #1141               // Method android/app/Activity.getApplicationContext:()Landroid/content/Context;
        17: dup
        18: ldc_w         #911                // String getApplicationContext(...)
        21: invokestatic  #505                // Method kotlin/jvm/internal/Intrinsics.checkNotNullExpressionValue:(Ljava/lang/Object;Ljava/lang/String;)V
        24: aload_1
        25: aload_2
        26: invokestatic  #1167               // Method org/fossify/commons/extensions/Context_storageKt.scanFilesRecursively:(Landroid/content/Context;Ljava/util/List;Lkotlin/jvm/functions/Function0;)V
        29: return

  public static void scanFilesRecursively$default(android.app.Activity, java.util.List, kotlin.jvm.functions.Function0, int, java.lang.Object);
    Code:
         0: iload_3
         1: iconst_2
         2: iand
         3: ifeq          8
         6: aconst_null
         7: astore_2
         8: aload_0
         9: aload_1
        10: aload_2
        11: invokestatic  #1172               // Method scanFilesRecursively:(Landroid/app/Activity;Ljava/util/List;Lkotlin/jvm/functions/Function0;)V
        14: return

  public static final void scanPathsRecursively(android.app.Activity, java.util.List<java.lang.String>, kotlin.jvm.functions.Function0<kotlin.Unit>);
    Code:
         0: aload_0
         1: ldc           #9                  // String <this>
         3: invokestatic  #15                 // Method kotlin/jvm/internal/Intrinsics.checkNotNullParameter:(Ljava/lang/Object;Ljava/lang/String;)V
         6: aload_1
         7: ldc_w         #568                // String paths
        10: invokestatic  #15                 // Method kotlin/jvm/internal/Intrinsics.checkNotNullParameter:(Ljava/lang/Object;Ljava/lang/String;)V
        13: aload_0
        14: invokevirtual #1141               // Method android/app/Activity.getApplicationContext:()Landroid/content/Context;
        17: dup
        18: ldc_w         #911                // String getApplicationContext(...)
        21: invokestatic  #505                // Method kotlin/jvm/internal/Intrinsics.checkNotNullExpressionValue:(Ljava/lang/Object;Ljava/lang/String;)V
        24: aload_1
        25: aload_2
        26: invokestatic  #1176               // Method org/fossify/commons/extensions/Context_storageKt.scanPathsRecursively:(Landroid/content/Context;Ljava/util/List;Lkotlin/jvm/functions/Function0;)V
        29: return

  public static void scanPathsRecursively$default(android.app.Activity, java.util.List, kotlin.jvm.functions.Function0, int, java.lang.Object);
    Code:
         0: iload_3
         1: iconst_2
         2: iand
         3: ifeq          8
         6: aconst_null
         7: astore_2
         8: aload_0
         9: aload_1
        10: aload_2
        11: invokestatic  #1180               // Method scanPathsRecursively:(Landroid/app/Activity;Ljava/util/List;Lkotlin/jvm/functions/Function0;)V
        14: return

  public static final void rescanPath(android.app.Activity, java.lang.String, kotlin.jvm.functions.Function0<kotlin.Unit>);
    Code:
         0: aload_0
         1: ldc           #9                  // String <this>
         3: invokestatic  #15                 // Method kotlin/jvm/internal/Intrinsics.checkNotNullParameter:(Ljava/lang/Object;Ljava/lang/String;)V
         6: aload_1
         7: ldc           #251                // String path
         9: invokestatic  #15                 // Method kotlin/jvm/internal/Intrinsics.checkNotNullParameter:(Ljava/lang/Object;Ljava/lang/String;)V
        12: aload_0
        13: invokevirtual #1141               // Method android/app/Activity.getApplicationContext:()Landroid/content/Context;
        16: dup
        17: ldc_w         #911                // String getApplicationContext(...)
        20: invokestatic  #505                // Method kotlin/jvm/internal/Intrinsics.checkNotNullExpressionValue:(Ljava/lang/Object;Ljava/lang/String;)V
        23: aload_1
        24: aload_2
        25: invokestatic  #1183               // Method org/fossify/commons/extensions/Context_storageKt.rescanPath:(Landroid/content/Context;Ljava/lang/String;Lkotlin/jvm/functions/Function0;)V
        28: return

  public static void rescanPath$default(android.app.Activity, java.lang.String, kotlin.jvm.functions.Function0, int, java.lang.Object);
    Code:
         0: iload_3
         1: iconst_2
         2: iand
         3: ifeq          8
         6: aconst_null
         7: astore_2
         8: aload_0
         9: aload_1
        10: aload_2
        11: invokestatic  #1187               // Method rescanPath:(Landroid/app/Activity;Ljava/lang/String;Lkotlin/jvm/functions/Function0;)V
        14: return

  public static final void rescanPaths(android.app.Activity, java.util.List<java.lang.String>, kotlin.jvm.functions.Function0<kotlin.Unit>);
    Code:
         0: aload_0
         1: ldc           #9                  // String <this>
         3: invokestatic  #15                 // Method kotlin/jvm/internal/Intrinsics.checkNotNullParameter:(Ljava/lang/Object;Ljava/lang/String;)V
         6: aload_1
         7: ldc_w         #568                // String paths
        10: invokestatic  #15                 // Method kotlin/jvm/internal/Intrinsics.checkNotNullParameter:(Ljava/lang/Object;Ljava/lang/String;)V
        13: aload_0
        14: invokevirtual #1141               // Method android/app/Activity.getApplicationContext:()Landroid/content/Context;
        17: dup
        18: ldc_w         #911                // String getApplicationContext(...)
        21: invokestatic  #505                // Method kotlin/jvm/internal/Intrinsics.checkNotNullExpressionValue:(Ljava/lang/Object;Ljava/lang/String;)V
        24: aload_1
        25: aload_2
        26: invokestatic  #1190               // Method org/fossify/commons/extensions/Context_storageKt.rescanPaths:(Landroid/content/Context;Ljava/util/List;Lkotlin/jvm/functions/Function0;)V
        29: return

  public static void rescanPaths$default(android.app.Activity, java.util.List, kotlin.jvm.functions.Function0, int, java.lang.Object);
    Code:
         0: iload_3
         1: iconst_2
         2: iand
         3: ifeq          8
         6: aconst_null
         7: astore_2
         8: aload_0
         9: aload_1
        10: aload_2
        11: invokestatic  #1194               // Method rescanPaths:(Landroid/app/Activity;Ljava/util/List;Lkotlin/jvm/functions/Function0;)V
        14: return

  public static final void renameFile(org.fossify.commons.activities.BaseSimpleActivity, java.lang.String, java.lang.String, boolean, kotlin.jvm.functions.Function2<? super java.lang.Boolean, ? super org.fossify.commons.models.Android30RenameFormat, kotlin.Unit>);
    Code:
         0: aload_0
         1: ldc           #9                  // String <this>
         3: invokestatic  #15                 // Method kotlin/jvm/internal/Intrinsics.checkNotNullParameter:(Ljava/lang/Object;Ljava/lang/String;)V
         6: aload_1
         7: ldc_w         #1199               // String oldPath
        10: invokestatic  #15                 // Method kotlin/jvm/internal/Intrinsics.checkNotNullParameter:(Ljava/lang/Object;Ljava/lang/String;)V
        13: aload_2
        14: ldc_w         #1201               // String newPath
        17: invokestatic  #15                 // Method kotlin/jvm/internal/Intrinsics.checkNotNullParameter:(Ljava/lang/Object;Ljava/lang/String;)V
        20: aload_0
        21: checkcast     #19                 // class android/content/Context
        24: aload_1
        25: invokestatic  #402                // Method org/fossify/commons/extensions/Context_storageKt.isRestrictedSAFOnlyRoot:(Landroid/content/Context;Ljava/lang/String;)Z
        28: ifeq          53
        31: aload_0
        32: aload_1
        33: iconst_0
        34: aload_0
        35: aload         4
        37: aload_1
        38: aload_2
        39: invokedynamic #1209,  0           // InvokeDynamic #35:invoke:(Lorg/fossify/commons/activities/BaseSimpleActivity;Lkotlin/jvm/functions/Function2;Ljava/lang/String;Ljava/lang/String;)Lkotlin/jvm/functions/Function1;
        44: iconst_2
        45: aconst_null
        46: invokestatic  #1212               // Method org/fossify/commons/activities/BaseSimpleActivity.handleAndroidSAFDialog$default:(Lorg/fossify/commons/activities/BaseSimpleActivity;Ljava/lang/String;ZLkotlin/jvm/functions/Function1;ILjava/lang/Object;)Z
        49: pop
        50: goto          172
        53: aload_0
        54: checkcast     #19                 // class android/content/Context
        57: aload_1
        58: invokestatic  #308                // Method org/fossify/commons/extensions/Context_storage_sdk30Kt.isAccessibleWithSAFSdk30:(Landroid/content/Context;Ljava/lang/String;)Z
        61: ifeq          133
        64: aload_0
        65: checkcast     #19                 // class android/content/Context
        68: invokestatic  #1091               // Method org/fossify/commons/extensions/Context_storage_sdk30Kt.canManageMedia:(Landroid/content/Context;)Z
        71: ifeq          111
        74: new           #873                // class java/io/File
        77: dup
        78: aload_1
        79: invokespecial #874                // Method java/io/File."<init>":(Ljava/lang/String;)V
        82: invokevirtual #1129               // Method java/io/File.isDirectory:()Z
        85: ifne          111
        88: aload_0
        89: checkcast     #19                 // class android/content/Context
        92: aload_1
        93: invokestatic  #1215               // Method org/fossify/commons/extensions/Context_storageKt.isPathOnInternalStorage:(Landroid/content/Context;Ljava/lang/String;)Z
        96: ifeq          111
        99: aload_0
       100: aload_1
       101: aload_2
       102: iload_3
       103: aload         4
       105: invokestatic  #1218               // Method renameCasually:(Lorg/fossify/commons/activities/BaseSimpleActivity;Ljava/lang/String;Ljava/lang/String;ZLkotlin/jvm/functions/Function2;)V
       108: goto          172
       111: aload_0
       112: aload_1
       113: iconst_0
       114: aload_0
       115: aload_1
       116: aload_2
       117: aload         4
       119: invokedynamic #1226,  0           // InvokeDynamic #36:invoke:(Lorg/fossify/commons/activities/BaseSimpleActivity;Ljava/lang/String;Ljava/lang/String;Lkotlin/jvm/functions/Function2;)Lkotlin/jvm/functions/Function1;
       124: iconst_2
       125: aconst_null
       126: invokestatic  #1104               // Method org/fossify/commons/activities/BaseSimpleActivity.handleSAFDialogSdk30$default:(Lorg/fossify/commons/activities/BaseSimpleActivity;Ljava/lang/String;ZLkotlin/jvm/functions/Function1;ILjava/lang/Object;)Z
       129: pop
       130: goto          172
       133: aload_0
       134: checkcast     #19                 // class android/content/Context
       137: aload_2
       138: invokestatic  #830                // Method org/fossify/commons/extensions/Context_storageKt.needsStupidWritePermissions:(Landroid/content/Context;Ljava/lang/String;)Z
       141: ifeq          163
       144: aload_0
       145: aload_2
       146: aload_0
       147: aload_1
       148: aload         4
       150: aload_2
       151: invokedynamic #1234,  0           // InvokeDynamic #37:invoke:(Lorg/fossify/commons/activities/BaseSimpleActivity;Ljava/lang/String;Lkotlin/jvm/functions/Function2;Ljava/lang/String;)Lkotlin/jvm/functions/Function1;
       156: invokevirtual #842                // Method org/fossify/commons/activities/BaseSimpleActivity.handleSAFDialog:(Ljava/lang/String;Lkotlin/jvm/functions/Function1;)Z
       159: pop
       160: goto          172
       163: aload_0
       164: aload_1
       165: aload_2
       166: iload_3
       167: aload         4
       169: invokestatic  #1218               // Method renameCasually:(Lorg/fossify/commons/activities/BaseSimpleActivity;Ljava/lang/String;Ljava/lang/String;ZLkotlin/jvm/functions/Function2;)V
       172: return

  public static void renameFile$default(org.fossify.commons.activities.BaseSimpleActivity, java.lang.String, java.lang.String, boolean, kotlin.jvm.functions.Function2, int, java.lang.Object);
    Code:
         0: iload         5
         2: bipush        8
         4: iand
         5: ifeq          11
         8: aconst_null
         9: astore        4
        11: aload_0
        12: aload_1
        13: aload_2
        14: iload_3
        15: aload         4
        17: invokestatic  #1241               // Method renameFile:(Lorg/fossify/commons/activities/BaseSimpleActivity;Ljava/lang/String;Ljava/lang/String;ZLkotlin/jvm/functions/Function2;)V
        20: return

  public static final java.io.File createTempFile(android.app.Activity, java.io.File);
    Code:
         0: aload_0
         1: ldc           #9                  // String <this>
         3: invokestatic  #15                 // Method kotlin/jvm/internal/Intrinsics.checkNotNullParameter:(Ljava/lang/Object;Ljava/lang/String;)V
         6: aload_1
         7: ldc_w         #957                // String file
        10: invokestatic  #15                 // Method kotlin/jvm/internal/Intrinsics.checkNotNullParameter:(Ljava/lang/Object;Ljava/lang/String;)V
        13: aload_1
        14: invokevirtual #1129               // Method java/io/File.isDirectory:()Z
        17: ifeq          65
        20: ldc_w         #1335               // String temp
        23: invokestatic  #1303               // Method java/lang/System.currentTimeMillis:()J
        26: invokestatic  #1338               // Method java/lang/String.valueOf:(J)Ljava/lang/String;
        29: aload_1
        30: invokevirtual #1342               // Method java/io/File.getParentFile:()Ljava/io/File;
        33: invokestatic  #1345               // Method java/io/File.createTempFile:(Ljava/lang/String;Ljava/lang/String;Ljava/io/File;)Ljava/io/File;
        36: astore_2
        37: aload_2
        38: invokevirtual #1061               // Method java/io/File.delete:()Z
        41: pop
        42: aload_2
        43: invokevirtual #1348               // Method java/io/File.mkdir:()Z
        46: ifeq          51
        49: aload_2
        50: areturn
        51: new           #1271               // class java/io/IOException
        54: dup
        55: aload_2
        56: invokedynamic #1353,  0           // InvokeDynamic #42:makeConcatWithConstants:(Ljava/io/File;)Ljava/lang/String;
        61: invokespecial #1354               // Method java/io/IOException."<init>":(Ljava/lang/String;)V
        64: athrow
        65: invokestatic  #256                // Method org/fossify/commons/helpers/ConstantsKt.isRPlus:()Z
        68: ifeq          102
        71: aload_1
        72: invokevirtual #1342               // Method java/io/File.getParentFile:()Ljava/io/File;
        75: invokevirtual #1358               // Method java/io/File.toPath:()Ljava/nio/file/Path;
        78: ldc_w         #1335               // String temp
        81: invokestatic  #1303               // Method java/lang/System.currentTimeMillis:()J
        84: invokestatic  #1338               // Method java/lang/String.valueOf:(J)Ljava/lang/String;
        87: iconst_0
        88: anewarray     #1360               // class java/nio/file/attribute/FileAttribute
        91: invokestatic  #1365               // Method kotlin/io/path/PathsKt.createTempFile:(Ljava/nio/file/Path;Ljava/lang/String;Ljava/lang/String;[Ljava/nio/file/attribute/FileAttribute;)Ljava/nio/file/Path;
        94: invokeinterface #1370,  1         // InterfaceMethod java/nio/file/Path.toFile:()Ljava/io/File;
        99: goto          118
       102: ldc_w         #1335               // String temp
       105: invokestatic  #1303               // Method java/lang/System.currentTimeMillis:()J
       108: invokestatic  #1338               // Method java/lang/String.valueOf:(J)Ljava/lang/String;
       111: aload_1
       112: invokevirtual #1342               // Method java/io/File.getParentFile:()Ljava/io/File;
       115: invokestatic  #1345               // Method java/io/File.createTempFile:(Ljava/lang/String;Ljava/lang/String;Ljava/io/File;)Ljava/io/File;
       118: areturn

  public static final void hideKeyboard(android.app.Activity);
    Code:
         0: aload_0
         1: ldc           #9                  // String <this>
         3: invokestatic  #15                 // Method kotlin/jvm/internal/Intrinsics.checkNotNullParameter:(Ljava/lang/Object;Ljava/lang/String;)V
         6: invokestatic  #1375               // Method org/fossify/commons/helpers/ConstantsKt.isOnMainThread:()Z
         9: ifeq          19
        12: aload_0
        13: invokestatic  #1378               // Method hideKeyboardSync:(Landroid/app/Activity;)V
        16: goto          39
        19: new           #1380               // class android/os/Handler
        22: dup
        23: invokestatic  #1386               // Method android/os/Looper.getMainLooper:()Landroid/os/Looper;
        26: invokespecial #1389               // Method android/os/Handler."<init>":(Landroid/os/Looper;)V
        29: aload_0
        30: invokedynamic #1396,  0           // InvokeDynamic #43:run:(Landroid/app/Activity;)Ljava/lang/Runnable;
        35: invokevirtual #1400               // Method android/os/Handler.post:(Ljava/lang/Runnable;)Z
        38: pop
        39: return

  public static final void hideKeyboardSync(android.app.Activity);
    Code:
         0: aload_0
         1: ldc           #9                  // String <this>
         3: invokestatic  #15                 // Method kotlin/jvm/internal/Intrinsics.checkNotNullParameter:(Ljava/lang/Object;Ljava/lang/String;)V
         6: aload_0
         7: ldc_w         #1403               // String input_method
        10: invokevirtual #1407               // Method android/app/Activity.getSystemService:(Ljava/lang/String;)Ljava/lang/Object;
        13: dup
        14: ldc_w         #1409               // String null cannot be cast to non-null type android.view.inputmethod.InputMethodManager
        17: invokestatic  #1411               // Method kotlin/jvm/internal/Intrinsics.checkNotNull:(Ljava/lang/Object;Ljava/lang/String;)V
        20: checkcast     #1413               // class android/view/inputmethod/InputMethodManager
        23: astore_1
        24: aload_1
        25: aload_0
        26: invokevirtual #1417               // Method android/app/Activity.getCurrentFocus:()Landroid/view/View;
        29: dup
        30: ifnonnull     45
        33: pop
        34: new           #1419               // class android/view/View
        37: dup
        38: aload_0
        39: checkcast     #19                 // class android/content/Context
        42: invokespecial #1421               // Method android/view/View."<init>":(Landroid/content/Context;)V
        45: invokevirtual #1425               // Method android/view/View.getWindowToken:()Landroid/os/IBinder;
        48: iconst_0
        49: invokevirtual #1429               // Method android/view/inputmethod/InputMethodManager.hideSoftInputFromWindow:(Landroid/os/IBinder;I)Z
        52: pop
        53: aload_0
        54: invokevirtual #1433               // Method android/app/Activity.getWindow:()Landroid/view/Window;
        57: dup
        58: invokestatic  #899                // Method kotlin/jvm/internal/Intrinsics.checkNotNull:(Ljava/lang/Object;)V
        61: iconst_3
        62: invokevirtual #1438               // Method android/view/Window.setSoftInputMode:(I)V
        65: aload_0
        66: invokevirtual #1417               // Method android/app/Activity.getCurrentFocus:()Landroid/view/View;
        69: dup
        70: ifnull        79
        73: invokevirtual #1441               // Method android/view/View.clearFocus:()V
        76: goto          80
        79: pop
        80: return

  public static final void showKeyboard(android.app.Activity, android.widget.EditText);
    Code:
         0: aload_0
         1: ldc           #9                  // String <this>
         3: invokestatic  #15                 // Method kotlin/jvm/internal/Intrinsics.checkNotNullParameter:(Ljava/lang/Object;Ljava/lang/String;)V
         6: aload_1
         7: ldc_w         #1448               // String et
        10: invokestatic  #15                 // Method kotlin/jvm/internal/Intrinsics.checkNotNullParameter:(Ljava/lang/Object;Ljava/lang/String;)V
        13: aload_1
        14: invokevirtual #1453               // Method android/widget/EditText.requestFocus:()Z
        17: pop
        18: aload_0
        19: ldc_w         #1403               // String input_method
        22: invokevirtual #1407               // Method android/app/Activity.getSystemService:(Ljava/lang/String;)Ljava/lang/Object;
        25: dup
        26: ldc_w         #1409               // String null cannot be cast to non-null type android.view.inputmethod.InputMethodManager
        29: invokestatic  #1411               // Method kotlin/jvm/internal/Intrinsics.checkNotNull:(Ljava/lang/Object;Ljava/lang/String;)V
        32: checkcast     #1413               // class android/view/inputmethod/InputMethodManager
        35: astore_2
        36: aload_2
        37: aload_1
        38: checkcast     #1419               // class android/view/View
        41: iconst_1
        42: invokevirtual #1457               // Method android/view/inputmethod/InputMethodManager.showSoftInput:(Landroid/view/View;I)Z
        45: pop
        46: return

  public static final void hideKeyboard(android.app.Activity, android.view.View);
    Code:
         0: aload_0
         1: ldc           #9                  // String <this>
         3: invokestatic  #15                 // Method kotlin/jvm/internal/Intrinsics.checkNotNullParameter:(Ljava/lang/Object;Ljava/lang/String;)V
         6: aload_1
         7: ldc_w         #1463               // String view
        10: invokestatic  #15                 // Method kotlin/jvm/internal/Intrinsics.checkNotNullParameter:(Ljava/lang/Object;Ljava/lang/String;)V
        13: aload_0
        14: ldc_w         #1403               // String input_method
        17: invokevirtual #1407               // Method android/app/Activity.getSystemService:(Ljava/lang/String;)Ljava/lang/Object;
        20: dup
        21: ldc_w         #1409               // String null cannot be cast to non-null type android.view.inputmethod.InputMethodManager
        24: invokestatic  #1411               // Method kotlin/jvm/internal/Intrinsics.checkNotNull:(Ljava/lang/Object;Ljava/lang/String;)V
        27: checkcast     #1413               // class android/view/inputmethod/InputMethodManager
        30: astore_2
        31: aload_2
        32: aload_1
        33: invokevirtual #1425               // Method android/view/View.getWindowToken:()Landroid/os/IBinder;
        36: iconst_0
        37: invokevirtual #1429               // Method android/view/inputmethod/InputMethodManager.hideSoftInputFromWindow:(Landroid/os/IBinder;I)Z
        40: pop
        41: return

  public static final void getFileOutputStream(org.fossify.commons.activities.BaseSimpleActivity, org.fossify.commons.models.FileDirItem, boolean, kotlin.jvm.functions.Function1<? super java.io.OutputStream, kotlin.Unit>);
    Code:
         0: aload_0
         1: ldc           #9                  // String <this>
         3: invokestatic  #15                 // Method kotlin/jvm/internal/Intrinsics.checkNotNullParameter:(Ljava/lang/Object;Ljava/lang/String;)V
         6: aload_1
         7: ldc_w         #871                // String fileDirItem
        10: invokestatic  #15                 // Method kotlin/jvm/internal/Intrinsics.checkNotNullParameter:(Ljava/lang/Object;Ljava/lang/String;)V
        13: aload_3
        14: ldc_w         #1467               // String callback
        17: invokestatic  #15                 // Method kotlin/jvm/internal/Intrinsics.checkNotNullParameter:(Ljava/lang/Object;Ljava/lang/String;)V
        20: new           #873                // class java/io/File
        23: dup
        24: aload_1
        25: invokevirtual #827                // Method org/fossify/commons/models/FileDirItem.getPath:()Ljava/lang/String;
        28: invokespecial #874                // Method java/io/File."<init>":(Ljava/lang/String;)V
        31: astore        4
        33: nop
        34: aload_0
        35: checkcast     #19                 // class android/content/Context
        38: aload_1
        39: invokevirtual #827                // Method org/fossify/commons/models/FileDirItem.getPath:()Ljava/lang/String;
        42: invokestatic  #402                // Method org/fossify/commons/extensions/Context_storageKt.isRestrictedSAFOnlyRoot:(Landroid/content/Context;Ljava/lang/String;)Z
        45: ifeq          71
        48: aload_0
        49: aload_1
        50: invokevirtual #827                // Method org/fossify/commons/models/FileDirItem.getPath:()Ljava/lang/String;
        53: iconst_0
        54: aload_0
        55: aload_1
        56: aload_3
        57: invokedynamic #1475,  0           // InvokeDynamic #44:invoke:(Lorg/fossify/commons/activities/BaseSimpleActivity;Lorg/fossify/commons/models/FileDirItem;Lkotlin/jvm/functions/Function1;)Lkotlin/jvm/functions/Function1;
        62: iconst_2
        63: aconst_null
        64: invokestatic  #1212               // Method org/fossify/commons/activities/BaseSimpleActivity.handleAndroidSAFDialog$default:(Lorg/fossify/commons/activities/BaseSimpleActivity;Ljava/lang/String;ZLkotlin/jvm/functions/Function1;ILjava/lang/Object;)Z
        67: pop
        68: goto          261
        71: aload_0
        72: checkcast     #19                 // class android/content/Context
        75: aload_1
        76: invokevirtual #827                // Method org/fossify/commons/models/FileDirItem.getPath:()Ljava/lang/String;
        79: invokestatic  #830                // Method org/fossify/commons/extensions/Context_storageKt.needsStupidWritePermissions:(Landroid/content/Context;Ljava/lang/String;)Z
        82: ifeq          106
        85: aload_0
        86: aload_1
        87: invokevirtual #827                // Method org/fossify/commons/models/FileDirItem.getPath:()Ljava/lang/String;
        90: aload_0
        91: aload_1
        92: iload_2
        93: aload_3
        94: invokedynamic #1480,  0           // InvokeDynamic #45:invoke:(Lorg/fossify/commons/activities/BaseSimpleActivity;Lorg/fossify/commons/models/FileDirItem;ZLkotlin/jvm/functions/Function1;)Lkotlin/jvm/functions/Function1;
        99: invokevirtual #842                // Method org/fossify/commons/activities/BaseSimpleActivity.handleSAFDialog:(Ljava/lang/String;Lkotlin/jvm/functions/Function1;)Z
       102: pop
       103: goto          261
       106: aload_0
       107: checkcast     #19                 // class android/content/Context
       110: aload_1
       111: invokevirtual #827                // Method org/fossify/commons/models/FileDirItem.getPath:()Ljava/lang/String;
       114: invokestatic  #308                // Method org/fossify/commons/extensions/Context_storage_sdk30Kt.isAccessibleWithSAFSdk30:(Landroid/content/Context;Ljava/lang/String;)Z
       117: ifeq          145
       120: aload_0
       121: aload_1
       122: invokevirtual #827                // Method org/fossify/commons/models/FileDirItem.getPath:()Ljava/lang/String;
       125: iconst_0
       126: aload_3
       127: aload_0
       128: aload_1
       129: aload         4
       131: invokedynamic #1488,  0           // InvokeDynamic #46:invoke:(Lkotlin/jvm/functions/Function1;Lorg/fossify/commons/activities/BaseSimpleActivity;Lorg/fossify/commons/models/FileDirItem;Ljava/io/File;)Lkotlin/jvm/functions/Function1;
       136: iconst_2
       137: aconst_null
       138: invokestatic  #1104               // Method org/fossify/commons/activities/BaseSimpleActivity.handleSAFDialogSdk30$default:(Lorg/fossify/commons/activities/BaseSimpleActivity;Ljava/lang/String;ZLkotlin/jvm/functions/Function1;ILjava/lang/Object;)Z
       141: pop
       142: goto          261
       145: aload_0
       146: checkcast     #19                 // class android/content/Context
       149: aload_1
       150: invokevirtual #827                // Method org/fossify/commons/models/FileDirItem.getPath:()Ljava/lang/String;
       153: invokestatic  #1274               // Method org/fossify/commons/extensions/Context_storage_sdk30Kt.isRestrictedWithSAFSdk30:(Landroid/content/Context;Ljava/lang/String;)Z
       156: ifeq          248
       159: aload_3
       160: astore        7
       162: nop
       163: aload         7
       165: aload_0
       166: checkcast     #19                 // class android/content/Context
       169: iconst_1
       170: anewarray     #824                // class org/fossify/commons/models/FileDirItem
       173: astore        6
       175: aload         6
       177: iconst_0
       178: aload_1
       179: aastore
       180: aload         6
       182: invokestatic  #961                // Method kotlin/collections/CollectionsKt.arrayListOf:([Ljava/lang/Object;)Ljava/util/ArrayList;
       185: checkcast     #781                // class java/util/List
       188: invokestatic  #1112               // Method org/fossify/commons/extensions/Context_storageKt.getFileUrisFromFileDirItems:(Landroid/content/Context;Ljava/util/List;)Ljava/util/List;
       191: astore        5
       193: aload_0
       194: invokevirtual #909                // Method org/fossify/commons/activities/BaseSimpleActivity.getApplicationContext:()Landroid/content/Context;
       197: invokevirtual #1492               // Method android/content/Context.getContentResolver:()Landroid/content/ContentResolver;
       200: aload         5
       202: invokestatic  #988                // Method kotlin/collections/CollectionsKt.first:(Ljava/util/List;)Ljava/lang/Object;
       205: checkcast     #686                // class android/net/Uri
       208: ldc_w         #1494               // String wt
       211: invokevirtual #1500               // Method android/content/ContentResolver.openOutputStream:(Landroid/net/Uri;Ljava/lang/String;)Ljava/io/OutputStream;
       214: astore        5
       216: goto          226
       219: astore        6
       221: aload         7
       223: aconst_null
       224: astore        5
       226: aload         5
       228: dup
       229: ifnonnull     239
       232: pop
       233: aload_0
       234: aload         4
       236: invokestatic  #1504               // Method createCasualFileOutputStream:(Lorg/fossify/commons/activities/BaseSimpleActivity;Ljava/io/File;)Ljava/io/OutputStream;
       239: invokeinterface #1055,  2         // InterfaceMethod kotlin/jvm/functions/Function1.invoke:(Ljava/lang/Object;)Ljava/lang/Object;
       244: pop
       245: goto          261
       248: aload_3
       249: aload_0
       250: aload         4
       252: invokestatic  #1504               // Method createCasualFileOutputStream:(Lorg/fossify/commons/activities/BaseSimpleActivity;Ljava/io/File;)Ljava/io/OutputStream;
       255: invokeinterface #1055,  2         // InterfaceMethod kotlin/jvm/functions/Function1.invoke:(Ljava/lang/Object;)Ljava/lang/Object;
       260: pop
       261: return
      Exception table:
         from    to  target type
           162   216   219   Class java/lang/Exception

  public static void getFileOutputStream$default(org.fossify.commons.activities.BaseSimpleActivity, org.fossify.commons.models.FileDirItem, boolean, kotlin.jvm.functions.Function1, int, java.lang.Object);
    Code:
         0: iload         4
         2: iconst_2
         3: iand
         4: ifeq          9
         7: iconst_0
         8: istore_2
         9: aload_0
        10: aload_1
        11: iload_2
        12: aload_3
        13: invokestatic  #1513               // Method getFileOutputStream:(Lorg/fossify/commons/activities/BaseSimpleActivity;Lorg/fossify/commons/models/FileDirItem;ZLkotlin/jvm/functions/Function1;)V
        16: return

  public static final void performSecurityCheck(android.app.Activity, int, java.lang.String, kotlin.jvm.functions.Function2<? super java.lang.String, ? super java.lang.Integer, kotlin.Unit>, kotlin.jvm.functions.Function0<kotlin.Unit>);
    Code:
         0: aload_0
         1: ldc           #9                  // String <this>
         3: invokestatic  #15                 // Method kotlin/jvm/internal/Intrinsics.checkNotNullParameter:(Ljava/lang/Object;Ljava/lang/String;)V
         6: aload_2
         7: ldc_w         #1527               // String requiredHash
        10: invokestatic  #15                 // Method kotlin/jvm/internal/Intrinsics.checkNotNullParameter:(Ljava/lang/Object;Ljava/lang/String;)V
        13: iload_1
        14: iconst_2
        15: if_icmpne     37
        18: invokestatic  #256                // Method org/fossify/commons/helpers/ConstantsKt.isRPlus:()Z
        21: ifeq          37
        24: aload_0
        25: aload_3
        26: aload         4
        28: invokestatic  #1531               // Method showBiometricPrompt:(Landroid/app/Activity;Lkotlin/jvm/functions/Function2;Lkotlin/jvm/functions/Function0;)V
        31: getstatic     #1537               // Field kotlin/Unit.INSTANCE:Lkotlin/Unit;
        34: goto          55
        37: new           #1539               // class org/fossify/commons/dialogs/SecurityDialog
        40: dup
        41: aload_0
        42: aload_2
        43: iload_1
        44: aload_3
        45: aload         4
        47: invokedynamic #1551,  0           // InvokeDynamic #47:invoke:(Lkotlin/jvm/functions/Function2;Lkotlin/jvm/functions/Function0;)Lkotlin/jvm/functions/Function3;
        52: invokespecial #1554               // Method org/fossify/commons/dialogs/SecurityDialog."<init>":(Landroid/app/Activity;Ljava/lang/String;ILkotlin/jvm/functions/Function3;)V
        55: pop
        56: return

  public static void performSecurityCheck$default(android.app.Activity, int, java.lang.String, kotlin.jvm.functions.Function2, kotlin.jvm.functions.Function0, int, java.lang.Object);
    Code:
         0: iload         5
         2: iconst_4
         3: iand
         4: ifeq          9
         7: aconst_null
         8: astore_3
         9: iload         5
        11: bipush        8
        13: iand
        14: ifeq          20
        17: aconst_null
        18: astore        4
        20: aload_0
        21: iload_1
        22: aload_2
        23: aload_3
        24: aload         4
        26: invokestatic  #1562               // Method performSecurityCheck:(Landroid/app/Activity;ILjava/lang/String;Lkotlin/jvm/functions/Function2;Lkotlin/jvm/functions/Function0;)V
        29: return

  public static final void showBiometricPrompt(android.app.Activity, kotlin.jvm.functions.Function2<? super java.lang.String, ? super java.lang.Integer, kotlin.Unit>, kotlin.jvm.functions.Function0<kotlin.Unit>);
    Code:
         0: aload_0
         1: ldc           #9                  // String <this>
         3: invokestatic  #15                 // Method kotlin/jvm/internal/Intrinsics.checkNotNullParameter:(Ljava/lang/Object;Ljava/lang/String;)V
         6: new           #1565               // class androidx/biometric/auth/Class2BiometricAuthPrompt$Builder
         9: dup
        10: aload_0
        11: getstatic     #1568               // Field org/fossify/commons/R$string.authenticate:I
        14: invokevirtual #1572               // Method android/app/Activity.getText:(I)Ljava/lang/CharSequence;
        17: aload_0
        18: getstatic     #1575               // Field org/fossify/commons/R$string.cancel:I
        21: invokevirtual #1572               // Method android/app/Activity.getText:(I)Ljava/lang/CharSequence;
        24: invokespecial #1578               // Method androidx/biometric/auth/Class2BiometricAuthPrompt$Builder."<init>":(Ljava/lang/CharSequence;Ljava/lang/CharSequence;)V
        27: invokevirtual #1582               // Method androidx/biometric/auth/Class2BiometricAuthPrompt$Builder.build:()Landroidx/biometric/auth/Class2BiometricAuthPrompt;
        30: new           #1584               // class androidx/biometric/auth/AuthPromptHost
        33: dup
        34: aload_0
        35: checkcast     #1586               // class androidx/fragment/app/FragmentActivity
        38: invokespecial #1589               // Method androidx/biometric/auth/AuthPromptHost."<init>":(Landroidx/fragment/app/FragmentActivity;)V
        41: new           #1591               // class org/fossify/commons/extensions/ActivityKt$showBiometricPrompt$1
        44: dup
        45: aload_1
        46: aload_0
        47: aload_2
        48: invokespecial #1594               // Method org/fossify/commons/extensions/ActivityKt$showBiometricPrompt$1."<init>":(Lkotlin/jvm/functions/Function2;Landroid/app/Activity;Lkotlin/jvm/functions/Function0;)V
        51: checkcast     #1596               // class androidx/biometric/auth/AuthPromptCallback
        54: invokevirtual #1602               // Method androidx/biometric/auth/Class2BiometricAuthPrompt.startAuthentication:(Landroidx/biometric/auth/AuthPromptHost;Landroidx/biometric/auth/AuthPromptCallback;)Landroidx/biometric/auth/AuthPrompt;
        57: pop
        58: return

  public static void showBiometricPrompt$default(android.app.Activity, kotlin.jvm.functions.Function2, kotlin.jvm.functions.Function0, int, java.lang.Object);
    Code:
         0: iload_3
         1: iconst_1
         2: iand
         3: ifeq          8
         6: aconst_null
         7: astore_1
         8: iload_3
         9: iconst_2
        10: iand
        11: ifeq          16
        14: aconst_null
        15: astore_2
        16: aload_0
        17: aload_1
        18: aload_2
        19: invokestatic  #1531               // Method showBiometricPrompt:(Landroid/app/Activity;Lkotlin/jvm/functions/Function2;Lkotlin/jvm/functions/Function0;)V
        22: return

  public static final void handleHiddenFolderPasswordProtection(android.app.Activity, kotlin.jvm.functions.Function0<kotlin.Unit>);
    Code:
         0: aload_0
         1: ldc           #9                  // String <this>
         3: invokestatic  #15                 // Method kotlin/jvm/internal/Intrinsics.checkNotNullParameter:(Ljava/lang/Object;Ljava/lang/String;)V
         6: aload_1
         7: ldc_w         #1467               // String callback
        10: invokestatic  #15                 // Method kotlin/jvm/internal/Intrinsics.checkNotNullParameter:(Ljava/lang/Object;Ljava/lang/String;)V
        13: aload_0
        14: checkcast     #19                 // class android/content/Context
        17: invokestatic  #25                 // Method org/fossify/commons/extensions/ContextKt.getBaseConfig:(Landroid/content/Context;)Lorg/fossify/commons/helpers/BaseConfig;
        20: invokevirtual #1611               // Method org/fossify/commons/helpers/BaseConfig.isHiddenPasswordProtectionOn:()Z
        23: ifeq          63
        26: new           #1539               // class org/fossify/commons/dialogs/SecurityDialog
        29: dup
        30: aload_0
        31: aload_0
        32: checkcast     #19                 // class android/content/Context
        35: invokestatic  #25                 // Method org/fossify/commons/extensions/ContextKt.getBaseConfig:(Landroid/content/Context;)Lorg/fossify/commons/helpers/BaseConfig;
        38: invokevirtual #1614               // Method org/fossify/commons/helpers/BaseConfig.getHiddenPasswordHash:()Ljava/lang/String;
        41: aload_0
        42: checkcast     #19                 // class android/content/Context
        45: invokestatic  #25                 // Method org/fossify/commons/extensions/ContextKt.getBaseConfig:(Landroid/content/Context;)Lorg/fossify/commons/helpers/BaseConfig;
        48: invokevirtual #1617               // Method org/fossify/commons/helpers/BaseConfig.getHiddenProtectionType:()I
        51: aload_1
        52: invokedynamic #1625,  0           // InvokeDynamic #48:invoke:(Lkotlin/jvm/functions/Function0;)Lkotlin/jvm/functions/Function3;
        57: invokespecial #1554               // Method org/fossify/commons/dialogs/SecurityDialog."<init>":(Landroid/app/Activity;Ljava/lang/String;ILkotlin/jvm/functions/Function3;)V
        60: goto          73
        63: aload_1
        64: invokeinterface #1629,  1         // InterfaceMethod kotlin/jvm/functions/Function0.invoke:()Ljava/lang/Object;
        69: pop
        70: getstatic     #1537               // Field kotlin/Unit.INSTANCE:Lkotlin/Unit;
        73: pop
        74: return

  public static final void handleAppPasswordProtection(android.app.Activity, kotlin.jvm.functions.Function1<? super java.lang.Boolean, kotlin.Unit>);
    Code:
         0: aload_0
         1: ldc           #9                  // String <this>
         3: invokestatic  #15                 // Method kotlin/jvm/internal/Intrinsics.checkNotNullParameter:(Ljava/lang/Object;Ljava/lang/String;)V
         6: aload_1
         7: ldc_w         #1467               // String callback
        10: invokestatic  #15                 // Method kotlin/jvm/internal/Intrinsics.checkNotNullParameter:(Ljava/lang/Object;Ljava/lang/String;)V
        13: aload_0
        14: checkcast     #19                 // class android/content/Context
        17: invokestatic  #25                 // Method org/fossify/commons/extensions/ContextKt.getBaseConfig:(Landroid/content/Context;)Lorg/fossify/commons/helpers/BaseConfig;
        20: invokevirtual #1636               // Method org/fossify/commons/helpers/BaseConfig.isAppPasswordProtectionOn:()Z
        23: ifeq          63
        26: new           #1539               // class org/fossify/commons/dialogs/SecurityDialog
        29: dup
        30: aload_0
        31: aload_0
        32: checkcast     #19                 // class android/content/Context
        35: invokestatic  #25                 // Method org/fossify/commons/extensions/ContextKt.getBaseConfig:(Landroid/content/Context;)Lorg/fossify/commons/helpers/BaseConfig;
        38: invokevirtual #1639               // Method org/fossify/commons/helpers/BaseConfig.getAppPasswordHash:()Ljava/lang/String;
        41: aload_0
        42: checkcast     #19                 // class android/content/Context
        45: invokestatic  #25                 // Method org/fossify/commons/extensions/ContextKt.getBaseConfig:(Landroid/content/Context;)Lorg/fossify/commons/helpers/BaseConfig;
        48: invokevirtual #1642               // Method org/fossify/commons/helpers/BaseConfig.getAppProtectionType:()I
        51: aload_1
        52: invokedynamic #1650,  0           // InvokeDynamic #49:invoke:(Lkotlin/jvm/functions/Function1;)Lkotlin/jvm/functions/Function3;
        57: invokespecial #1554               // Method org/fossify/commons/dialogs/SecurityDialog."<init>":(Landroid/app/Activity;Ljava/lang/String;ILkotlin/jvm/functions/Function3;)V
        60: goto          77
        63: aload_1
        64: iconst_1
        65: invokestatic  #1053               // Method java/lang/Boolean.valueOf:(Z)Ljava/lang/Boolean;
        68: invokeinterface #1055,  2         // InterfaceMethod kotlin/jvm/functions/Function1.invoke:(Ljava/lang/Object;)Ljava/lang/Object;
        73: pop
        74: getstatic     #1537               // Field kotlin/Unit.INSTANCE:Lkotlin/Unit;
        77: pop
        78: return

  public static final void handleDeletePasswordProtection(android.app.Activity, kotlin.jvm.functions.Function0<kotlin.Unit>);
    Code:
         0: aload_0
         1: ldc           #9                  // String <this>
         3: invokestatic  #15                 // Method kotlin/jvm/internal/Intrinsics.checkNotNullParameter:(Ljava/lang/Object;Ljava/lang/String;)V
         6: aload_1
         7: ldc_w         #1467               // String callback
        10: invokestatic  #15                 // Method kotlin/jvm/internal/Intrinsics.checkNotNullParameter:(Ljava/lang/Object;Ljava/lang/String;)V
        13: aload_0
        14: checkcast     #19                 // class android/content/Context
        17: invokestatic  #25                 // Method org/fossify/commons/extensions/ContextKt.getBaseConfig:(Landroid/content/Context;)Lorg/fossify/commons/helpers/BaseConfig;
        20: invokevirtual #1655               // Method org/fossify/commons/helpers/BaseConfig.isDeletePasswordProtectionOn:()Z
        23: ifeq          63
        26: new           #1539               // class org/fossify/commons/dialogs/SecurityDialog
        29: dup
        30: aload_0
        31: aload_0
        32: checkcast     #19                 // class android/content/Context
        35: invokestatic  #25                 // Method org/fossify/commons/extensions/ContextKt.getBaseConfig:(Landroid/content/Context;)Lorg/fossify/commons/helpers/BaseConfig;
        38: invokevirtual #1658               // Method org/fossify/commons/helpers/BaseConfig.getDeletePasswordHash:()Ljava/lang/String;
        41: aload_0
        42: checkcast     #19                 // class android/content/Context
        45: invokestatic  #25                 // Method org/fossify/commons/extensions/ContextKt.getBaseConfig:(Landroid/content/Context;)Lorg/fossify/commons/helpers/BaseConfig;
        48: invokevirtual #1661               // Method org/fossify/commons/helpers/BaseConfig.getDeleteProtectionType:()I
        51: aload_1
        52: invokedynamic #1666,  0           // InvokeDynamic #50:invoke:(Lkotlin/jvm/functions/Function0;)Lkotlin/jvm/functions/Function3;
        57: invokespecial #1554               // Method org/fossify/commons/dialogs/SecurityDialog."<init>":(Landroid/app/Activity;Ljava/lang/String;ILkotlin/jvm/functions/Function3;)V
        60: goto          73
        63: aload_1
        64: invokeinterface #1629,  1         // InterfaceMethod kotlin/jvm/functions/Function0.invoke:()Ljava/lang/Object;
        69: pop
        70: getstatic     #1537               // Field kotlin/Unit.INSTANCE:Lkotlin/Unit;
        73: pop
        74: return

  public static final void handleLockedFolderOpening(android.app.Activity, java.lang.String, kotlin.jvm.functions.Function1<? super java.lang.Boolean, kotlin.Unit>);
    Code:
         0: aload_0
         1: ldc           #9                  // String <this>
         3: invokestatic  #15                 // Method kotlin/jvm/internal/Intrinsics.checkNotNullParameter:(Ljava/lang/Object;Ljava/lang/String;)V
         6: aload_1
         7: ldc           #251                // String path
         9: invokestatic  #15                 // Method kotlin/jvm/internal/Intrinsics.checkNotNullParameter:(Ljava/lang/Object;Ljava/lang/String;)V
        12: aload_2
        13: ldc_w         #1467               // String callback
        16: invokestatic  #15                 // Method kotlin/jvm/internal/Intrinsics.checkNotNullParameter:(Ljava/lang/Object;Ljava/lang/String;)V
        19: aload_0
        20: checkcast     #19                 // class android/content/Context
        23: invokestatic  #25                 // Method org/fossify/commons/extensions/ContextKt.getBaseConfig:(Landroid/content/Context;)Lorg/fossify/commons/helpers/BaseConfig;
        26: aload_1
        27: invokevirtual #1674               // Method org/fossify/commons/helpers/BaseConfig.isFolderProtected:(Ljava/lang/String;)Z
        30: ifeq          72
        33: new           #1539               // class org/fossify/commons/dialogs/SecurityDialog
        36: dup
        37: aload_0
        38: aload_0
        39: checkcast     #19                 // class android/content/Context
        42: invokestatic  #25                 // Method org/fossify/commons/extensions/ContextKt.getBaseConfig:(Landroid/content/Context;)Lorg/fossify/commons/helpers/BaseConfig;
        45: aload_1
        46: invokevirtual #1677               // Method org/fossify/commons/helpers/BaseConfig.getFolderProtectionHash:(Ljava/lang/String;)Ljava/lang/String;
        49: aload_0
        50: checkcast     #19                 // class android/content/Context
        53: invokestatic  #25                 // Method org/fossify/commons/extensions/ContextKt.getBaseConfig:(Landroid/content/Context;)Lorg/fossify/commons/helpers/BaseConfig;
        56: aload_1
        57: invokevirtual #1681               // Method org/fossify/commons/helpers/BaseConfig.getFolderProtectionType:(Ljava/lang/String;)I
        60: aload_2
        61: invokedynamic #1686,  0           // InvokeDynamic #51:invoke:(Lkotlin/jvm/functions/Function1;)Lkotlin/jvm/functions/Function3;
        66: invokespecial #1554               // Method org/fossify/commons/dialogs/SecurityDialog."<init>":(Landroid/app/Activity;Ljava/lang/String;ILkotlin/jvm/functions/Function3;)V
        69: goto          86
        72: aload_2
        73: iconst_1
        74: invokestatic  #1053               // Method java/lang/Boolean.valueOf:(Z)Ljava/lang/Boolean;
        77: invokeinterface #1055,  2         // InterfaceMethod kotlin/jvm/functions/Function1.invoke:(Ljava/lang/Object;)Ljava/lang/Object;
        82: pop
        83: getstatic     #1537               // Field kotlin/Unit.INSTANCE:Lkotlin/Unit;
        86: pop
        87: return

  public static final void updateGlobalConfig(android.app.Activity, android.content.ContentValues);
    Code:
         0: aload_0
         1: ldc           #9                  // String <this>
         3: invokestatic  #15                 // Method kotlin/jvm/internal/Intrinsics.checkNotNullParameter:(Ljava/lang/Object;Ljava/lang/String;)V
         6: aload_1
         7: ldc_w         #1691               // String contentValues
        10: invokestatic  #15                 // Method kotlin/jvm/internal/Intrinsics.checkNotNullParameter:(Ljava/lang/Object;Ljava/lang/String;)V
        13: aload_1
        14: aload_0
        15: invokedynamic #1699,  0           // InvokeDynamic #52:invoke:(Landroid/content/ContentValues;Landroid/app/Activity;)Lkotlin/jvm/functions/Function0;
        20: invokestatic  #543                // Method org/fossify/commons/helpers/ConstantsKt.ensureBackgroundThread:(Lkotlin/jvm/functions/Function0;)V
        23: return

  public static final void setupDialogStuff(android.app.Activity, android.view.View, androidx.appcompat.app.AlertDialog$Builder, int, java.lang.String, boolean, kotlin.jvm.functions.Function1<? super androidx.appcompat.app.AlertDialog, kotlin.Unit>);
    Code:
         0: aload_0
         1: ldc           #9                  // String <this>
         3: invokestatic  #15                 // Method kotlin/jvm/internal/Intrinsics.checkNotNullParameter:(Ljava/lang/Object;Ljava/lang/String;)V
         6: aload_1
         7: ldc_w         #1463               // String view
        10: invokestatic  #15                 // Method kotlin/jvm/internal/Intrinsics.checkNotNullParameter:(Ljava/lang/Object;Ljava/lang/String;)V
        13: aload_2
        14: ldc_w         #1706               // String dialog
        17: invokestatic  #15                 // Method kotlin/jvm/internal/Intrinsics.checkNotNullParameter:(Ljava/lang/Object;Ljava/lang/String;)V
        20: aload         4
        22: ldc_w         #1708               // String titleText
        25: invokestatic  #15                 // Method kotlin/jvm/internal/Intrinsics.checkNotNullParameter:(Ljava/lang/Object;Ljava/lang/String;)V
        28: aload_0
        29: invokevirtual #1711               // Method android/app/Activity.isDestroyed:()Z
        32: ifne          42
        35: aload_0
        36: invokevirtual #1714               // Method android/app/Activity.isFinishing:()Z
        39: ifeq          43
        42: return
        43: aload_0
        44: checkcast     #19                 // class android/content/Context
        47: invokestatic  #1718               // Method org/fossify/commons/extensions/Context_stylingKt.getProperTextColor:(Landroid/content/Context;)I
        50: istore        7
        52: aload_0
        53: checkcast     #19                 // class android/content/Context
        56: invokestatic  #1721               // Method org/fossify/commons/extensions/Context_stylingKt.getProperBackgroundColor:(Landroid/content/Context;)I
        59: istore        8
        61: aload_0
        62: checkcast     #19                 // class android/content/Context
        65: invokestatic  #1724               // Method org/fossify/commons/extensions/Context_stylingKt.getProperPrimaryColor:(Landroid/content/Context;)I
        68: istore        9
        70: aload_1
        71: instanceof    #1726               // class android/view/ViewGroup
        74: ifeq          91
        77: aload_0
        78: checkcast     #19                 // class android/content/Context
        81: aload_1
        82: checkcast     #1726               // class android/view/ViewGroup
        85: invokestatic  #1730               // Method org/fossify/commons/extensions/Context_stylingKt.updateTextColors:(Landroid/content/Context;Landroid/view/ViewGroup;)V
        88: goto          111
        91: aload_1
        92: instanceof    #1732               // class org/fossify/commons/views/MyTextView
        95: ifeq          111
        98: aload_1
        99: checkcast     #1732               // class org/fossify/commons/views/MyTextView
       102: iload         7
       104: iload         9
       106: iload         8
       108: invokevirtual #1736               // Method org/fossify/commons/views/MyTextView.setColors:(III)V
       111: aload_2
       112: instanceof    #1738               // class com/google/android/material/dialog/MaterialAlertDialogBuilder
       115: ifeq          392
       118: aload_2
       119: checkcast     #1738               // class com/google/android/material/dialog/MaterialAlertDialogBuilder
       122: invokevirtual #1742               // Method com/google/android/material/dialog/MaterialAlertDialogBuilder.create:()Landroidx/appcompat/app/AlertDialog;
       125: astore        10
       127: aload         10
       129: astore        11
       131: iconst_0
       132: istore        12
       134: iload_3
       135: ifeq          147
       138: aload         11
       140: iload_3
       141: invokevirtual #1747               // Method androidx/appcompat/app/AlertDialog.setTitle:(I)V
       144: goto          178
       147: aload         4
       149: checkcast     #124                // class java/lang/CharSequence
       152: invokeinterface #269,  1          // InterfaceMethod java/lang/CharSequence.length:()I
       157: ifle          164
       160: iconst_1
       161: goto          165
       164: iconst_0
       165: ifeq          178
       168: aload         11
       170: aload         4
       172: checkcast     #124                // class java/lang/CharSequence
       175: invokevirtual #1750               // Method androidx/appcompat/app/AlertDialog.setTitle:(Ljava/lang/CharSequence;)V
       178: aload         11
       180: aload_1
       181: invokevirtual #1754               // Method androidx/appcompat/app/AlertDialog.setView:(Landroid/view/View;)V
       184: aload         11
       186: iload         5
       188: invokevirtual #1757               // Method androidx/appcompat/app/AlertDialog.setCancelable:(Z)V
       191: aload_0
       192: invokevirtual #1714               // Method android/app/Activity.isFinishing:()Z
       195: ifne          203
       198: aload         11
       200: invokevirtual #1760               // Method androidx/appcompat/app/AlertDialog.show:()V
       203: aload         11
       205: iconst_m1
       206: invokevirtual #1764               // Method androidx/appcompat/app/AlertDialog.getButton:(I)Landroid/widget/Button;
       209: dup
       210: ifnull        250
       213: astore        13
       215: aload         13
       217: astore        14
       219: iconst_0
       220: istore        15
       222: aload         14
       224: iload         9
       226: invokevirtual #1769               // Method android/widget/Button.setTextColor:(I)V
       229: aload_0
       230: checkcast     #19                 // class android/content/Context
       233: aload         14
       235: checkcast     #1771               // class android/widget/TextView
       238: aconst_null
       239: iconst_0
       240: bipush        6
       242: aconst_null
       243: invokestatic  #1775               // Method org/fossify/commons/extensions/ContextKt.applyFontToTextView$default:(Landroid/content/Context;Landroid/widget/TextView;Landroid/graphics/Typeface;ZILjava/lang/Object;)V
       246: nop
       247: goto          252
       250: pop
       251: nop
       252: aload         11
       254: bipush        -2
       256: invokevirtual #1764               // Method androidx/appcompat/app/AlertDialog.getButton:(I)Landroid/widget/Button;
       259: dup
       260: ifnull        300
       263: astore        13
       265: aload         13
       267: astore        14
       269: iconst_0
       270: istore        15
       272: aload         14
       274: iload         9
       276: invokevirtual #1769               // Method android/widget/Button.setTextColor:(I)V
       279: aload_0
       280: checkcast     #19                 // class android/content/Context
       283: aload         14
       285: checkcast     #1771               // class android/widget/TextView
       288: aconst_null
       289: iconst_0
       290: bipush        6
       292: aconst_null
       293: invokestatic  #1775               // Method org/fossify/commons/extensions/ContextKt.applyFontToTextView$default:(Landroid/content/Context;Landroid/widget/TextView;Landroid/graphics/Typeface;ZILjava/lang/Object;)V
       296: nop
       297: goto          302
       300: pop
       301: nop
       302: aload         11
       304: bipush        -3
       306: invokevirtual #1764               // Method androidx/appcompat/app/AlertDialog.getButton:(I)Landroid/widget/Button;
       309: dup
       310: ifnull        350
       313: astore        13
       315: aload         13
       317: astore        14
       319: iconst_0
       320: istore        15
       322: aload         14
       324: iload         9
       326: invokevirtual #1769               // Method android/widget/Button.setTextColor:(I)V
       329: aload_0
       330: checkcast     #19                 // class android/content/Context
       333: aload         14
       335: checkcast     #1771               // class android/widget/TextView
       338: aconst_null
       339: iconst_0
       340: bipush        6
       342: aconst_null
       343: invokestatic  #1775               // Method org/fossify/commons/extensions/ContextKt.applyFontToTextView$default:(Landroid/content/Context;Landroid/widget/TextView;Landroid/graphics/Typeface;ZILjava/lang/Object;)V
       346: nop
       347: goto          352
       350: pop
       351: nop
       352: aload_0
       353: checkcast     #19                 // class android/content/Context
       356: aload_1
       357: aconst_null
       358: iconst_0
       359: bipush        6
       361: aconst_null
       362: invokestatic  #1779               // Method org/fossify/commons/extensions/ContextKt.applyFontToViewRecursively$default:(Landroid/content/Context;Landroid/view/View;Landroid/graphics/Typeface;ZILjava/lang/Object;)V
       365: aload         6
       367: dup
       368: ifnull        387
       371: aload         11
       373: invokestatic  #899                // Method kotlin/jvm/internal/Intrinsics.checkNotNull:(Ljava/lang/Object;)V
       376: aload         11
       378: invokeinterface #1055,  2         // InterfaceMethod kotlin/jvm/functions/Function1.invoke:(Ljava/lang/Object;)Ljava/lang/Object;
       383: pop
       384: goto          388
       387: pop
       388: nop
       389: goto          899
       392: aconst_null
       393: astore        10
       395: iload_3
       396: ifne          420
       399: aload         4
       401: checkcast     #124                // class java/lang/CharSequence
       404: invokeinterface #269,  1          // InterfaceMethod java/lang/CharSequence.length:()I
       409: ifle          416
       412: iconst_1
       413: goto          417
       416: iconst_0
       417: ifeq          516
       420: aload_0
       421: invokevirtual #1783               // Method android/app/Activity.getLayoutInflater:()Landroid/view/LayoutInflater;
       424: aconst_null
       425: iconst_0
       426: invokestatic  #1789               // Method org/fossify/commons/databinding/DialogTitleBinding.inflate:(Landroid/view/LayoutInflater;Landroid/view/ViewGroup;Z)Lorg/fossify/commons/databinding/DialogTitleBinding;
       429: astore        10
       431: aload         10
       433: getfield      #1793               // Field org/fossify/commons/databinding/DialogTitleBinding.dialogTitleTextview:Lorg/fossify/commons/views/MyTextView;
       436: astore        11
       438: aload         11
       440: astore        12
       442: iconst_0
       443: istore        13
       445: aload         4
       447: checkcast     #124                // class java/lang/CharSequence
       450: invokeinterface #269,  1          // InterfaceMethod java/lang/CharSequence.length:()I
       455: ifle          462
       458: iconst_1
       459: goto          463
       462: iconst_0
       463: ifeq          479
       466: aload         12
       468: aload         4
       470: checkcast     #124                // class java/lang/CharSequence
       473: invokevirtual #1796               // Method org/fossify/commons/views/MyTextView.setText:(Ljava/lang/CharSequence;)V
       476: goto          485
       479: aload         12
       481: iload_3
       482: invokevirtual #1798               // Method org/fossify/commons/views/MyTextView.setText:(I)V
       485: aload         12
       487: iload         7
       489: invokevirtual #1799               // Method org/fossify/commons/views/MyTextView.setTextColor:(I)V
       492: aload_0
       493: checkcast     #19                 // class android/content/Context
       496: aload         12
       498: invokestatic  #899                // Method kotlin/jvm/internal/Intrinsics.checkNotNull:(Ljava/lang/Object;)V
       501: aload         12
       503: checkcast     #1771               // class android/widget/TextView
       506: aconst_null
       507: iconst_0
       508: bipush        6
       510: aconst_null
       511: invokestatic  #1775               // Method org/fossify/commons/extensions/ContextKt.applyFontToTextView$default:(Landroid/content/Context;Landroid/widget/TextView;Landroid/graphics/Typeface;ZILjava/lang/Object;)V
       514: nop
       515: nop
       516: iload         9
       518: aload_0
       519: checkcast     #19                 // class android/content/Context
       522: invokestatic  #25                 // Method org/fossify/commons/extensions/ContextKt.getBaseConfig:(Landroid/content/Context;)Lorg/fossify/commons/helpers/BaseConfig;
       525: invokevirtual #1802               // Method org/fossify/commons/helpers/BaseConfig.getBackgroundColor:()I
       528: if_icmpne     536
       531: iload         7
       533: goto          538
       536: iload         9
       538: istore        11
       540: aload_2
       541: invokevirtual #1805               // Method androidx/appcompat/app/AlertDialog$Builder.create:()Landroidx/appcompat/app/AlertDialog;
       544: astore        12
       546: aload         12
       548: astore        13
       550: iconst_0
       551: istore        14
       553: aload         13
       555: aload_1
       556: invokevirtual #1754               // Method androidx/appcompat/app/AlertDialog.setView:(Landroid/view/View;)V
       559: aload         13
       561: iconst_1
       562: invokevirtual #1808               // Method androidx/appcompat/app/AlertDialog.requestWindowFeature:(I)Z
       565: pop
       566: aload         13
       568: aload         10
       570: dup
       571: ifnull        580
       574: invokevirtual #1812               // Method org/fossify/commons/databinding/DialogTitleBinding.getRoot:()Lorg/fossify/commons/views/MyTextView;
       577: goto          582
       580: pop
       581: aconst_null
       582: checkcast     #1419               // class android/view/View
       585: invokevirtual #1815               // Method androidx/appcompat/app/AlertDialog.setCustomTitle:(Landroid/view/View;)V
       588: aload         13
       590: iload         5
       592: invokevirtual #1818               // Method androidx/appcompat/app/AlertDialog.setCanceledOnTouchOutside:(Z)V
       595: aload_0
       596: invokevirtual #1714               // Method android/app/Activity.isFinishing:()Z
       599: ifne          607
       602: aload         13
       604: invokevirtual #1760               // Method androidx/appcompat/app/AlertDialog.show:()V
       607: aload         13
       609: iconst_m1
       610: invokevirtual #1764               // Method androidx/appcompat/app/AlertDialog.getButton:(I)Landroid/widget/Button;
       613: dup
       614: ifnull        654
       617: astore        15
       619: aload         15
       621: astore        16
       623: iconst_0
       624: istore        17
       626: aload         16
       628: iload         11
       630: invokevirtual #1769               // Method android/widget/Button.setTextColor:(I)V
       633: aload_0
       634: checkcast     #19                 // class android/content/Context
       637: aload         16
       639: checkcast     #1771               // class android/widget/TextView
       642: aconst_null
       643: iconst_0
       644: bipush        6
       646: aconst_null
       647: invokestatic  #1775               // Method org/fossify/commons/extensions/ContextKt.applyFontToTextView$default:(Landroid/content/Context;Landroid/widget/TextView;Landroid/graphics/Typeface;ZILjava/lang/Object;)V
       650: nop
       651: goto          656
       654: pop
       655: nop
       656: aload         13
       658: bipush        -2
       660: invokevirtual #1764               // Method androidx/appcompat/app/AlertDialog.getButton:(I)Landroid/widget/Button;
       663: dup
       664: ifnull        704
       667: astore        15
       669: aload         15
       671: astore        16
       673: iconst_0
       674: istore        17
       676: aload         16
       678: iload         11
       680: invokevirtual #1769               // Method android/widget/Button.setTextColor:(I)V
       683: aload_0
       684: checkcast     #19                 // class android/content/Context
       687: aload         16
       689: checkcast     #1771               // class android/widget/TextView
       692: aconst_null
       693: iconst_0
       694: bipush        6
       696: aconst_null
       697: invokestatic  #1775               // Method org/fossify/commons/extensions/ContextKt.applyFontToTextView$default:(Landroid/content/Context;Landroid/widget/TextView;Landroid/graphics/Typeface;ZILjava/lang/Object;)V
       700: nop
       701: goto          706
       704: pop
       705: nop
       706: aload         13
       708: bipush        -3
       710: invokevirtual #1764               // Method androidx/appcompat/app/AlertDialog.getButton:(I)Landroid/widget/Button;
       713: dup
       714: ifnull        754
       717: astore        15
       719: aload         15
       721: astore        16
       723: iconst_0
       724: istore        17
       726: aload         16
       728: iload         11
       730: invokevirtual #1769               // Method android/widget/Button.setTextColor:(I)V
       733: aload_0
       734: checkcast     #19                 // class android/content/Context
       737: aload         16
       739: checkcast     #1771               // class android/widget/TextView
       742: aconst_null
       743: iconst_0
       744: bipush        6
       746: aconst_null
       747: invokestatic  #1775               // Method org/fossify/commons/extensions/ContextKt.applyFontToTextView$default:(Landroid/content/Context;Landroid/widget/TextView;Landroid/graphics/Typeface;ZILjava/lang/Object;)V
       750: nop
       751: goto          756
       754: pop
       755: nop
       756: aload_0
       757: checkcast     #19                 // class android/content/Context
       760: aload_1
       761: aconst_null
       762: iconst_0
       763: bipush        6
       765: aconst_null
       766: invokestatic  #1779               // Method org/fossify/commons/extensions/ContextKt.applyFontToViewRecursively$default:(Landroid/content/Context;Landroid/view/View;Landroid/graphics/Typeface;ZILjava/lang/Object;)V
       769: nop
       770: aload_0
       771: checkcast     #19                 // class android/content/Context
       774: invokestatic  #1821               // Method org/fossify/commons/extensions/Context_stylingKt.isBlackAndWhiteTheme:(Landroid/content/Context;)Z
       777: ifeq          797
       780: aload_0
       781: invokevirtual #67                 // Method android/app/Activity.getResources:()Landroid/content/res/Resources;
       784: getstatic     #1826               // Field org/fossify/commons/R$drawable.black_dialog_background:I
       787: aload_0
       788: invokevirtual #1830               // Method android/app/Activity.getTheme:()Landroid/content/res/Resources$Theme;
       791: invokevirtual #1834               // Method android/content/res/Resources.getDrawable:(ILandroid/content/res/Resources$Theme;)Landroid/graphics/drawable/Drawable;
       794: goto          854
       797: aload_0
       798: checkcast     #19                 // class android/content/Context
       801: invokestatic  #1837               // Method org/fossify/commons/extensions/Context_stylingKt.isDynamicTheme:(Landroid/content/Context;)Z
       804: ifeq          824
       807: aload_0
       808: invokevirtual #67                 // Method android/app/Activity.getResources:()Landroid/content/res/Resources;
       811: getstatic     #1840               // Field org/fossify/commons/R$drawable.dialog_you_background:I
       814: aload_0
       815: invokevirtual #1830               // Method android/app/Activity.getTheme:()Landroid/content/res/Resources$Theme;
       818: invokevirtual #1834               // Method android/content/res/Resources.getDrawable:(ILandroid/content/res/Resources$Theme;)Landroid/graphics/drawable/Drawable;
       821: goto          854
       824: aload_0
       825: invokevirtual #67                 // Method android/app/Activity.getResources:()Landroid/content/res/Resources;
       828: dup
       829: ldc_w         #1842               // String getResources(...)
       832: invokestatic  #505                // Method kotlin/jvm/internal/Intrinsics.checkNotNullExpressionValue:(Ljava/lang/Object;Ljava/lang/String;)V
       835: getstatic     #1845               // Field org/fossify/commons/R$drawable.dialog_bg:I
       838: aload_0
       839: checkcast     #19                 // class android/content/Context
       842: invokestatic  #25                 // Method org/fossify/commons/extensions/ContextKt.getBaseConfig:(Landroid/content/Context;)Lorg/fossify/commons/helpers/BaseConfig;
       845: invokevirtual #1802               // Method org/fossify/commons/helpers/BaseConfig.getBackgroundColor:()I
       848: iconst_0
       849: iconst_4
       850: aconst_null
       851: invokestatic  #1851               // Method org/fossify/commons/extensions/ResourcesKt.getColoredDrawableWithColor$default:(Landroid/content/res/Resources;IIIILjava/lang/Object;)Landroid/graphics/drawable/Drawable;
       854: astore        18
       856: aload         13
       858: invokevirtual #1852               // Method androidx/appcompat/app/AlertDialog.getWindow:()Landroid/view/Window;
       861: dup
       862: ifnull        873
       865: aload         18
       867: invokevirtual #1856               // Method android/view/Window.setBackgroundDrawable:(Landroid/graphics/drawable/Drawable;)V
       870: goto          874
       873: pop
       874: aload         6
       876: dup
       877: ifnull        896
       880: aload         13
       882: invokestatic  #899                // Method kotlin/jvm/internal/Intrinsics.checkNotNull:(Ljava/lang/Object;)V
       885: aload         13
       887: invokeinterface #1055,  2         // InterfaceMethod kotlin/jvm/functions/Function1.invoke:(Ljava/lang/Object;)Ljava/lang/Object;
       892: pop
       893: goto          897
       896: pop
       897: nop
       898: nop
       899: return

  public static void setupDialogStuff$default(android.app.Activity, android.view.View, androidx.appcompat.app.AlertDialog$Builder, int, java.lang.String, boolean, kotlin.jvm.functions.Function1, int, java.lang.Object);
    Code:
         0: iload         7
         2: iconst_4
         3: iand
         4: ifeq          9
         7: iconst_0
         8: istore_3
         9: iload         7
        11: bipush        8
        13: iand
        14: ifeq          22
        17: ldc_w         #627                // String
        20: astore        4
        22: iload         7
        24: bipush        16
        26: iand
        27: ifeq          33
        30: iconst_1
        31: istore        5
        33: iload         7
        35: bipush        32
        37: iand
        38: ifeq          44
        41: aconst_null
        42: astore        6
        44: aload_0
        45: aload_1
        46: aload_2
        47: iload_3
        48: aload         4
        50: iload         5
        52: aload         6
        54: invokestatic  #1892               // Method setupDialogStuff:(Landroid/app/Activity;Landroid/view/View;Landroidx/appcompat/app/AlertDialog$Builder;ILjava/lang/String;ZLkotlin/jvm/functions/Function1;)V
        57: return

  public static final androidx.appcompat.app.AlertDialog$Builder getAlertDialogBuilder(android.app.Activity);
    Code:
         0: aload_0
         1: ldc           #9                  // String <this>
         3: invokestatic  #15                 // Method kotlin/jvm/internal/Intrinsics.checkNotNullParameter:(Ljava/lang/Object;Ljava/lang/String;)V
         6: aload_0
         7: checkcast     #19                 // class android/content/Context
        10: invokestatic  #1837               // Method org/fossify/commons/extensions/Context_stylingKt.isDynamicTheme:(Landroid/content/Context;)Z
        13: ifeq          33
        16: new           #1738               // class com/google/android/material/dialog/MaterialAlertDialogBuilder
        19: dup
        20: aload_0
        21: checkcast     #19                 // class android/content/Context
        24: invokespecial #1895               // Method com/google/android/material/dialog/MaterialAlertDialogBuilder."<init>":(Landroid/content/Context;)V
        27: checkcast     #1804               // class androidx/appcompat/app/AlertDialog$Builder
        30: goto          44
        33: new           #1804               // class androidx/appcompat/app/AlertDialog$Builder
        36: dup
        37: aload_0
        38: checkcast     #19                 // class android/content/Context
        41: invokespecial #1896               // Method androidx/appcompat/app/AlertDialog$Builder."<init>":(Landroid/content/Context;)V
        44: areturn

  public static final void showPickSecondsDialogHelper(android.app.Activity, int, boolean, boolean, boolean, kotlin.jvm.functions.Function0<kotlin.Unit>, kotlin.jvm.functions.Function1<? super java.lang.Integer, kotlin.Unit>);
    Code:
         0: aload_0
         1: ldc           #9                  // String <this>
         3: invokestatic  #15                 // Method kotlin/jvm/internal/Intrinsics.checkNotNullParameter:(Ljava/lang/Object;Ljava/lang/String;)V
         6: aload         6
         8: ldc_w         #1467               // String callback
        11: invokestatic  #15                 // Method kotlin/jvm/internal/Intrinsics.checkNotNullParameter:(Ljava/lang/Object;Ljava/lang/String;)V
        14: iload_1
        15: iconst_m1
        16: if_icmpne     23
        19: iload_1
        20: goto          27
        23: iload_1
        24: bipush        60
        26: imul
        27: istore        7
        29: aload_0
        30: iload         7
        32: iload_2
        33: iload_3
        34: iload         4
        36: aload         5
        38: aload         6
        40: invokestatic  #1903               // Method showPickSecondsDialog:(Landroid/app/Activity;IZZZLkotlin/jvm/functions/Function0;Lkotlin/jvm/functions/Function1;)V
        43: return

  public static void showPickSecondsDialogHelper$default(android.app.Activity, int, boolean, boolean, boolean, kotlin.jvm.functions.Function0, kotlin.jvm.functions.Function1, int, java.lang.Object);
    Code:
         0: iload         7
         2: iconst_2
         3: iand
         4: ifeq          9
         7: iconst_0
         8: istore_2
         9: iload         7
        11: iconst_4
        12: iand
        13: ifeq          18
        16: iconst_0
        17: istore_3
        18: iload         7
        20: bipush        8
        22: iand
        23: ifeq          29
        26: iconst_0
        27: istore        4
        29: iload         7
        31: bipush        16
        33: iand
        34: ifeq          40
        37: aconst_null
        38: astore        5
        40: aload_0
        41: iload_1
        42: iload_2
        43: iload_3
        44: iload         4
        46: aload         5
        48: aload         6
        50: invokestatic  #1914               // Method showPickSecondsDialogHelper:(Landroid/app/Activity;IZZZLkotlin/jvm/functions/Function0;Lkotlin/jvm/functions/Function1;)V
        53: return

  public static final void showPickSecondsDialog(android.app.Activity, int, boolean, boolean, boolean, kotlin.jvm.functions.Function0<kotlin.Unit>, kotlin.jvm.functions.Function1<? super java.lang.Integer, kotlin.Unit>);
    Code:
         0: aload_0
         1: ldc           #9                  // String <this>
         3: invokestatic  #15                 // Method kotlin/jvm/internal/Intrinsics.checkNotNullParameter:(Ljava/lang/Object;Ljava/lang/String;)V
         6: aload         6
         8: ldc_w         #1467               // String callback
        11: invokestatic  #15                 // Method kotlin/jvm/internal/Intrinsics.checkNotNullParameter:(Ljava/lang/Object;Ljava/lang/String;)V
        14: aload_0
        15: invokestatic  #493                // Method hideKeyboard:(Landroid/app/Activity;)V
        18: new           #1916               // class java/util/TreeSet
        21: dup
        22: invokespecial #1917               // Method java/util/TreeSet."<init>":()V
        25: astore        7
        27: aload         7
        29: astore        8
        31: aload         8
        33: astore        9
        35: iconst_0
        36: istore        10
        38: iload_2
        39: ifne          62
        42: aload         9
        44: iconst_m1
        45: invokestatic  #1922               // Method java/lang/Integer.valueOf:(I)Ljava/lang/Integer;
        48: invokevirtual #1923               // Method java/util/TreeSet.add:(Ljava/lang/Object;)Z
        51: pop
        52: aload         9
        54: iconst_0
        55: invokestatic  #1922               // Method java/lang/Integer.valueOf:(I)Ljava/lang/Integer;
        58: invokevirtual #1923               // Method java/util/TreeSet.add:(Ljava/lang/Object;)Z
        61: pop
        62: aload         9
        64: bipush        60
        66: invokestatic  #1922               // Method java/lang/Integer.valueOf:(I)Ljava/lang/Integer;
        69: invokevirtual #1923               // Method java/util/TreeSet.add:(Ljava/lang/Object;)Z
        72: pop
        73: aload         9
        75: sipush        300
        78: invokestatic  #1922               // Method java/lang/Integer.valueOf:(I)Ljava/lang/Integer;
        81: invokevirtual #1923               // Method java/util/TreeSet.add:(Ljava/lang/Object;)Z
        84: pop
        85: aload         9
        87: sipush        600
        90: invokestatic  #1922               // Method java/lang/Integer.valueOf:(I)Ljava/lang/Integer;
        93: invokevirtual #1923               // Method java/util/TreeSet.add:(Ljava/lang/Object;)Z
        96: pop
        97: aload         9
        99: sipush        1800
       102: invokestatic  #1922               // Method java/lang/Integer.valueOf:(I)Ljava/lang/Integer;
       105: invokevirtual #1923               // Method java/util/TreeSet.add:(Ljava/lang/Object;)Z
       108: pop
       109: aload         9
       111: sipush        3600
       114: invokestatic  #1922               // Method java/lang/Integer.valueOf:(I)Ljava/lang/Integer;
       117: invokevirtual #1923               // Method java/util/TreeSet.add:(Ljava/lang/Object;)Z
       120: pop
       121: aload         9
       123: iload_1
       124: invokestatic  #1922               // Method java/lang/Integer.valueOf:(I)Ljava/lang/Integer;
       127: invokevirtual #1923               // Method java/util/TreeSet.add:(Ljava/lang/Object;)Z
       130: pop
       131: nop
       132: nop
       133: new           #762                // class java/util/ArrayList
       136: dup
       137: aload         7
       139: invokevirtual #1926               // Method java/util/TreeSet.size:()I
       142: iconst_1
       143: iadd
       144: invokespecial #1928               // Method java/util/ArrayList."<init>":(I)V
       147: astore        8
       149: aload         7
       151: checkcast     #88                 // class java/lang/Iterable
       154: astore        9
       156: aload         8
       158: checkcast     #765                // class java/util/Collection
       161: astore        10
       163: iconst_0
       164: istore        11
       166: iconst_0
       167: istore        12
       169: aload         9
       171: invokeinterface #92,  1           // InterfaceMethod java/lang/Iterable.iterator:()Ljava/util/Iterator;
       176: astore        13
       178: aload         13
       180: invokeinterface #97,  1           // InterfaceMethod java/util/Iterator.hasNext:()Z
       185: ifeq          277
       188: aload         13
       190: invokeinterface #101,  1          // InterfaceMethod java/util/Iterator.next:()Ljava/lang/Object;
       195: astore        14
       197: aload         10
       199: iload         12
       201: iinc          12, 1
       204: istore        15
       206: iload         15
       208: ifge          214
       211: invokestatic  #107                // Method kotlin/collections/CollectionsKt.throwIndexOverflow:()V
       214: iload         15
       216: aload         14
       218: checkcast     #109                // class java/lang/Number
       221: invokevirtual #112                // Method java/lang/Number.intValue:()I
       224: istore        16
       226: istore        17
       228: astore        19
       230: iconst_0
       231: istore        18
       233: new           #1930               // class org/fossify/commons/models/RadioItem
       236: dup
       237: iload         17
       239: aload_0
       240: checkcast     #19                 // class android/content/Context
       243: iload         16
       245: iload_2
       246: ifne          253
       249: iconst_1
       250: goto          254
       253: iconst_0
       254: invokestatic  #1934               // Method org/fossify/commons/extensions/ContextKt.getFormattedSeconds:(Landroid/content/Context;IZ)Ljava/lang/String;
       257: iload         16
       259: invokestatic  #1922               // Method java/lang/Integer.valueOf:(I)Ljava/lang/Integer;
       262: invokespecial #1937               // Method org/fossify/commons/models/RadioItem."<init>":(ILjava/lang/String;Ljava/lang/Object;)V
       265: aload         19
       267: swap
       268: invokeinterface #774,  2          // InterfaceMethod java/util/Collection.add:(Ljava/lang/Object;)Z
       273: pop
       274: goto          178
       277: nop
       278: iconst_0
       279: istore        9
       281: aload         7
       283: checkcast     #88                 // class java/lang/Iterable
       286: astore        10
       288: iconst_0
       289: istore        11
       291: iconst_0
       292: istore        12
       294: aload         10
       296: invokeinterface #92,  1           // InterfaceMethod java/lang/Iterable.iterator:()Ljava/util/Iterator;
       301: astore        13
       303: aload         13
       305: invokeinterface #97,  1           // InterfaceMethod java/util/Iterator.hasNext:()Z
       310: ifeq          369
       313: aload         13
       315: invokeinterface #101,  1          // InterfaceMethod java/util/Iterator.next:()Ljava/lang/Object;
       320: astore        14
       322: iload         12
       324: iinc          12, 1
       327: istore        15
       329: iload         15
       331: ifge          337
       334: invokestatic  #107                // Method kotlin/collections/CollectionsKt.throwIndexOverflow:()V
       337: iload         15
       339: aload         14
       341: checkcast     #109                // class java/lang/Number
       344: invokevirtual #112                // Method java/lang/Number.intValue:()I
       347: istore        16
       349: istore        17
       351: iconst_0
       352: istore        18
       354: iload         16
       356: iload_1
       357: if_icmpne     364
       360: iload         17
       362: istore        9
       364: nop
       365: nop
       366: goto          303
       369: nop
       370: aload         8
       372: new           #1930               // class org/fossify/commons/models/RadioItem
       375: dup
       376: bipush        -2
       378: aload_0
       379: getstatic     #1940               // Field org/fossify/commons/R$string.custom:I
       382: invokevirtual #500                // Method android/app/Activity.getString:(I)Ljava/lang/String;
       385: dup
       386: ldc_w         #502                // String getString(...)
       389: invokestatic  #505                // Method kotlin/jvm/internal/Intrinsics.checkNotNullExpressionValue:(Ljava/lang/Object;Ljava/lang/String;)V
       392: aconst_null
       393: iconst_4
       394: aconst_null
       395: invokespecial #1943               // Method org/fossify/commons/models/RadioItem."<init>":(ILjava/lang/String;Ljava/lang/Object;ILkotlin/jvm/internal/DefaultConstructorMarker;)V
       398: invokevirtual #1944               // Method java/util/ArrayList.add:(Ljava/lang/Object;)Z
       401: pop
       402: iload         4
       404: ifeq          439
       407: aload         8
       409: new           #1930               // class org/fossify/commons/models/RadioItem
       412: dup
       413: bipush        -3
       415: aload_0
       416: getstatic     #1947               // Field org/fossify/commons/R$string.during_day_at_hh_mm:I
       419: invokevirtual #500                // Method android/app/Activity.getString:(I)Ljava/lang/String;
       422: dup
       423: ldc_w         #502                // String getString(...)
       426: invokestatic  #505                // Method kotlin/jvm/internal/Intrinsics.checkNotNullExpressionValue:(Ljava/lang/Object;Ljava/lang/String;)V
       429: aconst_null
       430: iconst_4
       431: aconst_null
       432: invokespecial #1943               // Method org/fossify/commons/models/RadioItem."<init>":(ILjava/lang/String;Ljava/lang/Object;ILkotlin/jvm/internal/DefaultConstructorMarker;)V
       435: invokevirtual #1944               // Method java/util/ArrayList.add:(Ljava/lang/Object;)Z
       438: pop
       439: new           #1949               // class org/fossify/commons/dialogs/RadioGroupDialog
       442: dup
       443: aload_0
       444: aload         8
       446: iload         9
       448: iconst_0
       449: iload_2
       450: aload         5
       452: aload_0
       453: iload_3
       454: iload_1
       455: aload         6
       457: invokedynamic #1959,  0           // InvokeDynamic #53:invoke:(Landroid/app/Activity;ZILkotlin/jvm/functions/Function1;)Lkotlin/jvm/functions/Function1;
       462: bipush        8
       464: aconst_null
       465: invokespecial #1962               // Method org/fossify/commons/dialogs/RadioGroupDialog."<init>":(Landroid/app/Activity;Ljava/util/ArrayList;IIZLkotlin/jvm/functions/Function0;Lkotlin/jvm/functions/Function1;ILkotlin/jvm/internal/DefaultConstructorMarker;)V
       468: pop
       469: return

  public static void showPickSecondsDialog$default(android.app.Activity, int, boolean, boolean, boolean, kotlin.jvm.functions.Function0, kotlin.jvm.functions.Function1, int, java.lang.Object);
    Code:
         0: iload         7
         2: iconst_2
         3: iand
         4: ifeq          9
         7: iconst_0
         8: istore_2
         9: iload         7
        11: iconst_4
        12: iand
        13: ifeq          18
        16: iconst_0
        17: istore_3
        18: iload         7
        20: bipush        8
        22: iand
        23: ifeq          29
        26: iconst_0
        27: istore        4
        29: iload         7
        31: bipush        16
        33: iand
        34: ifeq          40
        37: aconst_null
        38: astore        5
        40: aload_0
        41: iload_1
        42: iload_2
        43: iload_3
        44: iload         4
        46: aload         5
        48: aload         6
        50: invokestatic  #1903               // Method showPickSecondsDialog:(Landroid/app/Activity;IZZZLkotlin/jvm/functions/Function0;Lkotlin/jvm/functions/Function1;)V
        53: return

  public static final void getAlarmSounds(org.fossify.commons.activities.BaseSimpleActivity, int, kotlin.jvm.functions.Function1<? super java.util.ArrayList<org.fossify.commons.models.AlarmSound>, kotlin.Unit>);
    Code:
         0: aload_0
         1: ldc           #9                  // String <this>
         3: invokestatic  #15                 // Method kotlin/jvm/internal/Intrinsics.checkNotNullParameter:(Ljava/lang/Object;Ljava/lang/String;)V
         6: aload_2
         7: ldc_w         #1467               // String callback
        10: invokestatic  #15                 // Method kotlin/jvm/internal/Intrinsics.checkNotNullParameter:(Ljava/lang/Object;Ljava/lang/String;)V
        13: new           #762                // class java/util/ArrayList
        16: dup
        17: invokespecial #763                // Method java/util/ArrayList."<init>":()V
        20: astore_3
        21: new           #1979               // class android/media/RingtoneManager
        24: dup
        25: aload_0
        26: checkcast     #63                 // class android/app/Activity
        29: invokespecial #1980               // Method android/media/RingtoneManager."<init>":(Landroid/app/Activity;)V
        32: astore        4
        34: aload         4
        36: iload_1
        37: invokevirtual #1982               // Method android/media/RingtoneManager.setType:(I)V
        40: nop
        41: aload         4
        43: invokevirtual #1986               // Method android/media/RingtoneManager.getCursor:()Landroid/database/Cursor;
        46: astore        5
        48: iconst_1
        49: istore        6
        51: aload_0
        52: checkcast     #19                 // class android/content/Context
        55: iload_1
        56: invokestatic  #1990               // Method org/fossify/commons/extensions/ContextKt.getDefaultAlarmSound:(Landroid/content/Context;I)Lorg/fossify/commons/models/AlarmSound;
        59: astore        7
        61: new           #1992               // class org/fossify/commons/models/AlarmSound
        64: dup
        65: iload         6
        67: iinc          6, 1
        70: aload         7
        72: invokevirtual #1995               // Method org/fossify/commons/models/AlarmSound.getTitle:()Ljava/lang/String;
        75: aload         7
        77: invokevirtual #1998               // Method org/fossify/commons/models/AlarmSound.getUri:()Ljava/lang/String;
        80: invokespecial #2001               // Method org/fossify/commons/models/AlarmSound."<init>":(ILjava/lang/String;Ljava/lang/String;)V
        83: astore        8
        85: aload_3
        86: aload         8
        88: invokevirtual #1944               // Method java/util/ArrayList.add:(Ljava/lang/Object;)Z
        91: pop
        92: new           #1992               // class org/fossify/commons/models/AlarmSound
        95: dup
        96: iload         6
        98: iinc          6, 1
       101: aload_0
       102: getstatic     #2004               // Field org/fossify/commons/R$string.no_sound:I
       105: invokevirtual #2005               // Method org/fossify/commons/activities/BaseSimpleActivity.getString:(I)Ljava/lang/String;
       108: dup
       109: ldc_w         #502                // String getString(...)
       112: invokestatic  #505                // Method kotlin/jvm/internal/Intrinsics.checkNotNullExpressionValue:(Ljava/lang/Object;Ljava/lang/String;)V
       115: ldc_w         #2007               // String silent
       118: invokespecial #2001               // Method org/fossify/commons/models/AlarmSound."<init>":(ILjava/lang/String;Ljava/lang/String;)V
       121: astore        9
       123: aload_3
       124: aload         9
       126: invokevirtual #1944               // Method java/util/ArrayList.add:(Ljava/lang/Object;)Z
       129: pop
       130: aload         5
       132: invokeinterface #2012,  1         // InterfaceMethod android/database/Cursor.moveToNext:()Z
       137: ifeq          250
       140: aload         5
       142: iconst_1
       143: invokeinterface #2013,  2         // InterfaceMethod android/database/Cursor.getString:(I)Ljava/lang/String;
       148: astore        10
       150: aload         5
       152: iconst_2
       153: invokeinterface #2013,  2         // InterfaceMethod android/database/Cursor.getString:(I)Ljava/lang/String;
       158: astore        11
       160: aload         5
       162: iconst_0
       163: invokeinterface #2013,  2         // InterfaceMethod android/database/Cursor.getString:(I)Ljava/lang/String;
       168: astore        12
       170: aload         11
       172: astore        13
       174: aload         13
       176: invokestatic  #899                // Method kotlin/jvm/internal/Intrinsics.checkNotNull:(Ljava/lang/Object;)V
       179: aload         13
       181: aload         12
       183: invokestatic  #899                // Method kotlin/jvm/internal/Intrinsics.checkNotNull:(Ljava/lang/Object;)V
       186: aload         12
       188: iconst_0
       189: iconst_2
       190: aconst_null
       191: invokestatic  #2016               // Method kotlin/text/StringsKt.endsWith$default:(Ljava/lang/String;Ljava/lang/String;ZILjava/lang/Object;)Z
       194: ifne          208
       197: aload         11
       199: aload         12
       201: invokedynamic #2019,  0           // InvokeDynamic #54:makeConcatWithConstants:(Ljava/lang/String;Ljava/lang/String;)Ljava/lang/String;
       206: astore        11
       208: new           #1992               // class org/fossify/commons/models/AlarmSound
       211: dup
       212: iload         6
       214: iinc          6, 1
       217: aload         10
       219: invokestatic  #899                // Method kotlin/jvm/internal/Intrinsics.checkNotNull:(Ljava/lang/Object;)V
       222: aload         10
       224: aload         11
       226: astore        14
       228: aload         14
       230: invokestatic  #899                // Method kotlin/jvm/internal/Intrinsics.checkNotNull:(Ljava/lang/Object;)V
       233: aload         14
       235: invokespecial #2001               // Method org/fossify/commons/models/AlarmSound."<init>":(ILjava/lang/String;Ljava/lang/String;)V
       238: astore        13
       240: aload_3
       241: aload         13
       243: invokevirtual #1944               // Method java/util/ArrayList.add:(Ljava/lang/Object;)Z
       246: pop
       247: goto          130
       250: aload_2
       251: aload_3
       252: invokeinterface #1055,  2         // InterfaceMethod kotlin/jvm/functions/Function1.invoke:(Ljava/lang/Object;)Ljava/lang/Object;
       257: pop
       258: goto          315
       261: astore        5
       263: aload         5
       265: instanceof    #2021               // class java/lang/SecurityException
       268: ifeq          289
       271: aload_0
       272: iconst_1
       273: aload_0
       274: iload_1
       275: aload_2
       276: aload         5
       278: invokedynamic #2029,  0           // InvokeDynamic #55:invoke:(Lorg/fossify/commons/activities/BaseSimpleActivity;ILkotlin/jvm/functions/Function1;Ljava/lang/Exception;)Lkotlin/jvm/functions/Function1;
       283: invokevirtual #672                // Method org/fossify/commons/activities/BaseSimpleActivity.handlePermission:(ILkotlin/jvm/functions/Function1;)V
       286: goto          315
       289: aload_0
       290: checkcast     #19                 // class android/content/Context
       293: aload         5
       295: iconst_0
       296: iconst_2
       297: aconst_null
       298: invokestatic  #731                // Method org/fossify/commons/extensions/ContextKt.showErrorToast$default:(Landroid/content/Context;Ljava/lang/Exception;IILjava/lang/Object;)V
       301: aload_2
       302: new           #762                // class java/util/ArrayList
       305: dup
       306: invokespecial #763                // Method java/util/ArrayList."<init>":()V
       309: invokeinterface #1055,  2         // InterfaceMethod kotlin/jvm/functions/Function1.invoke:(Ljava/lang/Object;)Ljava/lang/Object;
       314: pop
       315: return
      Exception table:
         from    to  target type
            40   258   261   Class java/lang/Exception

  public static final void showModdedAppWarning(org.fossify.commons.activities.BaseSimpleActivity);
    Code:
         0: aload_0
         1: ldc           #9                  // String <this>
         3: invokestatic  #15                 // Method kotlin/jvm/internal/Intrinsics.checkNotNullParameter:(Ljava/lang/Object;Ljava/lang/String;)V
         6: ldc_w         #2046               // String You are using a fake version of the app. For your own safety download the original one from www.fossify.org. Thanks
         9: astore_1
        10: new           #2048               // class org/fossify/commons/dialogs/ConfirmationDialog
        13: dup
        14: aload_0
        15: checkcast     #63                 // class android/app/Activity
        18: aload_1
        19: iconst_0
        20: getstatic     #2051               // Field org/fossify/commons/R$string.ok:I
        23: iconst_0
        24: iconst_0
        25: aconst_null
        26: aload_0
        27: invokedynamic #2059,  0           // InvokeDynamic #56:invoke:(Lorg/fossify/commons/activities/BaseSimpleActivity;)Lkotlin/jvm/functions/Function0;
        32: bipush        100
        34: aconst_null
        35: invokespecial #2062               // Method org/fossify/commons/dialogs/ConfirmationDialog."<init>":(Landroid/app/Activity;Ljava/lang/String;IIIZLjava/lang/String;Lkotlin/jvm/functions/Function0;ILkotlin/jvm/internal/DefaultConstructorMarker;)V
        38: pop
        39: return

  public static final boolean checkAppSideloading(android.app.Activity);
    Code:
         0: aload_0
         1: ldc           #9                  // String <this>
         3: invokestatic  #15                 // Method kotlin/jvm/internal/Intrinsics.checkNotNullParameter:(Ljava/lang/Object;Ljava/lang/String;)V
         6: aload_0
         7: checkcast     #19                 // class android/content/Context
        10: invokestatic  #25                 // Method org/fossify/commons/extensions/ContextKt.getBaseConfig:(Landroid/content/Context;)Lorg/fossify/commons/helpers/BaseConfig;
        13: invokevirtual #2068               // Method org/fossify/commons/helpers/BaseConfig.getAppSideloadingStatus:()I
        16: tableswitch   { // 1 to 2
                       1: 40
                       2: 44
                 default: 48
            }
        40: iconst_1
        41: goto          52
        44: iconst_0
        45: goto          52
        48: aload_0
        49: invokestatic  #2071               // Method isAppSideloaded:(Landroid/app/Activity;)Z
        52: istore_1
        53: aload_0
        54: checkcast     #19                 // class android/content/Context
        57: invokestatic  #25                 // Method org/fossify/commons/extensions/ContextKt.getBaseConfig:(Landroid/content/Context;)Lorg/fossify/commons/helpers/BaseConfig;
        60: iload_1
        61: ifeq          68
        64: iconst_1
        65: goto          69
        68: iconst_2
        69: invokevirtual #2074               // Method org/fossify/commons/helpers/BaseConfig.setAppSideloadingStatus:(I)V
        72: iload_1
        73: ifeq          80
        76: aload_0
        77: invokestatic  #2077               // Method showSideloadingDialog:(Landroid/app/Activity;)V
        80: iload_1
        81: ireturn

  public static final boolean isAppSideloaded(android.app.Activity);
    Code:
         0: aload_0
         1: ldc           #9                  // String <this>
         3: invokestatic  #15                 // Method kotlin/jvm/internal/Intrinsics.checkNotNullParameter:(Ljava/lang/Object;Ljava/lang/String;)V
         6: nop
         7: aload_0
         8: getstatic     #2082               // Field org/fossify/commons/R$drawable.ic_camera_vector:I
        11: invokevirtual #2085               // Method android/app/Activity.getDrawable:(I)Landroid/graphics/drawable/Drawable;
        14: pop
        15: iconst_0
        16: istore_1
        17: goto          23
        20: astore_2
        21: iconst_1
        22: istore_1
        23: iload_1
        24: ireturn
      Exception table:
         from    to  target type
             6    17    20   Class java/lang/Exception

  public static final void showSideloadingDialog(android.app.Activity);
    Code:
         0: aload_0
         1: ldc           #9                  // String <this>
         3: invokestatic  #15                 // Method kotlin/jvm/internal/Intrinsics.checkNotNullParameter:(Ljava/lang/Object;Ljava/lang/String;)V
         6: new           #2088               // class org/fossify/commons/dialogs/AppSideloadedDialog
         9: dup
        10: aload_0
        11: aload_0
        12: invokedynamic #2096,  0           // InvokeDynamic #57:invoke:(Landroid/app/Activity;)Lkotlin/jvm/functions/Function0;
        17: invokespecial #2098               // Method org/fossify/commons/dialogs/AppSideloadedDialog."<init>":(Landroid/app/Activity;Lkotlin/jvm/functions/Function0;)V
        20: pop
        21: return

  public static final void onApplyWindowInsets(android.app.Activity, kotlin.jvm.functions.Function1<? super androidx.core.view.WindowInsetsCompat, kotlin.Unit>);
    Code:
         0: aload_0
         1: ldc           #9                  // String <this>
         3: invokestatic  #15                 // Method kotlin/jvm/internal/Intrinsics.checkNotNullParameter:(Ljava/lang/Object;Ljava/lang/String;)V
         6: aload_1
         7: ldc_w         #1467               // String callback
        10: invokestatic  #15                 // Method kotlin/jvm/internal/Intrinsics.checkNotNullParameter:(Ljava/lang/Object;Ljava/lang/String;)V
        13: aload_0
        14: invokevirtual #1433               // Method android/app/Activity.getWindow:()Landroid/view/Window;
        17: invokevirtual #2104               // Method android/view/Window.getDecorView:()Landroid/view/View;
        20: aload_1
        21: invokedynamic #2114,  0           // InvokeDynamic #58:onApplyWindowInsets:(Lkotlin/jvm/functions/Function1;)Landroid/view/View$OnApplyWindowInsetsListener;
        26: invokevirtual #2118               // Method android/view/View.setOnApplyWindowInsetsListener:(Landroid/view/View$OnApplyWindowInsetsListener;)V
        29: return

  public static final void overrideActivityTransition(android.app.Activity, int, int, boolean);
    Code:
         0: aload_0
         1: ldc           #9                  // String <this>
         3: invokestatic  #15                 // Method kotlin/jvm/internal/Intrinsics.checkNotNullParameter:(Ljava/lang/Object;Ljava/lang/String;)V
         6: invokestatic  #2124               // Method org/fossify/commons/helpers/ConstantsKt.isUpsideDownCakePlus:()Z
         9: ifeq          34
        12: iload_3
        13: ifeq          20
        16: iconst_1
        17: goto          21
        20: iconst_0
        21: istore        4
        23: aload_0
        24: iload         4
        26: iload_1
        27: iload_2
        28: invokevirtual #2126               // Method android/app/Activity.overrideActivityTransition:(III)V
        31: goto          40
        34: aload_0
        35: iload_1
        36: iload_2
        37: invokevirtual #2130               // Method android/app/Activity.overridePendingTransition:(II)V
        40: return

  public static void overrideActivityTransition$default(android.app.Activity, int, int, boolean, int, java.lang.Object);
    Code:
         0: iload         4
         2: iconst_4
         3: iand
         4: ifeq          9
         7: iconst_0
         8: istore_3
         9: aload_0
        10: iload_1
        11: iload_2
        12: iload_3
        13: invokestatic  #2139               // Method overrideActivityTransition:(Landroid/app/Activity;IIZ)V
        16: return

  public static final void maybeShowNumberPickerDialog(android.app.Activity, java.util.List<org.fossify.commons.models.PhoneNumber>, boolean, kotlin.jvm.functions.Function1<? super org.fossify.commons.models.PhoneNumber, kotlin.Unit>);
    Code:
         0: aload_0
         1: ldc           #9                  // String <this>
         3: invokestatic  #15                 // Method kotlin/jvm/internal/Intrinsics.checkNotNullParameter:(Ljava/lang/Object;Ljava/lang/String;)V
         6: aload_1
         7: ldc_w         #2144               // String phoneNumbers
        10: invokestatic  #15                 // Method kotlin/jvm/internal/Intrinsics.checkNotNullParameter:(Ljava/lang/Object;Ljava/lang/String;)V
        13: aload_3
        14: ldc_w         #1467               // String callback
        17: invokestatic  #15                 // Method kotlin/jvm/internal/Intrinsics.checkNotNullParameter:(Ljava/lang/Object;Ljava/lang/String;)V
        20: nop
        21: aload_1
        22: invokeinterface #2145,  1         // InterfaceMethod java/util/List.size:()I
        27: iconst_1
        28: if_icmpne     48
        31: aload_3
        32: aload_1
        33: invokestatic  #988                // Method kotlin/collections/CollectionsKt.first:(Ljava/util/List;)Ljava/lang/Object;
        36: invokeinterface #1055,  2         // InterfaceMethod kotlin/jvm/functions/Function1.invoke:(Ljava/lang/Object;)Ljava/lang/Object;
        41: pop
        42: getstatic     #1537               // Field kotlin/Unit.INSTANCE:Lkotlin/Unit;
        45: goto          354
        48: aload_1
        49: invokeinterface #2145,  1         // InterfaceMethod java/util/List.size:()I
        54: iconst_1
        55: if_icmple     338
        58: iload_2
        59: ifeq          140
        62: aload_1
        63: checkcast     #88                 // class java/lang/Iterable
        66: astore        6
        68: aload         6
        70: invokeinterface #92,  1           // InterfaceMethod java/lang/Iterable.iterator:()Ljava/util/Iterator;
        75: astore        7
        77: aload         7
        79: invokeinterface #97,  1           // InterfaceMethod java/util/Iterator.hasNext:()Z
        84: ifeq          119
        87: aload         7
        89: invokeinterface #101,  1          // InterfaceMethod java/util/Iterator.next:()Ljava/lang/Object;
        94: astore        8
        96: aload         8
        98: checkcast     #2147               // class org/fossify/commons/models/PhoneNumber
       101: astore        9
       103: iconst_0
       104: istore        10
       106: aload         9
       108: invokevirtual #2150               // Method org/fossify/commons/models/PhoneNumber.isPrimary:()Z
       111: ifeq          77
       114: aload         8
       116: goto          120
       119: aconst_null
       120: checkcast     #2147               // class org/fossify/commons/models/PhoneNumber
       123: astore        4
       125: aload         4
       127: ifnull        140
       130: aload_3
       131: aload         4
       133: invokeinterface #1055,  2         // InterfaceMethod kotlin/jvm/functions/Function1.invoke:(Ljava/lang/Object;)Ljava/lang/Object;
       138: pop
       139: return
       140: aload_1
       141: checkcast     #88                 // class java/lang/Iterable
       144: astore        5
       146: iconst_0
       147: istore        6
       149: aload         5
       151: astore        7
       153: new           #762                // class java/util/ArrayList
       156: dup
       157: aload         5
       159: bipush        10
       161: invokestatic  #2154               // Method kotlin/collections/CollectionsKt.collectionSizeOrDefault:(Ljava/lang/Iterable;I)I
       164: invokespecial #1928               // Method java/util/ArrayList."<init>":(I)V
       167: checkcast     #765                // class java/util/Collection
       170: astore        8
       172: iconst_0
       173: istore        9
       175: iconst_0
       176: istore        10
       178: aload         7
       180: invokeinterface #92,  1           // InterfaceMethod java/lang/Iterable.iterator:()Ljava/util/Iterator;
       185: astore        11
       187: aload         11
       189: invokeinterface #97,  1           // InterfaceMethod java/util/Iterator.hasNext:()Z
       194: ifeq          294
       197: aload         11
       199: invokeinterface #101,  1          // InterfaceMethod java/util/Iterator.next:()Ljava/lang/Object;
       204: astore        12
       206: aload         8
       208: iload         10
       210: iinc          10, 1
       213: istore        13
       215: iload         13
       217: ifge          223
       220: invokestatic  #107                // Method kotlin/collections/CollectionsKt.throwIndexOverflow:()V
       223: iload         13
       225: aload         12
       227: checkcast     #2147               // class org/fossify/commons/models/PhoneNumber
       230: astore        14
       232: istore        15
       234: astore        18
       236: iconst_0
       237: istore        16
       239: aload_0
       240: checkcast     #19                 // class android/content/Context
       243: aload         14
       245: invokevirtual #2157               // Method org/fossify/commons/models/PhoneNumber.getType:()I
       248: aload         14
       250: invokevirtual #2160               // Method org/fossify/commons/models/PhoneNumber.getLabel:()Ljava/lang/String;
       253: invokestatic  #2164               // Method org/fossify/commons/extensions/ContextKt.getPhoneNumberTypeText:(Landroid/content/Context;ILjava/lang/String;)Ljava/lang/String;
       256: astore        17
       258: new           #1930               // class org/fossify/commons/models/RadioItem
       261: dup
       262: iload         15
       264: aload         14
       266: invokevirtual #2167               // Method org/fossify/commons/models/PhoneNumber.getValue:()Ljava/lang/String;
       269: aload         17
       271: invokedynamic #2170,  0           // InvokeDynamic #59:makeConcatWithConstants:(Ljava/lang/String;Ljava/lang/String;)Ljava/lang/String;
       276: aload         14
       278: invokespecial #1937               // Method org/fossify/commons/models/RadioItem."<init>":(ILjava/lang/String;Ljava/lang/Object;)V
       281: nop
       282: aload         18
       284: swap
       285: invokeinterface #774,  2          // InterfaceMethod java/util/Collection.add:(Ljava/lang/Object;)Z
       290: pop
       291: goto          187
       294: aload         8
       296: checkcast     #781                // class java/util/List
       299: nop
       300: astore        4
       302: new           #1949               // class org/fossify/commons/dialogs/RadioGroupDialog
       305: dup
       306: aload_0
       307: new           #762                // class java/util/ArrayList
       310: dup
       311: aload         4
       313: checkcast     #765                // class java/util/Collection
       316: invokespecial #2173               // Method java/util/ArrayList."<init>":(Ljava/util/Collection;)V
       319: iconst_0
       320: iconst_0
       321: iconst_0
       322: aconst_null
       323: aload_3
       324: invokedynamic #2181,  0           // InvokeDynamic #60:invoke:(Lkotlin/jvm/functions/Function1;)Lkotlin/jvm/functions/Function1;
       329: bipush        60
       331: aconst_null
       332: invokespecial #1962               // Method org/fossify/commons/dialogs/RadioGroupDialog."<init>":(Landroid/app/Activity;Ljava/util/ArrayList;IIZLkotlin/jvm/functions/Function0;Lkotlin/jvm/functions/Function1;ILkotlin/jvm/internal/DefaultConstructorMarker;)V
       335: goto          354
       338: aload_0
       339: checkcast     #19                 // class android/content/Context
       342: getstatic     #2184               // Field org/fossify/commons/R$string.no_phone_number_found:I
       345: iconst_0
       346: iconst_2
       347: aconst_null
       348: invokestatic  #383                // Method org/fossify/commons/extensions/ContextKt.toast$default:(Landroid/content/Context;IIILjava/lang/Object;)V
       351: getstatic     #1537               // Field kotlin/Unit.INSTANCE:Lkotlin/Unit;
       354: pop
       355: return

  public static void maybeShowNumberPickerDialog$default(android.app.Activity, java.util.List, boolean, kotlin.jvm.functions.Function1, int, java.lang.Object);
    Code:
         0: iload         4
         2: iconst_2
         3: iand
         4: ifeq          9
         7: iconst_0
         8: istore_2
         9: aload_0
        10: aload_1
        11: iload_2
        12: aload_3
        13: invokestatic  #2200               // Method maybeShowNumberPickerDialog:(Landroid/app/Activity;Ljava/util/List;ZLkotlin/jvm/functions/Function1;)V
        16: return
}
