Compiled from "BaseSimpleActivity.kt"
public abstract class org.fossify.commons.activities.BaseSimpleActivity extends org.fossify.commons.activities.EdgeToEdgeActivity {
  public static final org.fossify.commons.activities.BaseSimpleActivity$Companion Companion;

  public static final int $stable;

  public org.fossify.commons.activities.BaseSimpleActivity();
    Code:
         0: aload_0
         1: invokespecial #8                  // Method org/fossify/commons/activities/EdgeToEdgeActivity."<init>":()V
         4: aload_0
         5: iconst_1
         6: putfield      #12                 // Field useDynamicTheme:Z
         9: aload_0
        10: ldc           #14                 // String
        12: putfield      #18                 // Field checkedDocumentPath:Ljava/lang/String;
        15: aload_0
        16: new           #20                 // class java/util/LinkedHashMap
        19: dup
        20: invokespecial #21                 // Method java/util/LinkedHashMap."<init>":()V
        23: putfield      #25                 // Field configItemsToExport:Ljava/util/LinkedHashMap;
        26: aload_0
        27: new           #27                 // class org/fossify/commons/activities/BaseSimpleActivity$copyMoveListener$1
        30: dup
        31: aload_0
        32: invokespecial #30                 // Method org/fossify/commons/activities/BaseSimpleActivity$copyMoveListener$1."<init>":(Lorg/fossify/commons/activities/BaseSimpleActivity;)V
        35: checkcast     #32                 // class org/fossify/commons/interfaces/CopyMoveListener
        38: putfield      #36                 // Field copyMoveListener:Lorg/fossify/commons/interfaces/CopyMoveListener;
        41: return

  public final kotlin.jvm.functions.Function1<java.lang.String, kotlin.Unit> getCopyMoveCallback();
    Code:
         0: aload_0
         1: getfield      #46                 // Field copyMoveCallback:Lkotlin/jvm/functions/Function1;
         4: areturn

  public final void setCopyMoveCallback(kotlin.jvm.functions.Function1<? super java.lang.String, kotlin.Unit>);
    Code:
         0: aload_0
         1: aload_1
         2: putfield      #46                 // Field copyMoveCallback:Lkotlin/jvm/functions/Function1;
         5: return

  public final kotlin.jvm.functions.Function1<java.lang.Boolean, kotlin.Unit> getActionOnPermission();
    Code:
         0: aload_0
         1: getfield      #55                 // Field actionOnPermission:Lkotlin/jvm/functions/Function1;
         4: areturn

  public final void setActionOnPermission(kotlin.jvm.functions.Function1<? super java.lang.Boolean, kotlin.Unit>);
    Code:
         0: aload_0
         1: aload_1
         2: putfield      #55                 // Field actionOnPermission:Lkotlin/jvm/functions/Function1;
         5: return

  public final boolean isAskingPermissions();
    Code:
         0: aload_0
         1: getfield      #61                 // Field isAskingPermissions:Z
         4: ireturn

  public final void setAskingPermissions(boolean);
    Code:
         0: aload_0
         1: iload_1
         2: putfield      #61                 // Field isAskingPermissions:Z
         5: return

  public final boolean getUseDynamicTheme();
    Code:
         0: aload_0
         1: getfield      #12                 // Field useDynamicTheme:Z
         4: ireturn

  public final void setUseDynamicTheme(boolean);
    Code:
         0: aload_0
         1: iload_1
         2: putfield      #12                 // Field useDynamicTheme:Z
         5: return

  public final java.lang.String getCheckedDocumentPath();
    Code:
         0: aload_0
         1: getfield      #18                 // Field checkedDocumentPath:Ljava/lang/String;
         4: areturn

  public final void setCheckedDocumentPath(java.lang.String);
    Code:
         0: aload_1
         1: ldc           #71                 // String <set-?>
         3: invokestatic  #77                 // Method kotlin/jvm/internal/Intrinsics.checkNotNullParameter:(Ljava/lang/Object;Ljava/lang/String;)V
         6: aload_0
         7: aload_1
         8: putfield      #18                 // Field checkedDocumentPath:Ljava/lang/String;
        11: return

  public final java.util.LinkedHashMap<java.lang.String, java.lang.Object> getConfigItemsToExport();
    Code:
         0: aload_0
         1: getfield      #25                 // Field configItemsToExport:Ljava/util/LinkedHashMap;
         4: areturn

  public final void setConfigItemsToExport(java.util.LinkedHashMap<java.lang.String, java.lang.Object>);
    Code:
         0: aload_1
         1: ldc           #71                 // String <set-?>
         3: invokestatic  #77                 // Method kotlin/jvm/internal/Intrinsics.checkNotNullParameter:(Ljava/lang/Object;Ljava/lang/String;)V
         6: aload_0
         7: aload_1
         8: putfield      #25                 // Field configItemsToExport:Ljava/util/LinkedHashMap;
        11: return

  public abstract java.util.ArrayList<java.lang.Integer> getAppIconIDs();

  public abstract java.lang.String getAppLauncherName();

  public abstract java.lang.String getRepositoryName();

  protected boolean onBackPressedCompat();
    Code:
         0: iconst_0
         1: ireturn

  protected final void setBackHandlingEnabled(boolean);
    Code:
         0: aload_0
         1: getfield      #94                 // Field backCallback:Landroidx/activity/OnBackPressedCallback;
         4: dup
         5: ifnonnull     15
         8: pop
         9: ldc           #95                 // String backCallback
        11: invokestatic  #98                 // Method kotlin/jvm/internal/Intrinsics.throwUninitializedPropertyAccessException:(Ljava/lang/String;)V
        14: aconst_null
        15: iload_1
        16: invokevirtual #103                // Method androidx/activity/OnBackPressedCallback.setEnabled:(Z)V
        19: return

  protected final void performDefaultBack();
    Code:
         0: aload_0
         1: getfield      #94                 // Field backCallback:Landroidx/activity/OnBackPressedCallback;
         4: dup
         5: ifnonnull     15
         8: pop
         9: ldc           #95                 // String backCallback
        11: invokestatic  #98                 // Method kotlin/jvm/internal/Intrinsics.throwUninitializedPropertyAccessException:(Ljava/lang/String;)V
        14: aconst_null
        15: iconst_0
        16: invokevirtual #103                // Method androidx/activity/OnBackPressedCallback.setEnabled:(Z)V
        19: aload_0
        20: invokevirtual #109                // Method getOnBackPressedDispatcher:()Landroidx/activity/OnBackPressedDispatcher;
        23: invokevirtual #114                // Method androidx/activity/OnBackPressedDispatcher.onBackPressed:()V
        26: aload_0
        27: getfield      #94                 // Field backCallback:Landroidx/activity/OnBackPressedCallback;
        30: dup
        31: ifnonnull     41
        34: pop
        35: ldc           #95                 // String backCallback
        37: invokestatic  #98                 // Method kotlin/jvm/internal/Intrinsics.throwUninitializedPropertyAccessException:(Ljava/lang/String;)V
        40: aconst_null
        41: iconst_1
        42: invokevirtual #103                // Method androidx/activity/OnBackPressedCallback.setEnabled:(Z)V
        45: return

  protected void onCreate(android.os.Bundle);
    Code:
         0: aload_0
         1: getfield      #12                 // Field useDynamicTheme:Z
         4: ifeq          22
         7: aload_0
         8: aload_0
         9: checkcast     #118                // class android/app/Activity
        12: iconst_0
        13: iconst_1
        14: iconst_1
        15: aconst_null
        16: invokestatic  #124                // Method org/fossify/commons/extensions/Activity_themesKt.getThemeId$default:(Landroid/app/Activity;IZILjava/lang/Object;)I
        19: invokevirtual #128                // Method setTheme:(I)V
        22: aload_0
        23: invokespecial #131                // Method installFontInflaterFactory:()V
        26: aload_0
        27: aload_1
        28: invokespecial #133                // Method org/fossify/commons/activities/EdgeToEdgeActivity.onCreate:(Landroid/os/Bundle;)V
        31: aload_0
        32: invokevirtual #137                // Method getWindow:()Landroid/view/Window;
        35: invokestatic  #143                // Method androidx/core/view/WindowCompat.enableEdgeToEdge:(Landroid/view/Window;)V
        38: aload_0
        39: invokevirtual #146                // Method registerBackPressedCallback:()V
        42: aload_0
        43: invokevirtual #149                // Method getPackageName:()Ljava/lang/String;
        46: dup
        47: ldc           #151                // String getPackageName(...)
        49: invokestatic  #154                // Method kotlin/jvm/internal/Intrinsics.checkNotNullExpressionValue:(Ljava/lang/Object;Ljava/lang/String;)V
        52: ldc           #156                // String org.fossify.
        54: iconst_1
        55: invokestatic  #162                // Method kotlin/text/StringsKt.startsWith:(Ljava/lang/String;Ljava/lang/String;Z)Z
        58: ifne          102
        61: new           #164                // class kotlin/ranges/IntRange
        64: dup
        65: iconst_0
        66: bipush        50
        68: invokespecial #167                // Method kotlin/ranges/IntRange."<init>":(II)V
        71: checkcast     #169                // class kotlin/ranges/ClosedRange
        74: invokestatic  #175                // Method org/fossify/commons/extensions/IntKt.random:(Lkotlin/ranges/ClosedRange;)I
        77: bipush        10
        79: if_icmpeq     98
        82: aload_0
        83: checkcast     #177                // class android/content/Context
        86: invokestatic  #183                // Method org/fossify/commons/extensions/ContextKt.getBaseConfig:(Landroid/content/Context;)Lorg/fossify/commons/helpers/BaseConfig;
        89: invokevirtual #189                // Method org/fossify/commons/helpers/BaseConfig.getAppRunCount:()I
        92: bipush        100
        94: irem
        95: ifne          102
        98: aload_0
        99: invokestatic  #194                // Method org/fossify/commons/extensions/ActivityKt.showModdedAppWarning:(Lorg/fossify/commons/activities/BaseSimpleActivity;)V
       102: return

  protected void onResume();
    Code:
         0: aload_0
         1: invokespecial #234                // Method org/fossify/commons/activities/EdgeToEdgeActivity.onResume:()V
         4: aload_0
         5: getfield      #12                 // Field useDynamicTheme:Z
         8: ifeq          37
        11: aload_0
        12: aload_0
        13: checkcast     #118                // class android/app/Activity
        16: iconst_0
        17: iconst_1
        18: iconst_1
        19: aconst_null
        20: invokestatic  #124                // Method org/fossify/commons/extensions/Activity_themesKt.getThemeId$default:(Landroid/app/Activity;IZILjava/lang/Object;)I
        23: invokevirtual #128                // Method setTheme:(I)V
        26: aload_0
        27: aload_0
        28: checkcast     #177                // class android/content/Context
        31: invokestatic  #240                // Method org/fossify/commons/extensions/Context_stylingKt.getProperBackgroundColor:(Landroid/content/Context;)I
        34: invokevirtual #243                // Method updateBackgroundColor:(I)V
        37: aload_0
        38: invokevirtual #246                // Method updateRecentsAppIcon:()V
        41: aload_0
        42: checkcast     #118                // class android/app/Activity
        45: sipush        1012
        48: invokestatic  #252                // Method org/fossify/commons/activities/AppLockActivityKt.maybeLaunchAppUnlockActivity:(Landroid/app/Activity;I)V
        51: return

  protected void onDestroy();
    Code:
         0: aload_0
         1: invokespecial #255                // Method org/fossify/commons/activities/EdgeToEdgeActivity.onDestroy:()V
         4: aconst_null
         5: putstatic     #258                // Field funAfterSAFPermission:Lkotlin/jvm/functions/Function1;
         8: aload_0
         9: aconst_null
        10: putfield      #55                 // Field actionOnPermission:Lkotlin/jvm/functions/Function1;
        13: return

  public void onConfigurationChanged(android.content.res.Configuration);
    Code:
         0: aload_1
         1: ldc_w         #262                // String newConfig
         4: invokestatic  #77                 // Method kotlin/jvm/internal/Intrinsics.checkNotNullParameter:(Ljava/lang/Object;Ljava/lang/String;)V
         7: aload_0
         8: aload_1
         9: invokespecial #264                // Method org/fossify/commons/activities/EdgeToEdgeActivity.onConfigurationChanged:(Landroid/content/res/Configuration;)V
        12: aload_0
        13: ldc_w         #265                // int 16908290
        16: invokevirtual #269                // Method findViewById:(I)Landroid/view/View;
        19: invokestatic  #275                // Method androidx/core/view/ViewCompat.requestApplyInsets:(Landroid/view/View;)V
        22: return

  public boolean onOptionsItemSelected(android.view.MenuItem);
    Code:
         0: aload_1
         1: ldc_w         #280                // String item
         4: invokestatic  #77                 // Method kotlin/jvm/internal/Intrinsics.checkNotNullParameter:(Ljava/lang/Object;Ljava/lang/String;)V
         7: aload_1
         8: invokeinterface #285,  1          // InterfaceMethod android/view/MenuItem.getItemId:()I
        13: ldc_w         #286                // int 16908332
        16: if_icmpne     33
        19: aload_0
        20: checkcast     #118                // class android/app/Activity
        23: invokestatic  #290                // Method org/fossify/commons/extensions/ActivityKt.hideKeyboard:(Landroid/app/Activity;)V
        26: aload_0
        27: invokevirtual #293                // Method finish:()V
        30: goto          39
        33: aload_0
        34: aload_1
        35: invokespecial #295                // Method org/fossify/commons/activities/EdgeToEdgeActivity.onOptionsItemSelected:(Landroid/view/MenuItem;)Z
        38: ireturn
        39: iconst_1
        40: ireturn

  protected void attachBaseContext(android.content.Context);
    Code:
         0: aload_1
         1: ldc_w         #300                // String newBase
         4: invokestatic  #77                 // Method kotlin/jvm/internal/Intrinsics.checkNotNullParameter:(Ljava/lang/Object;Ljava/lang/String;)V
         7: aload_1
         8: invokestatic  #183                // Method org/fossify/commons/extensions/ContextKt.getBaseConfig:(Landroid/content/Context;)Lorg/fossify/commons/helpers/BaseConfig;
        11: invokevirtual #303                // Method org/fossify/commons/helpers/BaseConfig.getUseEnglish:()Z
        14: ifeq          48
        17: invokestatic  #308                // Method org/fossify/commons/helpers/ConstantsKt.isTiramisuPlus:()Z
        20: ifne          48
        23: aload_0
        24: new           #310                // class org/fossify/commons/helpers/MyContextWrapper
        27: dup
        28: aload_1
        29: invokespecial #312                // Method org/fossify/commons/helpers/MyContextWrapper."<init>":(Landroid/content/Context;)V
        32: aload_1
        33: ldc_w         #314                // String en
        36: invokevirtual #318                // Method org/fossify/commons/helpers/MyContextWrapper.wrap:(Landroid/content/Context;Ljava/lang/String;)Landroid/content/ContextWrapper;
        39: checkcast     #177                // class android/content/Context
        42: invokespecial #320                // Method org/fossify/commons/activities/EdgeToEdgeActivity.attachBaseContext:(Landroid/content/Context;)V
        45: goto          53
        48: aload_0
        49: aload_1
        50: invokespecial #320                // Method org/fossify/commons/activities/EdgeToEdgeActivity.attachBaseContext:(Landroid/content/Context;)V
        53: return

  public final void registerBackPressedCallback();
    Code:
         0: aload_0
         1: aload_0
         2: invokevirtual #109                // Method getOnBackPressedDispatcher:()Landroidx/activity/OnBackPressedDispatcher;
         5: aload_0
         6: checkcast     #323                // class androidx/lifecycle/LifecycleOwner
         9: iconst_0
        10: aload_0
        11: invokedynamic #343,  0            // InvokeDynamic #0:invoke:(Lorg/fossify/commons/activities/BaseSimpleActivity;)Lkotlin/jvm/functions/Function1;
        16: iconst_2
        17: aconst_null
        18: invokestatic  #349                // Method androidx/activity/OnBackPressedDispatcherKt.addCallback$default:(Landroidx/activity/OnBackPressedDispatcher;Landroidx/lifecycle/LifecycleOwner;ZLkotlin/jvm/functions/Function1;ILjava/lang/Object;)Landroidx/activity/OnBackPressedCallback;
        21: putfield      #94                 // Field backCallback:Landroidx/activity/OnBackPressedCallback;
        24: return

  public final void updateBackgroundColor(int);
    Code:
         0: aload_0
         1: invokevirtual #137                // Method getWindow:()Landroid/view/Window;
         4: invokevirtual #355                // Method android/view/Window.getDecorView:()Landroid/view/View;
         7: iload_1
         8: invokevirtual #360                // Method android/view/View.setBackgroundColor:(I)V
        11: return

  public static void updateBackgroundColor$default(org.fossify.commons.activities.BaseSimpleActivity, int, int, java.lang.Object);
    Code:
         0: aload_3
         1: ifnull        15
         4: new           #366                // class java/lang/UnsupportedOperationException
         7: dup
         8: ldc_w         #368                // String Super calls with default arguments not supported in this target, function: updateBackgroundColor
        11: invokespecial #370                // Method java/lang/UnsupportedOperationException."<init>":(Ljava/lang/String;)V
        14: athrow
        15: iload_2
        16: iconst_1
        17: iand
        18: ifeq          32
        21: aload_0
        22: checkcast     #177                // class android/content/Context
        25: invokestatic  #183                // Method org/fossify/commons/extensions/ContextKt.getBaseConfig:(Landroid/content/Context;)Lorg/fossify/commons/helpers/BaseConfig;
        28: invokevirtual #373                // Method org/fossify/commons/helpers/BaseConfig.getBackgroundColor:()I
        31: istore_1
        32: aload_0
        33: iload_1
        34: invokevirtual #243                // Method updateBackgroundColor:(I)V
        37: return

  public final void setupTopAppBar(org.fossify.commons.views.MyAppBarLayout, org.fossify.commons.helpers.NavigationIcon, int, android.view.MenuItem);
    Code:
         0: aload_1
         1: ldc_w         #377                // String topAppBar
         4: invokestatic  #77                 // Method kotlin/jvm/internal/Intrinsics.checkNotNullParameter:(Ljava/lang/Object;Ljava/lang/String;)V
         7: aload_2
         8: ldc_w         #379                // String navigationIcon
        11: invokestatic  #77                 // Method kotlin/jvm/internal/Intrinsics.checkNotNullParameter:(Ljava/lang/Object;Ljava/lang/String;)V
        14: iload_3
        15: invokestatic  #383                // Method org/fossify/commons/extensions/IntKt.getContrastColor:(I)I
        18: istore        5
        20: aload_2
        21: getstatic     #389                // Field org/fossify/commons/helpers/NavigationIcon.None:Lorg/fossify/commons/helpers/NavigationIcon;
        24: if_acmpeq     100
        27: aload_2
        28: getstatic     #392                // Field org/fossify/commons/helpers/NavigationIcon.Cross:Lorg/fossify/commons/helpers/NavigationIcon;
        31: if_acmpne     40
        34: getstatic     #397                // Field org/fossify/commons/R$drawable.ic_cross_vector:I
        37: goto          43
        40: getstatic     #400                // Field org/fossify/commons/R$drawable.ic_arrow_left_vector:I
        43: istore        6
        45: aload_1
        46: invokevirtual #406                // Method org/fossify/commons/views/MyAppBarLayout.getToolbar:()Lcom/google/android/material/appbar/MaterialToolbar;
        49: dup
        50: ifnull        80
        53: aload_0
        54: invokevirtual #410                // Method getResources:()Landroid/content/res/Resources;
        57: dup
        58: ldc_w         #412                // String getResources(...)
        61: invokestatic  #154                // Method kotlin/jvm/internal/Intrinsics.checkNotNullExpressionValue:(Ljava/lang/Object;Ljava/lang/String;)V
        64: iload         6
        66: iload         5
        68: iconst_0
        69: iconst_4
        70: aconst_null
        71: invokestatic  #418                // Method org/fossify/commons/extensions/ResourcesKt.getColoredDrawableWithColor$default:(Landroid/content/res/Resources;IIIILjava/lang/Object;)Landroid/graphics/drawable/Drawable;
        74: invokevirtual #424                // Method com/google/android/material/appbar/MaterialToolbar.setNavigationIcon:(Landroid/graphics/drawable/Drawable;)V
        77: goto          81
        80: pop
        81: aload_1
        82: invokevirtual #406                // Method org/fossify/commons/views/MyAppBarLayout.getToolbar:()Lcom/google/android/material/appbar/MaterialToolbar;
        85: dup
        86: ifnull        99
        89: aload_2
        90: invokevirtual #427                // Method org/fossify/commons/helpers/NavigationIcon.getAccessibilityResId:()I
        93: invokevirtual #430                // Method com/google/android/material/appbar/MaterialToolbar.setNavigationContentDescription:(I)V
        96: goto          100
        99: pop
       100: aload_1
       101: invokevirtual #406                // Method org/fossify/commons/views/MyAppBarLayout.getToolbar:()Lcom/google/android/material/appbar/MaterialToolbar;
       104: dup
       105: ifnull        120
       108: aload_0
       109: invokedynamic #440,  0            // InvokeDynamic #1:onClick:(Lorg/fossify/commons/activities/BaseSimpleActivity;)Landroid/view/View$OnClickListener;
       114: invokevirtual #444                // Method com/google/android/material/appbar/MaterialToolbar.setNavigationOnClickListener:(Landroid/view/View$OnClickListener;)V
       117: goto          121
       120: pop
       121: aload_0
       122: aload_1
       123: iload_3
       124: invokevirtual #448                // Method updateTopBarColors:(Lorg/fossify/commons/views/MyAppBarLayout;I)V
       127: aload_0
       128: invokevirtual #451                // Method isSearchBarEnabled:()Z
       131: ifne          362
       134: aload         4
       136: ifnull        193
       139: aload         4
       141: invokeinterface #454,  1          // InterfaceMethod android/view/MenuItem.getActionView:()Landroid/view/View;
       146: astore        6
       148: aload         6
       150: ifnull        193
       153: aload         6
       155: getstatic     #459                // Field androidx/appcompat/R$id.search_close_btn:I
       158: invokevirtual #460                // Method android/view/View.findViewById:(I)Landroid/view/View;
       161: checkcast     #462                // class android/widget/ImageView
       164: astore        7
       166: aload         7
       168: ifnull        193
       171: aload         7
       173: astore        8
       175: aload         8
       177: astore        9
       179: iconst_0
       180: istore        10
       182: aload         9
       184: iload         5
       186: invokestatic  #468                // Method org/fossify/commons/extensions/ImageViewKt.applyColorFilter:(Landroid/widget/ImageView;I)V
       189: nop
       190: goto          194
       193: nop
       194: aload         4
       196: ifnull        298
       199: aload         4
       201: invokeinterface #454,  1          // InterfaceMethod android/view/MenuItem.getActionView:()Landroid/view/View;
       206: astore        6
       208: aload         6
       210: ifnull        298
       213: aload         6
       215: getstatic     #471                // Field androidx/appcompat/R$id.search_src_text:I
       218: invokevirtual #460                // Method android/view/View.findViewById:(I)Landroid/view/View;
       221: checkcast     #473                // class android/widget/EditText
       224: astore        7
       226: aload         7
       228: ifnull        298
       231: aload         7
       233: astore        8
       235: aload         8
       237: astore        9
       239: iconst_0
       240: istore        10
       242: aload         9
       244: iload         5
       246: invokevirtual #476                // Method android/widget/EditText.setTextColor:(I)V
       249: aload         9
       251: iload         5
       253: ldc_w         #477                // float 0.5f
       256: invokestatic  #481                // Method org/fossify/commons/extensions/IntKt.adjustAlpha:(IF)I
       259: invokevirtual #484                // Method android/widget/EditText.setHintTextColor:(I)V
       262: aload         9
       264: aload_0
       265: getstatic     #489                // Field org/fossify/commons/R$string.search:I
       268: invokevirtual #493                // Method getString:(I)Ljava/lang/String;
       271: invokedynamic #505,  0            // InvokeDynamic #2:makeConcatWithConstants:(Ljava/lang/String;)Ljava/lang/String;
       276: checkcast     #507                // class java/lang/CharSequence
       279: invokevirtual #511                // Method android/widget/EditText.setHint:(Ljava/lang/CharSequence;)V
       282: invokestatic  #514                // Method org/fossify/commons/helpers/ConstantsKt.isQPlus:()Z
       285: ifeq          294
       288: aload         9
       290: aconst_null
       291: invokevirtual #517                // Method android/widget/EditText.setTextCursorDrawable:(Landroid/graphics/drawable/Drawable;)V
       294: nop
       295: goto          299
       298: nop
       299: aload         4
       301: ifnull        361
       304: aload         4
       306: invokeinterface #454,  1          // InterfaceMethod android/view/MenuItem.getActionView:()Landroid/view/View;
       311: astore        6
       313: aload         6
       315: ifnull        361
       318: aload         6
       320: getstatic     #520                // Field androidx/appcompat/R$id.search_plate:I
       323: invokevirtual #460                // Method android/view/View.findViewById:(I)Landroid/view/View;
       326: astore        7
       328: aload         7
       330: ifnull        361
       333: aload         7
       335: astore        8
       337: aload         8
       339: astore        9
       341: iconst_0
       342: istore        10
       344: aload         9
       346: invokevirtual #524                // Method android/view/View.getBackground:()Landroid/graphics/drawable/Drawable;
       349: iload         5
       351: getstatic     #530                // Field android/graphics/PorterDuff$Mode.MULTIPLY:Landroid/graphics/PorterDuff$Mode;
       354: invokevirtual #536                // Method android/graphics/drawable/Drawable.setColorFilter:(ILandroid/graphics/PorterDuff$Mode;)V
       357: nop
       358: goto          362
       361: nop
       362: return

  public static void setupTopAppBar$default(org.fossify.commons.activities.BaseSimpleActivity, org.fossify.commons.views.MyAppBarLayout, org.fossify.commons.helpers.NavigationIcon, int, android.view.MenuItem, int, java.lang.Object);
    Code:
         0: aload         6
         2: ifnull        16
         5: new           #366                // class java/lang/UnsupportedOperationException
         8: dup
         9: ldc_w         #554                // String Super calls with default arguments not supported in this target, function: setupTopAppBar
        12: invokespecial #370                // Method java/lang/UnsupportedOperationException."<init>":(Ljava/lang/String;)V
        15: athrow
        16: iload         5
        18: iconst_2
        19: iand
        20: ifeq          27
        23: getstatic     #389                // Field org/fossify/commons/helpers/NavigationIcon.None:Lorg/fossify/commons/helpers/NavigationIcon;
        26: astore_2
        27: iload         5
        29: iconst_4
        30: iand
        31: ifeq          39
        34: aload_0
        35: invokevirtual #557                // Method getRequiredTopBarColor:()I
        38: istore_3
        39: iload         5
        41: bipush        8
        43: iand
        44: ifeq          50
        47: aconst_null
        48: astore        4
        50: aload_0
        51: aload_1
        52: aload_2
        53: iload_3
        54: aload         4
        56: invokevirtual #559                // Method setupTopAppBar:(Lorg/fossify/commons/views/MyAppBarLayout;Lorg/fossify/commons/helpers/NavigationIcon;ILandroid/view/MenuItem;)V
        59: return

  public final void updateRecentsAppIcon();
    Code:
         0: aload_0
         1: checkcast     #177                // class android/content/Context
         4: invokestatic  #183                // Method org/fossify/commons/extensions/ContextKt.getBaseConfig:(Landroid/content/Context;)Lorg/fossify/commons/helpers/BaseConfig;
         7: invokevirtual #562                // Method org/fossify/commons/helpers/BaseConfig.isUsingModifiedAppIcon:()Z
        10: ifeq          98
        13: aload_0
        14: invokevirtual #564                // Method getAppIconIDs:()Ljava/util/ArrayList;
        17: astore_1
        18: aload_0
        19: invokespecial #567                // Method getCurrentAppIconColorIndex:()I
        22: istore_2
        23: aload_1
        24: invokevirtual #572                // Method java/util/ArrayList.size:()I
        27: iconst_1
        28: isub
        29: iload_2
        30: if_icmpge     34
        33: return
        34: aload_0
        35: invokevirtual #410                // Method getResources:()Landroid/content/res/Resources;
        38: aload_1
        39: iload_2
        40: invokevirtual #576                // Method java/util/ArrayList.get:(I)Ljava/lang/Object;
        43: dup
        44: ldc_w         #578                // String get(...)
        47: invokestatic  #154                // Method kotlin/jvm/internal/Intrinsics.checkNotNullExpressionValue:(Ljava/lang/Object;Ljava/lang/String;)V
        50: checkcast     #580                // class java/lang/Number
        53: invokevirtual #583                // Method java/lang/Number.intValue:()I
        56: invokestatic  #589                // Method android/graphics/BitmapFactory.decodeResource:(Landroid/content/res/Resources;I)Landroid/graphics/Bitmap;
        59: astore_3
        60: aload_0
        61: invokevirtual #591                // Method getAppLauncherName:()Ljava/lang/String;
        64: astore        4
        66: aload_0
        67: checkcast     #177                // class android/content/Context
        70: invokestatic  #183                // Method org/fossify/commons/extensions/ContextKt.getBaseConfig:(Landroid/content/Context;)Lorg/fossify/commons/helpers/BaseConfig;
        73: invokevirtual #594                // Method org/fossify/commons/helpers/BaseConfig.getPrimaryColor:()I
        76: istore        5
        78: new           #596                // class android/app/ActivityManager$TaskDescription
        81: dup
        82: aload         4
        84: aload_3
        85: iload         5
        87: invokespecial #599                // Method android/app/ActivityManager$TaskDescription."<init>":(Ljava/lang/String;Landroid/graphics/Bitmap;I)V
        90: astore        6
        92: aload_0
        93: aload         6
        95: invokevirtual #603                // Method setTaskDescription:(Landroid/app/ActivityManager$TaskDescription;)V
        98: return

  public final void updateMenuItemColors(android.view.Menu, int, boolean);
    Code:
         0: aload_1
         1: ifnonnull     5
         4: return
         5: iload_2
         6: invokestatic  #383                // Method org/fossify/commons/extensions/IntKt.getContrastColor:(I)I
         9: istore        4
        11: iload_3
        12: ifeq          18
        15: iconst_m1
        16: istore        4
        18: iconst_0
        19: istore        5
        21: aload_1
        22: astore        7
        24: iconst_0
        25: istore        8
        27: aload         7
        29: invokeinterface #618,  1          // InterfaceMethod android/view/Menu.size:()I
        34: istore        6
        36: iload         5
        38: iload         6
        40: if_icmpge     92
        43: nop
        44: aload_1
        45: astore        8
        47: iload         5
        49: istore        9
        51: iconst_0
        52: istore        10
        54: aload         8
        56: iload         9
        58: invokeinterface #622,  2          // InterfaceMethod android/view/Menu.getItem:(I)Landroid/view/MenuItem;
        63: invokeinterface #625,  1          // InterfaceMethod android/view/MenuItem.getIcon:()Landroid/graphics/drawable/Drawable;
        68: dup
        69: ifnull        80
        72: iload         4
        74: invokevirtual #628                // Method android/graphics/drawable/Drawable.setTint:(I)V
        77: goto          86
        80: pop
        81: goto          86
        84: astore        8
        86: iinc          5, 1
        89: goto          36
        92: return
      Exception table:
         from    to  target type
            43    81    84   Class java/lang/Exception

  public static void updateMenuItemColors$default(org.fossify.commons.activities.BaseSimpleActivity, android.view.Menu, int, boolean, int, java.lang.Object);
    Code:
         0: aload         5
         2: ifnull        16
         5: new           #366                // class java/lang/UnsupportedOperationException
         8: dup
         9: ldc_w         #644                // String Super calls with default arguments not supported in this target, function: updateMenuItemColors
        12: invokespecial #370                // Method java/lang/UnsupportedOperationException."<init>":(Ljava/lang/String;)V
        15: athrow
        16: iload         4
        18: iconst_2
        19: iand
        20: ifeq          31
        23: aload_0
        24: checkcast     #177                // class android/content/Context
        27: invokestatic  #647                // Method org/fossify/commons/extensions/Context_stylingKt.getProperStatusBarColor:(Landroid/content/Context;)I
        30: istore_2
        31: iload         4
        33: iconst_4
        34: iand
        35: ifeq          40
        38: iconst_0
        39: istore_3
        40: aload_0
        41: aload_1
        42: iload_2
        43: iload_3
        44: invokevirtual #649                // Method updateMenuItemColors:(Landroid/view/Menu;IZ)V
        47: return

  protected void onActivityResult(int, int, android.content.Intent);
    Code:
         0: aload_0
         1: iload_1
         2: iload_2
         3: aload_3
         4: invokespecial #688                // Method org/fossify/commons/activities/EdgeToEdgeActivity.onActivityResult:(IILandroid/content/Intent;)V
         7: nop
         8: aload_0
         9: getfield      #18                 // Field checkedDocumentPath:Ljava/lang/String;
        12: bipush        9
        14: bipush        18
        16: invokevirtual #694                // Method java/lang/String.substring:(II)Ljava/lang/String;
        19: dup
        20: ldc_w         #696                // String substring(...)
        23: invokestatic  #154                // Method kotlin/jvm/internal/Intrinsics.checkNotNullExpressionValue:(Ljava/lang/Object;Ljava/lang/String;)V
        26: astore        5
        28: goto          37
        31: astore        6
        33: ldc           #14                 // String
        35: astore        5
        37: aload         5
        39: astore        4
        41: ldc_w         #698                // String ^[A-Za-z0-9]{4}-[A-Za-z0-9]{4}$
        44: invokestatic  #704                // Method java/util/regex/Pattern.compile:(Ljava/lang/String;)Ljava/util/regex/Pattern;
        47: astore        5
        49: iload_1
        50: sipush        1008
        53: if_icmpne     215
        56: iload_2
        57: iconst_m1
        58: if_icmpne     191
        61: aload_3
        62: ifnull        191
        65: aload_3
        66: invokevirtual #710                // Method android/content/Intent.getData:()Landroid/net/Uri;
        69: ifnull        191
        72: aload_3
        73: invokevirtual #710                // Method android/content/Intent.getData:()Landroid/net/Uri;
        76: astore        6
        78: aload_0
        79: checkcast     #177                // class android/content/Context
        82: aload_0
        83: getfield      #18                 // Field checkedDocumentPath:Ljava/lang/String;
        86: invokestatic  #716                // Method org/fossify/commons/extensions/Context_storage_sdk30Kt.buildDocumentUriSdk30:(Landroid/content/Context;Ljava/lang/String;)Landroid/net/Uri;
        89: astore        7
        91: aload         6
        93: aload         7
        95: invokestatic  #720                // Method kotlin/jvm/internal/Intrinsics.areEqual:(Ljava/lang/Object;Ljava/lang/Object;)Z
        98: ifne          142
       101: aload_0
       102: checkcast     #177                // class android/content/Context
       105: aload_0
       106: getstatic     #723                // Field org/fossify/commons/R$string.wrong_folder_selected:I
       109: iconst_1
       110: anewarray     #640                // class java/lang/Object
       113: astore        9
       115: aload         9
       117: iconst_0
       118: aload_0
       119: getfield      #18                 // Field checkedDocumentPath:Ljava/lang/String;
       122: aastore
       123: aload         9
       125: invokevirtual #726                // Method getString:(I[Ljava/lang/Object;)Ljava/lang/String;
       128: dup
       129: ldc_w         #728                // String getString(...)
       132: invokestatic  #154                // Method kotlin/jvm/internal/Intrinsics.checkNotNullExpressionValue:(Ljava/lang/Object;Ljava/lang/String;)V
       135: iconst_0
       136: iconst_2
       137: aconst_null
       138: invokestatic  #732                // Method org/fossify/commons/extensions/ContextKt.toast$default:(Landroid/content/Context;Ljava/lang/String;IILjava/lang/Object;)V
       141: return
       142: iconst_3
       143: istore        8
       145: aload_0
       146: invokevirtual #736                // Method getApplicationContext:()Landroid/content/Context;
       149: invokevirtual #740                // Method android/content/Context.getContentResolver:()Landroid/content/ContentResolver;
       152: aload         6
       154: iload         8
       156: invokevirtual #746                // Method android/content/ContentResolver.takePersistableUriPermission:(Landroid/net/Uri;I)V
       159: getstatic     #749                // Field funAfterSdk30Action:Lkotlin/jvm/functions/Function1;
       162: astore        9
       164: aconst_null
       165: putstatic     #749                // Field funAfterSdk30Action:Lkotlin/jvm/functions/Function1;
       168: aload         9
       170: dup
       171: ifnull        187
       174: iconst_1
       175: invokestatic  #755                // Method java/lang/Boolean.valueOf:(Z)Ljava/lang/Boolean;
       178: invokeinterface #759,  2          // InterfaceMethod kotlin/jvm/functions/Function1.invoke:(Ljava/lang/Object;)Ljava/lang/Object;
       183: pop
       184: goto          1669
       187: pop
       188: goto          1669
       191: getstatic     #749                // Field funAfterSdk30Action:Lkotlin/jvm/functions/Function1;
       194: dup
       195: ifnull        211
       198: iconst_0
       199: invokestatic  #755                // Method java/lang/Boolean.valueOf:(Z)Ljava/lang/Boolean;
       202: invokeinterface #759,  2          // InterfaceMethod kotlin/jvm/functions/Function1.invoke:(Ljava/lang/Object;)Ljava/lang/Object;
       207: pop
       208: goto          1669
       211: pop
       212: goto          1669
       215: iload_1
       216: sipush        1003
       219: if_icmpne     414
       222: iload_2
       223: iconst_m1
       224: if_icmpne     390
       227: aload_3
       228: ifnull        390
       231: aload_3
       232: invokevirtual #710                // Method android/content/Intent.getData:()Landroid/net/Uri;
       235: ifnull        390
       238: aload_3
       239: invokevirtual #710                // Method android/content/Intent.getData:()Landroid/net/Uri;
       242: astore        6
       244: aload_0
       245: checkcast     #177                // class android/content/Context
       248: aload_0
       249: getfield      #18                 // Field checkedDocumentPath:Ljava/lang/String;
       252: invokestatic  #762                // Method org/fossify/commons/extensions/Context_storage_sdk30Kt.createFirstParentTreeUri:(Landroid/content/Context;Ljava/lang/String;)Landroid/net/Uri;
       255: astore        7
       257: aload         6
       259: aload         7
       261: invokestatic  #720                // Method kotlin/jvm/internal/Intrinsics.areEqual:(Ljava/lang/Object;Ljava/lang/Object;)Z
       264: ifne          341
       267: aload_0
       268: checkcast     #177                // class android/content/Context
       271: aload_0
       272: getfield      #18                 // Field checkedDocumentPath:Ljava/lang/String;
       275: invokestatic  #766                // Method org/fossify/commons/extensions/Context_storage_sdk30Kt.getFirstParentLevel:(Landroid/content/Context;Ljava/lang/String;)I
       278: istore        8
       280: aload_0
       281: getfield      #18                 // Field checkedDocumentPath:Ljava/lang/String;
       284: aload_0
       285: checkcast     #177                // class android/content/Context
       288: iload         8
       290: invokestatic  #772                // Method org/fossify/commons/extensions/StringKt.getFirstParentPath:(Ljava/lang/String;Landroid/content/Context;I)Ljava/lang/String;
       293: astore        9
       295: aload_0
       296: checkcast     #177                // class android/content/Context
       299: aload_0
       300: getstatic     #723                // Field org/fossify/commons/R$string.wrong_folder_selected:I
       303: iconst_1
       304: anewarray     #640                // class java/lang/Object
       307: astore        10
       309: aload         10
       311: iconst_0
       312: aload_0
       313: checkcast     #177                // class android/content/Context
       316: aload         9
       318: invokestatic  #778                // Method org/fossify/commons/extensions/Context_storageKt.humanizePath:(Landroid/content/Context;Ljava/lang/String;)Ljava/lang/String;
       321: aastore
       322: aload         10
       324: invokevirtual #726                // Method getString:(I[Ljava/lang/Object;)Ljava/lang/String;
       327: dup
       328: ldc_w         #728                // String getString(...)
       331: invokestatic  #154                // Method kotlin/jvm/internal/Intrinsics.checkNotNullExpressionValue:(Ljava/lang/Object;Ljava/lang/String;)V
       334: iconst_0
       335: iconst_2
       336: aconst_null
       337: invokestatic  #732                // Method org/fossify/commons/extensions/ContextKt.toast$default:(Landroid/content/Context;Ljava/lang/String;IILjava/lang/Object;)V
       340: return
       341: iconst_3
       342: istore        8
       344: aload_0
       345: invokevirtual #736                // Method getApplicationContext:()Landroid/content/Context;
       348: invokevirtual #740                // Method android/content/Context.getContentResolver:()Landroid/content/ContentResolver;
       351: aload         6
       353: iload         8
       355: invokevirtual #746                // Method android/content/ContentResolver.takePersistableUriPermission:(Landroid/net/Uri;I)V
       358: getstatic     #749                // Field funAfterSdk30Action:Lkotlin/jvm/functions/Function1;
       361: astore        9
       363: aconst_null
       364: putstatic     #749                // Field funAfterSdk30Action:Lkotlin/jvm/functions/Function1;
       367: aload         9
       369: dup
       370: ifnull        386
       373: iconst_1
       374: invokestatic  #755                // Method java/lang/Boolean.valueOf:(Z)Ljava/lang/Boolean;
       377: invokeinterface #759,  2          // InterfaceMethod kotlin/jvm/functions/Function1.invoke:(Ljava/lang/Object;)Ljava/lang/Object;
       382: pop
       383: goto          1669
       386: pop
       387: goto          1669
       390: getstatic     #749                // Field funAfterSdk30Action:Lkotlin/jvm/functions/Function1;
       393: dup
       394: ifnull        410
       397: iconst_0
       398: invokestatic  #755                // Method java/lang/Boolean.valueOf:(Z)Ljava/lang/Boolean;
       401: invokeinterface #759,  2          // InterfaceMethod kotlin/jvm/functions/Function1.invoke:(Ljava/lang/Object;)Ljava/lang/Object;
       406: pop
       407: goto          1669
       410: pop
       411: goto          1669
       414: iload_1
       415: sipush        1000
       418: if_icmpne     767
       421: iload_2
       422: iconst_m1
       423: if_icmpne     743
       426: aload_3
       427: ifnull        743
       430: aload_3
       431: invokevirtual #710                // Method android/content/Intent.getData:()Landroid/net/Uri;
       434: ifnull        743
       437: aload_0
       438: aload_0
       439: getfield      #18                 // Field checkedDocumentPath:Ljava/lang/String;
       442: aload_3
       443: invokevirtual #710                // Method android/content/Intent.getData:()Landroid/net/Uri;
       446: dup
       447: invokestatic  #782                // Method kotlin/jvm/internal/Intrinsics.checkNotNull:(Ljava/lang/Object;)V
       450: invokespecial #786                // Method isProperAndroidRoot:(Ljava/lang/String;Landroid/net/Uri;)Z
       453: ifeq          619
       456: aload_3
       457: invokevirtual #789                // Method android/content/Intent.getDataString:()Ljava/lang/String;
       460: aload_0
       461: checkcast     #177                // class android/content/Context
       464: invokestatic  #183                // Method org/fossify/commons/extensions/ContextKt.getBaseConfig:(Landroid/content/Context;)Lorg/fossify/commons/helpers/BaseConfig;
       467: invokevirtual #792                // Method org/fossify/commons/helpers/BaseConfig.getOTGTreeUri:()Ljava/lang/String;
       470: invokestatic  #720                // Method kotlin/jvm/internal/Intrinsics.areEqual:(Ljava/lang/Object;Ljava/lang/Object;)Z
       473: ifne          496
       476: aload_3
       477: invokevirtual #789                // Method android/content/Intent.getDataString:()Ljava/lang/String;
       480: aload_0
       481: checkcast     #177                // class android/content/Context
       484: invokestatic  #183                // Method org/fossify/commons/extensions/ContextKt.getBaseConfig:(Landroid/content/Context;)Lorg/fossify/commons/helpers/BaseConfig;
       487: invokevirtual #795                // Method org/fossify/commons/helpers/BaseConfig.getSdTreeUri:()Ljava/lang/String;
       490: invokestatic  #720                // Method kotlin/jvm/internal/Intrinsics.areEqual:(Ljava/lang/Object;Ljava/lang/Object;)Z
       493: ifeq          548
       496: aload_0
       497: checkcast     #177                // class android/content/Context
       500: aload_0
       501: getfield      #18                 // Field checkedDocumentPath:Ljava/lang/String;
       504: invokestatic  #798                // Method org/fossify/commons/extensions/Context_storageKt.createAndroidDataOrObbPath:(Landroid/content/Context;Ljava/lang/String;)Ljava/lang/String;
       507: astore        6
       509: aload_0
       510: checkcast     #177                // class android/content/Context
       513: aload_0
       514: getstatic     #723                // Field org/fossify/commons/R$string.wrong_folder_selected:I
       517: iconst_1
       518: anewarray     #640                // class java/lang/Object
       521: astore        8
       523: aload         8
       525: iconst_0
       526: aload         6
       528: aastore
       529: aload         8
       531: invokevirtual #726                // Method getString:(I[Ljava/lang/Object;)Ljava/lang/String;
       534: dup
       535: ldc_w         #728                // String getString(...)
       538: invokestatic  #154                // Method kotlin/jvm/internal/Intrinsics.checkNotNullExpressionValue:(Ljava/lang/Object;Ljava/lang/String;)V
       541: iconst_0
       542: iconst_2
       543: aconst_null
       544: invokestatic  #732                // Method org/fossify/commons/extensions/ContextKt.toast$default:(Landroid/content/Context;Ljava/lang/String;IILjava/lang/Object;)V
       547: return
       548: aload_3
       549: invokevirtual #710                // Method android/content/Intent.getData:()Landroid/net/Uri;
       552: astore        6
       554: aload_0
       555: checkcast     #177                // class android/content/Context
       558: aload_0
       559: getfield      #18                 // Field checkedDocumentPath:Ljava/lang/String;
       562: aload         6
       564: invokestatic  #801                // Method java/lang/String.valueOf:(Ljava/lang/Object;)Ljava/lang/String;
       567: invokestatic  #805                // Method org/fossify/commons/extensions/Context_storageKt.storeAndroidTreeUri:(Landroid/content/Context;Ljava/lang/String;Ljava/lang/String;)V
       570: iconst_3
       571: istore        7
       573: aload_0
       574: invokevirtual #736                // Method getApplicationContext:()Landroid/content/Context;
       577: invokevirtual #740                // Method android/content/Context.getContentResolver:()Landroid/content/ContentResolver;
       580: aload         6
       582: dup
       583: invokestatic  #782                // Method kotlin/jvm/internal/Intrinsics.checkNotNull:(Ljava/lang/Object;)V
       586: iload         7
       588: invokevirtual #746                // Method android/content/ContentResolver.takePersistableUriPermission:(Landroid/net/Uri;I)V
       591: getstatic     #258                // Field funAfterSAFPermission:Lkotlin/jvm/functions/Function1;
       594: dup
       595: ifnull        611
       598: iconst_1
       599: invokestatic  #755                // Method java/lang/Boolean.valueOf:(Z)Ljava/lang/Boolean;
       602: invokeinterface #759,  2          // InterfaceMethod kotlin/jvm/functions/Function1.invoke:(Ljava/lang/Object;)Ljava/lang/Object;
       607: pop
       608: goto          612
       611: pop
       612: aconst_null
       613: putstatic     #258                // Field funAfterSAFPermission:Lkotlin/jvm/functions/Function1;
       616: goto          1669
       619: aload_0
       620: checkcast     #177                // class android/content/Context
       623: aload_0
       624: getstatic     #723                // Field org/fossify/commons/R$string.wrong_folder_selected:I
       627: iconst_1
       628: anewarray     #640                // class java/lang/Object
       631: astore        7
       633: aload         7
       635: iconst_0
       636: aload_0
       637: checkcast     #177                // class android/content/Context
       640: aload_0
       641: getfield      #18                 // Field checkedDocumentPath:Ljava/lang/String;
       644: invokestatic  #798                // Method org/fossify/commons/extensions/Context_storageKt.createAndroidDataOrObbPath:(Landroid/content/Context;Ljava/lang/String;)Ljava/lang/String;
       647: aastore
       648: aload         7
       650: invokevirtual #726                // Method getString:(I[Ljava/lang/Object;)Ljava/lang/String;
       653: dup
       654: ldc_w         #728                // String getString(...)
       657: invokestatic  #154                // Method kotlin/jvm/internal/Intrinsics.checkNotNullExpressionValue:(Ljava/lang/Object;Ljava/lang/String;)V
       660: iconst_0
       661: iconst_2
       662: aconst_null
       663: invokestatic  #732                // Method org/fossify/commons/extensions/ContextKt.toast$default:(Landroid/content/Context;Ljava/lang/String;IILjava/lang/Object;)V
       666: new           #706                // class android/content/Intent
       669: dup
       670: ldc_w         #807                // String android.intent.action.OPEN_DOCUMENT_TREE
       673: invokespecial #808                // Method android/content/Intent."<init>":(Ljava/lang/String;)V
       676: astore        6
       678: aload         6
       680: astore        7
       682: iconst_0
       683: istore        8
       685: invokestatic  #811                // Method org/fossify/commons/helpers/ConstantsKt.isRPlus:()Z
       688: ifeq          714
       691: aload         7
       693: ldc_w         #813                // String android.provider.extra.INITIAL_URI
       696: aload_0
       697: checkcast     #177                // class android/content/Context
       700: aload_0
       701: getfield      #18                 // Field checkedDocumentPath:Ljava/lang/String;
       704: invokestatic  #816                // Method org/fossify/commons/extensions/Context_storageKt.createAndroidDataOrObbUri:(Landroid/content/Context;Ljava/lang/String;)Landroid/net/Uri;
       707: checkcast     #818                // class android/os/Parcelable
       710: invokevirtual #822                // Method android/content/Intent.putExtra:(Ljava/lang/String;Landroid/os/Parcelable;)Landroid/content/Intent;
       713: pop
       714: nop
       715: aload_0
       716: aload         7
       718: iload_1
       719: invokevirtual #826                // Method startActivityForResult:(Landroid/content/Intent;I)V
       722: goto          739
       725: astore        9
       727: aload_0
       728: checkcast     #177                // class android/content/Context
       731: aload         9
       733: iconst_0
       734: iconst_2
       735: aconst_null
       736: invokestatic  #830                // Method org/fossify/commons/extensions/ContextKt.showErrorToast$default:(Landroid/content/Context;Ljava/lang/Exception;IILjava/lang/Object;)V
       739: nop
       740: goto          1669
       743: getstatic     #258                // Field funAfterSAFPermission:Lkotlin/jvm/functions/Function1;
       746: dup
       747: ifnull        763
       750: iconst_0
       751: invokestatic  #755                // Method java/lang/Boolean.valueOf:(Z)Ljava/lang/Boolean;
       754: invokeinterface #759,  2          // InterfaceMethod kotlin/jvm/functions/Function1.invoke:(Ljava/lang/Object;)Ljava/lang/Object;
       759: pop
       760: goto          1669
       763: pop
       764: goto          1669
       767: iload_1
       768: sipush        1002
       771: if_icmpne     1039
       774: iload_2
       775: iconst_m1
       776: if_icmpne     1015
       779: aload_3
       780: ifnull        1015
       783: aload_3
       784: invokevirtual #710                // Method android/content/Intent.getData:()Landroid/net/Uri;
       787: ifnull        1015
       790: aload         4
       792: checkcast     #507                // class java/lang/CharSequence
       795: invokeinterface #833,  1          // InterfaceMethod java/lang/CharSequence.length:()I
       800: ifne          807
       803: iconst_1
       804: goto          808
       807: iconst_0
       808: ifne          868
       811: aload         5
       813: aload         4
       815: checkcast     #507                // class java/lang/CharSequence
       818: invokevirtual #837                // Method java/util/regex/Pattern.matcher:(Ljava/lang/CharSequence;)Ljava/util/regex/Matcher;
       821: invokevirtual #842                // Method java/util/regex/Matcher.matches:()Z
       824: ifeq          868
       827: aload         5
       829: aload         4
       831: checkcast     #507                // class java/lang/CharSequence
       834: invokevirtual #837                // Method java/util/regex/Pattern.matcher:(Ljava/lang/CharSequence;)Ljava/util/regex/Matcher;
       837: invokevirtual #842                // Method java/util/regex/Matcher.matches:()Z
       840: ifeq          872
       843: aload_3
       844: invokevirtual #789                // Method android/content/Intent.getDataString:()Ljava/lang/String;
       847: dup
       848: invokestatic  #782                // Method kotlin/jvm/internal/Intrinsics.checkNotNull:(Ljava/lang/Object;)V
       851: checkcast     #507                // class java/lang/CharSequence
       854: aload         4
       856: checkcast     #507                // class java/lang/CharSequence
       859: iconst_0
       860: iconst_2
       861: aconst_null
       862: invokestatic  #846                // Method kotlin/text/StringsKt.contains$default:(Ljava/lang/CharSequence;Ljava/lang/CharSequence;ZILjava/lang/Object;)Z
       865: ifeq          872
       868: iconst_1
       869: goto          873
       872: iconst_0
       873: istore        6
       875: aload_0
       876: aload_3
       877: invokevirtual #710                // Method android/content/Intent.getData:()Landroid/net/Uri;
       880: dup
       881: invokestatic  #782                // Method kotlin/jvm/internal/Intrinsics.checkNotNull:(Ljava/lang/Object;)V
       884: invokespecial #850                // Method isProperSDRootFolder:(Landroid/net/Uri;)Z
       887: ifeq          962
       890: iload         6
       892: ifeq          962
       895: aload_3
       896: invokevirtual #789                // Method android/content/Intent.getDataString:()Ljava/lang/String;
       899: aload_0
       900: checkcast     #177                // class android/content/Context
       903: invokestatic  #183                // Method org/fossify/commons/extensions/ContextKt.getBaseConfig:(Landroid/content/Context;)Lorg/fossify/commons/helpers/BaseConfig;
       906: invokevirtual #792                // Method org/fossify/commons/helpers/BaseConfig.getOTGTreeUri:()Ljava/lang/String;
       909: invokestatic  #720                // Method kotlin/jvm/internal/Intrinsics.areEqual:(Ljava/lang/Object;Ljava/lang/Object;)Z
       912: ifeq          929
       915: aload_0
       916: checkcast     #177                // class android/content/Context
       919: getstatic     #853                // Field org/fossify/commons/R$string.sd_card_usb_same:I
       922: iconst_0
       923: iconst_2
       924: aconst_null
       925: invokestatic  #856                // Method org/fossify/commons/extensions/ContextKt.toast$default:(Landroid/content/Context;IIILjava/lang/Object;)V
       928: return
       929: aload_0
       930: aload_3
       931: invokespecial #860                // Method saveTreeUri:(Landroid/content/Intent;)V
       934: getstatic     #258                // Field funAfterSAFPermission:Lkotlin/jvm/functions/Function1;
       937: dup
       938: ifnull        954
       941: iconst_1
       942: invokestatic  #755                // Method java/lang/Boolean.valueOf:(Z)Ljava/lang/Boolean;
       945: invokeinterface #759,  2          // InterfaceMethod kotlin/jvm/functions/Function1.invoke:(Ljava/lang/Object;)Ljava/lang/Object;
       950: pop
       951: goto          955
       954: pop
       955: aconst_null
       956: putstatic     #258                // Field funAfterSAFPermission:Lkotlin/jvm/functions/Function1;
       959: goto          1669
       962: aload_0
       963: checkcast     #177                // class android/content/Context
       966: getstatic     #863                // Field org/fossify/commons/R$string.wrong_root_selected:I
       969: iconst_0
       970: iconst_2
       971: aconst_null
       972: invokestatic  #856                // Method org/fossify/commons/extensions/ContextKt.toast$default:(Landroid/content/Context;IIILjava/lang/Object;)V
       975: new           #706                // class android/content/Intent
       978: dup
       979: ldc_w         #807                // String android.intent.action.OPEN_DOCUMENT_TREE
       982: invokespecial #808                // Method android/content/Intent."<init>":(Ljava/lang/String;)V
       985: astore        7
       987: nop
       988: aload_0
       989: aload         7
       991: iload_1
       992: invokevirtual #826                // Method startActivityForResult:(Landroid/content/Intent;I)V
       995: goto          1669
       998: astore        8
      1000: aload_0
      1001: checkcast     #177                // class android/content/Context
      1004: aload         8
      1006: iconst_0
      1007: iconst_2
      1008: aconst_null
      1009: invokestatic  #830                // Method org/fossify/commons/extensions/ContextKt.showErrorToast$default:(Landroid/content/Context;Ljava/lang/Exception;IILjava/lang/Object;)V
      1012: goto          1669
      1015: getstatic     #258                // Field funAfterSAFPermission:Lkotlin/jvm/functions/Function1;
      1018: dup
      1019: ifnull        1035
      1022: iconst_0
      1023: invokestatic  #755                // Method java/lang/Boolean.valueOf:(Z)Ljava/lang/Boolean;
      1026: invokeinterface #759,  2          // InterfaceMethod kotlin/jvm/functions/Function1.invoke:(Ljava/lang/Object;)Ljava/lang/Object;
      1031: pop
      1032: goto          1669
      1035: pop
      1036: goto          1669
      1039: iload_1
      1040: sipush        1001
      1043: if_icmpne     1428
      1046: iload_2
      1047: iconst_m1
      1048: if_icmpne     1404
      1051: aload_3
      1052: ifnull        1404
      1055: aload_3
      1056: invokevirtual #710                // Method android/content/Intent.getData:()Landroid/net/Uri;
      1059: ifnull        1404
      1062: aload         4
      1064: checkcast     #507                // class java/lang/CharSequence
      1067: invokeinterface #833,  1          // InterfaceMethod java/lang/CharSequence.length:()I
      1072: ifne          1079
      1075: iconst_1
      1076: goto          1080
      1079: iconst_0
      1080: ifne          1140
      1083: aload         5
      1085: aload         4
      1087: checkcast     #507                // class java/lang/CharSequence
      1090: invokevirtual #837                // Method java/util/regex/Pattern.matcher:(Ljava/lang/CharSequence;)Ljava/util/regex/Matcher;
      1093: invokevirtual #842                // Method java/util/regex/Matcher.matches:()Z
      1096: ifeq          1140
      1099: aload         5
      1101: aload         4
      1103: checkcast     #507                // class java/lang/CharSequence
      1106: invokevirtual #837                // Method java/util/regex/Pattern.matcher:(Ljava/lang/CharSequence;)Ljava/util/regex/Matcher;
      1109: invokevirtual #842                // Method java/util/regex/Matcher.matches:()Z
      1112: ifeq          1144
      1115: aload_3
      1116: invokevirtual #789                // Method android/content/Intent.getDataString:()Ljava/lang/String;
      1119: dup
      1120: invokestatic  #782                // Method kotlin/jvm/internal/Intrinsics.checkNotNull:(Ljava/lang/Object;)V
      1123: checkcast     #507                // class java/lang/CharSequence
      1126: aload         4
      1128: checkcast     #507                // class java/lang/CharSequence
      1131: iconst_0
      1132: iconst_2
      1133: aconst_null
      1134: invokestatic  #846                // Method kotlin/text/StringsKt.contains$default:(Ljava/lang/CharSequence;Ljava/lang/CharSequence;ZILjava/lang/Object;)Z
      1137: ifeq          1144
      1140: iconst_1
      1141: goto          1145
      1144: iconst_0
      1145: istore        6
      1147: aload_0
      1148: aload_3
      1149: invokevirtual #710                // Method android/content/Intent.getData:()Landroid/net/Uri;
      1152: dup
      1153: invokestatic  #782                // Method kotlin/jvm/internal/Intrinsics.checkNotNull:(Ljava/lang/Object;)V
      1156: invokespecial #866                // Method isProperOTGRootFolder:(Landroid/net/Uri;)Z
      1159: ifeq          1351
      1162: iload         6
      1164: ifeq          1351
      1167: aload_3
      1168: invokevirtual #789                // Method android/content/Intent.getDataString:()Ljava/lang/String;
      1171: aload_0
      1172: checkcast     #177                // class android/content/Context
      1175: invokestatic  #183                // Method org/fossify/commons/extensions/ContextKt.getBaseConfig:(Landroid/content/Context;)Lorg/fossify/commons/helpers/BaseConfig;
      1178: invokevirtual #795                // Method org/fossify/commons/helpers/BaseConfig.getSdTreeUri:()Ljava/lang/String;
      1181: invokestatic  #720                // Method kotlin/jvm/internal/Intrinsics.areEqual:(Ljava/lang/Object;Ljava/lang/Object;)Z
      1184: ifeq          1222
      1187: getstatic     #258                // Field funAfterSAFPermission:Lkotlin/jvm/functions/Function1;
      1190: dup
      1191: ifnull        1207
      1194: iconst_0
      1195: invokestatic  #755                // Method java/lang/Boolean.valueOf:(Z)Ljava/lang/Boolean;
      1198: invokeinterface #759,  2          // InterfaceMethod kotlin/jvm/functions/Function1.invoke:(Ljava/lang/Object;)Ljava/lang/Object;
      1203: pop
      1204: goto          1208
      1207: pop
      1208: aload_0
      1209: checkcast     #177                // class android/content/Context
      1212: getstatic     #853                // Field org/fossify/commons/R$string.sd_card_usb_same:I
      1215: iconst_0
      1216: iconst_2
      1217: aconst_null
      1218: invokestatic  #856                // Method org/fossify/commons/extensions/ContextKt.toast$default:(Landroid/content/Context;IIILjava/lang/Object;)V
      1221: return
      1222: aload_0
      1223: checkcast     #177                // class android/content/Context
      1226: invokestatic  #183                // Method org/fossify/commons/extensions/ContextKt.getBaseConfig:(Landroid/content/Context;)Lorg/fossify/commons/helpers/BaseConfig;
      1229: aload_3
      1230: invokevirtual #789                // Method android/content/Intent.getDataString:()Ljava/lang/String;
      1233: dup
      1234: invokestatic  #782                // Method kotlin/jvm/internal/Intrinsics.checkNotNull:(Ljava/lang/Object;)V
      1237: invokevirtual #869                // Method org/fossify/commons/helpers/BaseConfig.setOTGTreeUri:(Ljava/lang/String;)V
      1240: aload_0
      1241: checkcast     #177                // class android/content/Context
      1244: invokestatic  #183                // Method org/fossify/commons/extensions/ContextKt.getBaseConfig:(Landroid/content/Context;)Lorg/fossify/commons/helpers/BaseConfig;
      1247: aload_0
      1248: checkcast     #177                // class android/content/Context
      1251: invokestatic  #183                // Method org/fossify/commons/extensions/ContextKt.getBaseConfig:(Landroid/content/Context;)Lorg/fossify/commons/helpers/BaseConfig;
      1254: invokevirtual #792                // Method org/fossify/commons/helpers/BaseConfig.getOTGTreeUri:()Ljava/lang/String;
      1257: ldc_w         #871                // String %3A
      1260: checkcast     #507                // class java/lang/CharSequence
      1263: invokestatic  #875                // Method kotlin/text/StringsKt.removeSuffix:(Ljava/lang/String;Ljava/lang/CharSequence;)Ljava/lang/String;
      1266: bipush        47
      1268: aconst_null
      1269: iconst_2
      1270: aconst_null
      1271: invokestatic  #879                // Method kotlin/text/StringsKt.substringAfterLast$default:(Ljava/lang/String;CLjava/lang/String;ILjava/lang/Object;)Ljava/lang/String;
      1274: iconst_1
      1275: newarray       char
      1277: astore        7
      1279: aload         7
      1281: iconst_0
      1282: bipush        47
      1284: castore
      1285: aload         7
      1287: invokestatic  #883                // Method kotlin/text/StringsKt.trimEnd:(Ljava/lang/String;[C)Ljava/lang/String;
      1290: invokevirtual #886                // Method org/fossify/commons/helpers/BaseConfig.setOTGPartition:(Ljava/lang/String;)V
      1293: aload_0
      1294: checkcast     #177                // class android/content/Context
      1297: invokestatic  #889                // Method org/fossify/commons/extensions/Context_storageKt.updateOTGPathFromPartition:(Landroid/content/Context;)V
      1300: iconst_3
      1301: istore        7
      1303: aload_0
      1304: invokevirtual #736                // Method getApplicationContext:()Landroid/content/Context;
      1307: invokevirtual #740                // Method android/content/Context.getContentResolver:()Landroid/content/ContentResolver;
      1310: aload_3
      1311: invokevirtual #710                // Method android/content/Intent.getData:()Landroid/net/Uri;
      1314: dup
      1315: invokestatic  #782                // Method kotlin/jvm/internal/Intrinsics.checkNotNull:(Ljava/lang/Object;)V
      1318: iload         7
      1320: invokevirtual #746                // Method android/content/ContentResolver.takePersistableUriPermission:(Landroid/net/Uri;I)V
      1323: getstatic     #258                // Field funAfterSAFPermission:Lkotlin/jvm/functions/Function1;
      1326: dup
      1327: ifnull        1343
      1330: iconst_1
      1331: invokestatic  #755                // Method java/lang/Boolean.valueOf:(Z)Ljava/lang/Boolean;
      1334: invokeinterface #759,  2          // InterfaceMethod kotlin/jvm/functions/Function1.invoke:(Ljava/lang/Object;)Ljava/lang/Object;
      1339: pop
      1340: goto          1344
      1343: pop
      1344: aconst_null
      1345: putstatic     #258                // Field funAfterSAFPermission:Lkotlin/jvm/functions/Function1;
      1348: goto          1669
      1351: aload_0
      1352: checkcast     #177                // class android/content/Context
      1355: getstatic     #892                // Field org/fossify/commons/R$string.wrong_root_selected_usb:I
      1358: iconst_0
      1359: iconst_2
      1360: aconst_null
      1361: invokestatic  #856                // Method org/fossify/commons/extensions/ContextKt.toast$default:(Landroid/content/Context;IIILjava/lang/Object;)V
      1364: new           #706                // class android/content/Intent
      1367: dup
      1368: ldc_w         #807                // String android.intent.action.OPEN_DOCUMENT_TREE
      1371: invokespecial #808                // Method android/content/Intent."<init>":(Ljava/lang/String;)V
      1374: astore        7
      1376: nop
      1377: aload_0
      1378: aload         7
      1380: iload_1
      1381: invokevirtual #826                // Method startActivityForResult:(Landroid/content/Intent;I)V
      1384: goto          1669
      1387: astore        8
      1389: aload_0
      1390: checkcast     #177                // class android/content/Context
      1393: aload         8
      1395: iconst_0
      1396: iconst_2
      1397: aconst_null
      1398: invokestatic  #830                // Method org/fossify/commons/extensions/ContextKt.showErrorToast$default:(Landroid/content/Context;Ljava/lang/Exception;IILjava/lang/Object;)V
      1401: goto          1669
      1404: getstatic     #258                // Field funAfterSAFPermission:Lkotlin/jvm/functions/Function1;
      1407: dup
      1408: ifnull        1424
      1411: iconst_0
      1412: invokestatic  #755                // Method java/lang/Boolean.valueOf:(Z)Ljava/lang/Boolean;
      1415: invokeinterface #759,  2          // InterfaceMethod kotlin/jvm/functions/Function1.invoke:(Ljava/lang/Object;)Ljava/lang/Object;
      1420: pop
      1421: goto          1669
      1424: pop
      1425: goto          1669
      1428: iload_1
      1429: sipush        1006
      1432: if_icmpne     1481
      1435: iload_2
      1436: iconst_m1
      1437: if_icmpne     1481
      1440: aload_3
      1441: ifnull        1481
      1444: aload_3
      1445: invokevirtual #710                // Method android/content/Intent.getData:()Landroid/net/Uri;
      1448: ifnull        1481
      1451: aload_0
      1452: invokevirtual #893                // Method getContentResolver:()Landroid/content/ContentResolver;
      1455: aload_3
      1456: invokevirtual #710                // Method android/content/Intent.getData:()Landroid/net/Uri;
      1459: dup
      1460: invokestatic  #782                // Method kotlin/jvm/internal/Intrinsics.checkNotNull:(Ljava/lang/Object;)V
      1463: invokevirtual #897                // Method android/content/ContentResolver.openOutputStream:(Landroid/net/Uri;)Ljava/io/OutputStream;
      1466: astore        6
      1468: aload_0
      1469: aload         6
      1471: aload_0
      1472: getfield      #25                 // Field configItemsToExport:Ljava/util/LinkedHashMap;
      1475: invokespecial #901                // Method exportSettingsTo:(Ljava/io/OutputStream;Ljava/util/LinkedHashMap;)V
      1478: goto          1669
      1481: iload_1
      1482: sipush        300
      1485: if_icmpne     1521
      1488: getstatic     #749                // Field funAfterSdk30Action:Lkotlin/jvm/functions/Function1;
      1491: dup
      1492: ifnull        1517
      1495: iload_2
      1496: iconst_m1
      1497: if_icmpne     1504
      1500: iconst_1
      1501: goto          1505
      1504: iconst_0
      1505: invokestatic  #755                // Method java/lang/Boolean.valueOf:(Z)Ljava/lang/Boolean;
      1508: invokeinterface #759,  2          // InterfaceMethod kotlin/jvm/functions/Function1.invoke:(Ljava/lang/Object;)Ljava/lang/Object;
      1513: pop
      1514: goto          1669
      1517: pop
      1518: goto          1669
      1521: iload_1
      1522: sipush        301
      1525: if_icmpne     1565
      1528: getstatic     #904                // Field funRecoverableSecurity:Lkotlin/jvm/functions/Function1;
      1531: dup
      1532: ifnull        1557
      1535: iload_2
      1536: iconst_m1
      1537: if_icmpne     1544
      1540: iconst_1
      1541: goto          1545
      1544: iconst_0
      1545: invokestatic  #755                // Method java/lang/Boolean.valueOf:(Z)Ljava/lang/Boolean;
      1548: invokeinterface #759,  2          // InterfaceMethod kotlin/jvm/functions/Function1.invoke:(Ljava/lang/Object;)Ljava/lang/Object;
      1553: pop
      1554: goto          1558
      1557: pop
      1558: aconst_null
      1559: putstatic     #904                // Field funRecoverableSecurity:Lkotlin/jvm/functions/Function1;
      1562: goto          1669
      1565: iload_1
      1566: sipush        302
      1569: if_icmpne     1605
      1572: getstatic     #907                // Field funAfterUpdate30File:Lkotlin/jvm/functions/Function1;
      1575: dup
      1576: ifnull        1601
      1579: iload_2
      1580: iconst_m1
      1581: if_icmpne     1588
      1584: iconst_1
      1585: goto          1589
      1588: iconst_0
      1589: invokestatic  #755                // Method java/lang/Boolean.valueOf:(Z)Ljava/lang/Boolean;
      1592: invokeinterface #759,  2          // InterfaceMethod kotlin/jvm/functions/Function1.invoke:(Ljava/lang/Object;)Ljava/lang/Object;
      1597: pop
      1598: goto          1669
      1601: pop
      1602: goto          1669
      1605: iload_1
      1606: sipush        303
      1609: if_icmpne     1632
      1612: getstatic     #911                // Field funAfterManageMediaPermission:Lkotlin/jvm/functions/Function0;
      1615: dup
      1616: ifnull        1628
      1619: invokeinterface #915,  1          // InterfaceMethod kotlin/jvm/functions/Function0.invoke:()Ljava/lang/Object;
      1624: pop
      1625: goto          1669
      1628: pop
      1629: goto          1669
      1632: iload_1
      1633: sipush        304
      1636: if_icmpne     1669
      1639: getstatic     #918                // Field funAfterTrash30File:Lkotlin/jvm/functions/Function1;
      1642: dup
      1643: ifnull        1668
      1646: iload_2
      1647: iconst_m1
      1648: if_icmpne     1655
      1651: iconst_1
      1652: goto          1656
      1655: iconst_0
      1656: invokestatic  #755                // Method java/lang/Boolean.valueOf:(Z)Ljava/lang/Boolean;
      1659: invokeinterface #759,  2          // InterfaceMethod kotlin/jvm/functions/Function1.invoke:(Ljava/lang/Object;)Ljava/lang/Object;
      1664: pop
      1665: goto          1669
      1668: pop
      1669: return
      Exception table:
         from    to  target type
             7    28    31   Class java/lang/Exception
           714   722   725   Class java/lang/Exception
           987   995   998   Class java/lang/Exception
          1376  1384  1387   Class java/lang/Exception

  public final void startAboutActivity(int, long, java.lang.String, java.util.ArrayList<org.fossify.commons.models.FAQItem>, boolean);
    Code:
         0: aload         4
         2: ldc_w         #1013               // String versionName
         5: invokestatic  #77                 // Method kotlin/jvm/internal/Intrinsics.checkNotNullParameter:(Ljava/lang/Object;Ljava/lang/String;)V
         8: aload         5
        10: ldc_w         #1015               // String faqItems
        13: invokestatic  #77                 // Method kotlin/jvm/internal/Intrinsics.checkNotNullParameter:(Ljava/lang/Object;Ljava/lang/String;)V
        16: aload_0
        17: checkcast     #118                // class android/app/Activity
        20: invokestatic  #290                // Method org/fossify/commons/extensions/ActivityKt.hideKeyboard:(Landroid/app/Activity;)V
        23: new           #706                // class android/content/Intent
        26: dup
        27: aload_0
        28: invokevirtual #736                // Method getApplicationContext:()Landroid/content/Context;
        31: ldc_w         #1017               // class org/fossify/commons/activities/AboutActivity
        34: invokespecial #1020               // Method android/content/Intent."<init>":(Landroid/content/Context;Ljava/lang/Class;)V
        37: astore        7
        39: aload         7
        41: astore        8
        43: iconst_0
        44: istore        9
        46: aload         8
        48: ldc_w         #1022               // String app_icon_ids
        51: aload_0
        52: invokevirtual #564                // Method getAppIconIDs:()Ljava/util/ArrayList;
        55: checkcast     #1024               // class java/io/Serializable
        58: invokevirtual #1027               // Method android/content/Intent.putExtra:(Ljava/lang/String;Ljava/io/Serializable;)Landroid/content/Intent;
        61: pop
        62: aload         8
        64: ldc_w         #1029               // String app_launcher_name
        67: aload_0
        68: invokevirtual #591                // Method getAppLauncherName:()Ljava/lang/String;
        71: invokevirtual #1032               // Method android/content/Intent.putExtra:(Ljava/lang/String;Ljava/lang/String;)Landroid/content/Intent;
        74: pop
        75: aload         8
        77: ldc_w         #1034               // String app_name
        80: aload_0
        81: iload_1
        82: invokevirtual #493                // Method getString:(I)Ljava/lang/String;
        85: invokevirtual #1032               // Method android/content/Intent.putExtra:(Ljava/lang/String;Ljava/lang/String;)Landroid/content/Intent;
        88: pop
        89: aload         8
        91: ldc_w         #1036               // String app_repo_name
        94: aload_0
        95: invokevirtual #1038               // Method getRepositoryName:()Ljava/lang/String;
        98: invokevirtual #1032               // Method android/content/Intent.putExtra:(Ljava/lang/String;Ljava/lang/String;)Landroid/content/Intent;
       101: pop
       102: aload         8
       104: ldc_w         #1040               // String app_licenses
       107: lload_2
       108: invokevirtual #1043               // Method android/content/Intent.putExtra:(Ljava/lang/String;J)Landroid/content/Intent;
       111: pop
       112: aload         8
       114: ldc_w         #1045               // String app_version_name
       117: aload         4
       119: invokevirtual #1032               // Method android/content/Intent.putExtra:(Ljava/lang/String;Ljava/lang/String;)Landroid/content/Intent;
       122: pop
       123: aload         8
       125: ldc_w         #1047               // String app_package_name
       128: aload_0
       129: checkcast     #177                // class android/content/Context
       132: invokestatic  #183                // Method org/fossify/commons/extensions/ContextKt.getBaseConfig:(Landroid/content/Context;)Lorg/fossify/commons/helpers/BaseConfig;
       135: invokevirtual #1050               // Method org/fossify/commons/helpers/BaseConfig.getAppId:()Ljava/lang/String;
       138: invokevirtual #1032               // Method android/content/Intent.putExtra:(Ljava/lang/String;Ljava/lang/String;)Landroid/content/Intent;
       141: pop
       142: aload         8
       144: ldc_w         #1052               // String app_faq
       147: aload         5
       149: checkcast     #1024               // class java/io/Serializable
       152: invokevirtual #1027               // Method android/content/Intent.putExtra:(Ljava/lang/String;Ljava/io/Serializable;)Landroid/content/Intent;
       155: pop
       156: aload         8
       158: ldc_w         #1054               // String show_faq_before_mail
       161: iload         6
       163: invokevirtual #1057               // Method android/content/Intent.putExtra:(Ljava/lang/String;Z)Landroid/content/Intent;
       166: pop
       167: aload_0
       168: aload         8
       170: invokevirtual #1060               // Method startActivity:(Landroid/content/Intent;)V
       173: nop
       174: nop
       175: return

  public final void startCustomizationActivity();
    Code:
         0: aload_0
         1: invokevirtual #149                // Method getPackageName:()Ljava/lang/String;
         4: dup
         5: ldc           #151                // String getPackageName(...)
         7: invokestatic  #154                // Method kotlin/jvm/internal/Intrinsics.checkNotNullExpressionValue:(Ljava/lang/Object;Ljava/lang/String;)V
        10: checkcast     #507                // class java/lang/CharSequence
        13: ldc_w         #1069               // String yfissof
        16: checkcast     #507                // class java/lang/CharSequence
        19: invokestatic  #1073               // Method kotlin/text/StringsKt.reversed:(Ljava/lang/CharSequence;)Ljava/lang/CharSequence;
        22: invokevirtual #1076               // Method java/lang/Object.toString:()Ljava/lang/String;
        25: checkcast     #507                // class java/lang/CharSequence
        28: iconst_1
        29: invokestatic  #1080               // Method kotlin/text/StringsKt.contains:(Ljava/lang/CharSequence;Ljava/lang/CharSequence;Z)Z
        32: ifne          55
        35: aload_0
        36: checkcast     #177                // class android/content/Context
        39: invokestatic  #183                // Method org/fossify/commons/extensions/ContextKt.getBaseConfig:(Landroid/content/Context;)Lorg/fossify/commons/helpers/BaseConfig;
        42: invokevirtual #189                // Method org/fossify/commons/helpers/BaseConfig.getAppRunCount:()I
        45: bipush        100
        47: if_icmple     55
        50: aload_0
        51: invokestatic  #194                // Method org/fossify/commons/extensions/ActivityKt.showModdedAppWarning:(Lorg/fossify/commons/activities/BaseSimpleActivity;)V
        54: return
        55: new           #706                // class android/content/Intent
        58: dup
        59: aload_0
        60: invokevirtual #736                // Method getApplicationContext:()Landroid/content/Context;
        63: ldc_w         #1082               // class org/fossify/commons/activities/CustomizationActivity
        66: invokespecial #1020               // Method android/content/Intent."<init>":(Landroid/content/Context;Ljava/lang/Class;)V
        69: astore_1
        70: aload_1
        71: astore_2
        72: iconst_0
        73: istore_3
        74: aload_2
        75: ldc_w         #1022               // String app_icon_ids
        78: aload_0
        79: invokevirtual #564                // Method getAppIconIDs:()Ljava/util/ArrayList;
        82: checkcast     #1024               // class java/io/Serializable
        85: invokevirtual #1027               // Method android/content/Intent.putExtra:(Ljava/lang/String;Ljava/io/Serializable;)Landroid/content/Intent;
        88: pop
        89: aload_2
        90: ldc_w         #1029               // String app_launcher_name
        93: aload_0
        94: invokevirtual #591                // Method getAppLauncherName:()Ljava/lang/String;
        97: invokevirtual #1032               // Method android/content/Intent.putExtra:(Ljava/lang/String;Ljava/lang/String;)Landroid/content/Intent;
       100: pop
       101: aload_0
       102: aload_2
       103: invokevirtual #1060               // Method startActivity:(Landroid/content/Intent;)V
       106: nop
       107: nop
       108: return

  public final void launchCustomizeNotificationsIntent();
    Code:
         0: new           #706                // class android/content/Intent
         3: dup
         4: ldc_w         #1087               // String android.settings.APP_NOTIFICATION_SETTINGS
         7: invokespecial #808                // Method android/content/Intent."<init>":(Ljava/lang/String;)V
        10: astore_1
        11: aload_1
        12: astore_2
        13: iconst_0
        14: istore_3
        15: aload_2
        16: ldc_w         #1089               // String android.provider.extra.APP_PACKAGE
        19: aload_0
        20: invokevirtual #149                // Method getPackageName:()Ljava/lang/String;
        23: invokevirtual #1032               // Method android/content/Intent.putExtra:(Ljava/lang/String;Ljava/lang/String;)Landroid/content/Intent;
        26: pop
        27: aload_0
        28: aload_2
        29: invokevirtual #1060               // Method startActivity:(Landroid/content/Intent;)V
        32: nop
        33: nop
        34: return

  public final void launchChangeAppLanguageIntent();
    Code:
         0: nop
         1: new           #706                // class android/content/Intent
         4: dup
         5: ldc_w         #1097               // String android.settings.APP_LOCALE_SETTINGS
         8: invokespecial #808                // Method android/content/Intent."<init>":(Ljava/lang/String;)V
        11: astore_1
        12: aload_1
        13: astore_2
        14: iconst_0
        15: istore_3
        16: aload_2
        17: ldc_w         #1099               // String package
        20: aload_0
        21: invokevirtual #149                // Method getPackageName:()Ljava/lang/String;
        24: aconst_null
        25: invokestatic  #1103               // Method android/net/Uri.fromParts:(Ljava/lang/String;Ljava/lang/String;Ljava/lang/String;)Landroid/net/Uri;
        28: invokevirtual #1107               // Method android/content/Intent.setData:(Landroid/net/Uri;)Landroid/content/Intent;
        31: pop
        32: aload_0
        33: aload_2
        34: invokevirtual #1060               // Method startActivity:(Landroid/content/Intent;)V
        37: nop
        38: goto          49
        41: astore_2
        42: aload_0
        43: checkcast     #177                // class android/content/Context
        46: invokestatic  #1110               // Method org/fossify/commons/extensions/ContextKt.openDeviceSettings:(Landroid/content/Context;)V
        49: return
      Exception table:
         from    to  target type
             0    38    41   Class java/lang/Exception

  public final boolean handleSAFDialog(java.lang.String, kotlin.jvm.functions.Function1<? super java.lang.Boolean, kotlin.Unit>);
    Code:
         0: aload_1
         1: ldc_w         #1116               // String path
         4: invokestatic  #77                 // Method kotlin/jvm/internal/Intrinsics.checkNotNullParameter:(Ljava/lang/Object;Ljava/lang/String;)V
         7: aload_2
         8: ldc_w         #1118               // String callback
        11: invokestatic  #77                 // Method kotlin/jvm/internal/Intrinsics.checkNotNullParameter:(Ljava/lang/Object;Ljava/lang/String;)V
        14: aload_0
        15: checkcast     #118                // class android/app/Activity
        18: invokestatic  #290                // Method org/fossify/commons/extensions/ActivityKt.hideKeyboard:(Landroid/app/Activity;)V
        21: aload_0
        22: invokevirtual #149                // Method getPackageName:()Ljava/lang/String;
        25: dup
        26: ldc           #151                // String getPackageName(...)
        28: invokestatic  #154                // Method kotlin/jvm/internal/Intrinsics.checkNotNullExpressionValue:(Ljava/lang/Object;Ljava/lang/String;)V
        31: ldc_w         #1120               // String org.fossify
        34: iconst_0
        35: iconst_2
        36: aconst_null
        37: invokestatic  #1123               // Method kotlin/text/StringsKt.startsWith$default:(Ljava/lang/String;Ljava/lang/String;ZILjava/lang/Object;)Z
        40: ifne          58
        43: aload_2
        44: iconst_1
        45: invokestatic  #755                // Method java/lang/Boolean.valueOf:(Z)Ljava/lang/Boolean;
        48: invokeinterface #759,  2          // InterfaceMethod kotlin/jvm/functions/Function1.invoke:(Ljava/lang/Object;)Ljava/lang/Object;
        53: pop
        54: iconst_0
        55: goto          94
        58: aload_0
        59: aload_1
        60: invokestatic  #1127               // Method org/fossify/commons/extensions/ActivityKt.isShowingSAFDialog:(Lorg/fossify/commons/activities/BaseSimpleActivity;Ljava/lang/String;)Z
        63: ifne          74
        66: aload_0
        67: aload_1
        68: invokestatic  #1130               // Method org/fossify/commons/extensions/ActivityKt.isShowingOTGDialog:(Lorg/fossify/commons/activities/BaseSimpleActivity;Ljava/lang/String;)Z
        71: ifeq          82
        74: aload_2
        75: putstatic     #258                // Field funAfterSAFPermission:Lkotlin/jvm/functions/Function1;
        78: iconst_1
        79: goto          94
        82: aload_2
        83: iconst_1
        84: invokestatic  #755                // Method java/lang/Boolean.valueOf:(Z)Ljava/lang/Boolean;
        87: invokeinterface #759,  2          // InterfaceMethod kotlin/jvm/functions/Function1.invoke:(Ljava/lang/Object;)Ljava/lang/Object;
        92: pop
        93: iconst_0
        94: ireturn

  public final boolean handleSAFDialogSdk30(java.lang.String, boolean, kotlin.jvm.functions.Function1<? super java.lang.Boolean, kotlin.Unit>);
    Code:
         0: aload_1
         1: ldc_w         #1116               // String path
         4: invokestatic  #77                 // Method kotlin/jvm/internal/Intrinsics.checkNotNullParameter:(Ljava/lang/Object;Ljava/lang/String;)V
         7: aload_3
         8: ldc_w         #1118               // String callback
        11: invokestatic  #77                 // Method kotlin/jvm/internal/Intrinsics.checkNotNullParameter:(Ljava/lang/Object;Ljava/lang/String;)V
        14: aload_0
        15: checkcast     #118                // class android/app/Activity
        18: invokestatic  #290                // Method org/fossify/commons/extensions/ActivityKt.hideKeyboard:(Landroid/app/Activity;)V
        21: aload_0
        22: invokevirtual #149                // Method getPackageName:()Ljava/lang/String;
        25: dup
        26: ldc           #151                // String getPackageName(...)
        28: invokestatic  #154                // Method kotlin/jvm/internal/Intrinsics.checkNotNullExpressionValue:(Ljava/lang/Object;Ljava/lang/String;)V
        31: ldc_w         #1120               // String org.fossify
        34: iconst_0
        35: iconst_2
        36: aconst_null
        37: invokestatic  #1123               // Method kotlin/text/StringsKt.startsWith$default:(Ljava/lang/String;Ljava/lang/String;ZILjava/lang/Object;)Z
        40: ifne          58
        43: aload_3
        44: iconst_1
        45: invokestatic  #755                // Method java/lang/Boolean.valueOf:(Z)Ljava/lang/Boolean;
        48: invokeinterface #759,  2          // InterfaceMethod kotlin/jvm/functions/Function1.invoke:(Ljava/lang/Object;)Ljava/lang/Object;
        53: pop
        54: iconst_0
        55: goto          87
        58: aload_0
        59: aload_1
        60: iload_2
        61: invokestatic  #1137               // Method org/fossify/commons/extensions/ActivityKt.isShowingSAFDialogSdk30:(Lorg/fossify/commons/activities/BaseSimpleActivity;Ljava/lang/String;Z)Z
        64: ifeq          75
        67: aload_3
        68: putstatic     #749                // Field funAfterSdk30Action:Lkotlin/jvm/functions/Function1;
        71: iconst_1
        72: goto          87
        75: aload_3
        76: iconst_1
        77: invokestatic  #755                // Method java/lang/Boolean.valueOf:(Z)Ljava/lang/Boolean;
        80: invokeinterface #759,  2          // InterfaceMethod kotlin/jvm/functions/Function1.invoke:(Ljava/lang/Object;)Ljava/lang/Object;
        85: pop
        86: iconst_0
        87: ireturn

  public static boolean handleSAFDialogSdk30$default(org.fossify.commons.activities.BaseSimpleActivity, java.lang.String, boolean, kotlin.jvm.functions.Function1, int, java.lang.Object);
    Code:
         0: aload         5
         2: ifnull        16
         5: new           #366                // class java/lang/UnsupportedOperationException
         8: dup
         9: ldc_w         #1142               // String Super calls with default arguments not supported in this target, function: handleSAFDialogSdk30
        12: invokespecial #370                // Method java/lang/UnsupportedOperationException."<init>":(Ljava/lang/String;)V
        15: athrow
        16: iload         4
        18: iconst_2
        19: iand
        20: ifeq          25
        23: iconst_1
        24: istore_2
        25: aload_0
        26: aload_1
        27: iload_2
        28: aload_3
        29: invokevirtual #1144               // Method handleSAFDialogSdk30:(Ljava/lang/String;ZLkotlin/jvm/functions/Function1;)Z
        32: ireturn

  public final boolean checkManageMediaOrHandleSAFDialogSdk30(java.lang.String, kotlin.jvm.functions.Function1<? super java.lang.Boolean, kotlin.Unit>);
    Code:
         0: aload_1
         1: ldc_w         #1116               // String path
         4: invokestatic  #77                 // Method kotlin/jvm/internal/Intrinsics.checkNotNullParameter:(Ljava/lang/Object;Ljava/lang/String;)V
         7: aload_2
         8: ldc_w         #1118               // String callback
        11: invokestatic  #77                 // Method kotlin/jvm/internal/Intrinsics.checkNotNullParameter:(Ljava/lang/Object;Ljava/lang/String;)V
        14: aload_0
        15: checkcast     #118                // class android/app/Activity
        18: invokestatic  #290                // Method org/fossify/commons/extensions/ActivityKt.hideKeyboard:(Landroid/app/Activity;)V
        21: aload_0
        22: checkcast     #177                // class android/content/Context
        25: invokestatic  #1149               // Method org/fossify/commons/extensions/Context_storage_sdk30Kt.canManageMedia:(Landroid/content/Context;)Z
        28: ifeq          46
        31: aload_2
        32: iconst_1
        33: invokestatic  #755                // Method java/lang/Boolean.valueOf:(Z)Ljava/lang/Boolean;
        36: invokeinterface #759,  2          // InterfaceMethod kotlin/jvm/functions/Function1.invoke:(Ljava/lang/Object;)Ljava/lang/Object;
        41: pop
        42: iconst_0
        43: goto          55
        46: aload_0
        47: aload_1
        48: iconst_0
        49: aload_2
        50: iconst_2
        51: aconst_null
        52: invokestatic  #1151               // Method handleSAFDialogSdk30$default:(Lorg/fossify/commons/activities/BaseSimpleActivity;Ljava/lang/String;ZLkotlin/jvm/functions/Function1;ILjava/lang/Object;)Z
        55: ireturn

  public final boolean handleSAFCreateDocumentDialogSdk30(java.lang.String, kotlin.jvm.functions.Function1<? super java.lang.Boolean, kotlin.Unit>);
    Code:
         0: aload_1
         1: ldc_w         #1116               // String path
         4: invokestatic  #77                 // Method kotlin/jvm/internal/Intrinsics.checkNotNullParameter:(Ljava/lang/Object;Ljava/lang/String;)V
         7: aload_2
         8: ldc_w         #1118               // String callback
        11: invokestatic  #77                 // Method kotlin/jvm/internal/Intrinsics.checkNotNullParameter:(Ljava/lang/Object;Ljava/lang/String;)V
        14: aload_0
        15: checkcast     #118                // class android/app/Activity
        18: invokestatic  #290                // Method org/fossify/commons/extensions/ActivityKt.hideKeyboard:(Landroid/app/Activity;)V
        21: aload_0
        22: invokevirtual #149                // Method getPackageName:()Ljava/lang/String;
        25: dup
        26: ldc           #151                // String getPackageName(...)
        28: invokestatic  #154                // Method kotlin/jvm/internal/Intrinsics.checkNotNullExpressionValue:(Ljava/lang/Object;Ljava/lang/String;)V
        31: ldc_w         #1120               // String org.fossify
        34: iconst_0
        35: iconst_2
        36: aconst_null
        37: invokestatic  #1123               // Method kotlin/text/StringsKt.startsWith$default:(Ljava/lang/String;Ljava/lang/String;ZILjava/lang/Object;)Z
        40: ifne          58
        43: aload_2
        44: iconst_1
        45: invokestatic  #755                // Method java/lang/Boolean.valueOf:(Z)Ljava/lang/Boolean;
        48: invokeinterface #759,  2          // InterfaceMethod kotlin/jvm/functions/Function1.invoke:(Ljava/lang/Object;)Ljava/lang/Object;
        53: pop
        54: iconst_0
        55: goto          86
        58: aload_0
        59: aload_1
        60: invokestatic  #1155               // Method org/fossify/commons/extensions/ActivityKt.isShowingSAFCreateDocumentDialogSdk30:(Lorg/fossify/commons/activities/BaseSimpleActivity;Ljava/lang/String;)Z
        63: ifeq          74
        66: aload_2
        67: putstatic     #749                // Field funAfterSdk30Action:Lkotlin/jvm/functions/Function1;
        70: iconst_1
        71: goto          86
        74: aload_2
        75: iconst_1
        76: invokestatic  #755                // Method java/lang/Boolean.valueOf:(Z)Ljava/lang/Boolean;
        79: invokeinterface #759,  2          // InterfaceMethod kotlin/jvm/functions/Function1.invoke:(Ljava/lang/Object;)Ljava/lang/Object;
        84: pop
        85: iconst_0
        86: ireturn

  public final boolean handleAndroidSAFDialog(java.lang.String, boolean, kotlin.jvm.functions.Function1<? super java.lang.Boolean, kotlin.Unit>);
    Code:
         0: aload_1
         1: ldc_w         #1116               // String path
         4: invokestatic  #77                 // Method kotlin/jvm/internal/Intrinsics.checkNotNullParameter:(Ljava/lang/Object;Ljava/lang/String;)V
         7: aload_3
         8: ldc_w         #1118               // String callback
        11: invokestatic  #77                 // Method kotlin/jvm/internal/Intrinsics.checkNotNullParameter:(Ljava/lang/Object;Ljava/lang/String;)V
        14: aload_0
        15: checkcast     #118                // class android/app/Activity
        18: invokestatic  #290                // Method org/fossify/commons/extensions/ActivityKt.hideKeyboard:(Landroid/app/Activity;)V
        21: aload_0
        22: invokevirtual #149                // Method getPackageName:()Ljava/lang/String;
        25: dup
        26: ldc           #151                // String getPackageName(...)
        28: invokestatic  #154                // Method kotlin/jvm/internal/Intrinsics.checkNotNullExpressionValue:(Ljava/lang/Object;Ljava/lang/String;)V
        31: ldc_w         #1120               // String org.fossify
        34: iconst_0
        35: iconst_2
        36: aconst_null
        37: invokestatic  #1123               // Method kotlin/text/StringsKt.startsWith$default:(Ljava/lang/String;Ljava/lang/String;ZILjava/lang/Object;)Z
        40: ifne          58
        43: aload_3
        44: iconst_1
        45: invokestatic  #755                // Method java/lang/Boolean.valueOf:(Z)Ljava/lang/Boolean;
        48: invokeinterface #759,  2          // InterfaceMethod kotlin/jvm/functions/Function1.invoke:(Ljava/lang/Object;)Ljava/lang/Object;
        53: pop
        54: iconst_0
        55: goto          87
        58: aload_0
        59: aload_1
        60: iload_2
        61: invokestatic  #1159               // Method org/fossify/commons/extensions/ActivityKt.isShowingAndroidSAFDialog:(Lorg/fossify/commons/activities/BaseSimpleActivity;Ljava/lang/String;Z)Z
        64: ifeq          75
        67: aload_3
        68: putstatic     #258                // Field funAfterSAFPermission:Lkotlin/jvm/functions/Function1;
        71: iconst_1
        72: goto          87
        75: aload_3
        76: iconst_1
        77: invokestatic  #755                // Method java/lang/Boolean.valueOf:(Z)Ljava/lang/Boolean;
        80: invokeinterface #759,  2          // InterfaceMethod kotlin/jvm/functions/Function1.invoke:(Ljava/lang/Object;)Ljava/lang/Object;
        85: pop
        86: iconst_0
        87: ireturn

  public static boolean handleAndroidSAFDialog$default(org.fossify.commons.activities.BaseSimpleActivity, java.lang.String, boolean, kotlin.jvm.functions.Function1, int, java.lang.Object);
    Code:
         0: aload         5
         2: ifnull        16
         5: new           #366                // class java/lang/UnsupportedOperationException
         8: dup
         9: ldc_w         #1163               // String Super calls with default arguments not supported in this target, function: handleAndroidSAFDialog
        12: invokespecial #370                // Method java/lang/UnsupportedOperationException."<init>":(Ljava/lang/String;)V
        15: athrow
        16: iload         4
        18: iconst_2
        19: iand
        20: ifeq          25
        23: iconst_0
        24: istore_2
        25: aload_0
        26: aload_1
        27: iload_2
        28: aload_3
        29: invokevirtual #1165               // Method handleAndroidSAFDialog:(Ljava/lang/String;ZLkotlin/jvm/functions/Function1;)Z
        32: ireturn

  public final void handleOTGPermission(kotlin.jvm.functions.Function1<? super java.lang.Boolean, kotlin.Unit>);
    Code:
         0: aload_1
         1: ldc_w         #1118               // String callback
         4: invokestatic  #77                 // Method kotlin/jvm/internal/Intrinsics.checkNotNullParameter:(Ljava/lang/Object;Ljava/lang/String;)V
         7: aload_0
         8: checkcast     #118                // class android/app/Activity
        11: invokestatic  #290                // Method org/fossify/commons/extensions/ActivityKt.hideKeyboard:(Landroid/app/Activity;)V
        14: aload_0
        15: checkcast     #177                // class android/content/Context
        18: invokestatic  #183                // Method org/fossify/commons/extensions/ContextKt.getBaseConfig:(Landroid/content/Context;)Lorg/fossify/commons/helpers/BaseConfig;
        21: invokevirtual #792                // Method org/fossify/commons/helpers/BaseConfig.getOTGTreeUri:()Ljava/lang/String;
        24: checkcast     #507                // class java/lang/CharSequence
        27: invokeinterface #833,  1          // InterfaceMethod java/lang/CharSequence.length:()I
        32: ifle          39
        35: iconst_1
        36: goto          40
        39: iconst_0
        40: ifeq          55
        43: aload_1
        44: iconst_1
        45: invokestatic  #755                // Method java/lang/Boolean.valueOf:(Z)Ljava/lang/Boolean;
        48: invokeinterface #759,  2          // InterfaceMethod kotlin/jvm/functions/Function1.invoke:(Ljava/lang/Object;)Ljava/lang/Object;
        53: pop
        54: return
        55: aload_1
        56: putstatic     #258                // Field funAfterSAFPermission:Lkotlin/jvm/functions/Function1;
        59: new           #1168               // class org/fossify/commons/dialogs/WritePermissionDialog
        62: dup
        63: aload_0
        64: checkcast     #118                // class android/app/Activity
        67: getstatic     #1174               // Field org/fossify/commons/dialogs/WritePermissionDialog$WritePermissionDialogMode$Otg.INSTANCE:Lorg/fossify/commons/dialogs/WritePermissionDialog$WritePermissionDialogMode$Otg;
        70: checkcast     #1176               // class org/fossify/commons/dialogs/WritePermissionDialog$WritePermissionDialogMode
        73: aload_0
        74: invokedynamic #1187,  0           // InvokeDynamic #3:invoke:(Lorg/fossify/commons/activities/BaseSimpleActivity;)Lkotlin/jvm/functions/Function0;
        79: invokespecial #1190               // Method org/fossify/commons/dialogs/WritePermissionDialog."<init>":(Landroid/app/Activity;Lorg/fossify/commons/dialogs/WritePermissionDialog$WritePermissionDialogMode;Lkotlin/jvm/functions/Function0;)V
        82: pop
        83: return

  public final void deleteSDK30Uris(java.util.List<? extends android.net.Uri>, kotlin.jvm.functions.Function1<? super java.lang.Boolean, kotlin.Unit>);
    Code:
         0: aload_1
         1: ldc_w         #1197               // String uris
         4: invokestatic  #77                 // Method kotlin/jvm/internal/Intrinsics.checkNotNullParameter:(Ljava/lang/Object;Ljava/lang/String;)V
         7: aload_2
         8: ldc_w         #1118               // String callback
        11: invokestatic  #77                 // Method kotlin/jvm/internal/Intrinsics.checkNotNullParameter:(Ljava/lang/Object;Ljava/lang/String;)V
        14: aload_0
        15: checkcast     #118                // class android/app/Activity
        18: invokestatic  #290                // Method org/fossify/commons/extensions/ActivityKt.hideKeyboard:(Landroid/app/Activity;)V
        21: invokestatic  #811                // Method org/fossify/commons/helpers/ConstantsKt.isRPlus:()Z
        24: ifeq          84
        27: aload_2
        28: putstatic     #749                // Field funAfterSdk30Action:Lkotlin/jvm/functions/Function1;
        31: nop
        32: aload_0
        33: invokevirtual #893                // Method getContentResolver:()Landroid/content/ContentResolver;
        36: aload_1
        37: checkcast     #1199               // class java/util/Collection
        40: invokestatic  #1205               // Method android/provider/MediaStore.createDeleteRequest:(Landroid/content/ContentResolver;Ljava/util/Collection;)Landroid/app/PendingIntent;
        43: invokevirtual #1211               // Method android/app/PendingIntent.getIntentSender:()Landroid/content/IntentSender;
        46: dup
        47: ldc_w         #1213               // String getIntentSender(...)
        50: invokestatic  #154                // Method kotlin/jvm/internal/Intrinsics.checkNotNullExpressionValue:(Ljava/lang/Object;Ljava/lang/String;)V
        53: astore_3
        54: aload_0
        55: aload_3
        56: sipush        300
        59: aconst_null
        60: iconst_0
        61: iconst_0
        62: iconst_0
        63: invokevirtual #1217               // Method startIntentSenderForResult:(Landroid/content/IntentSender;ILandroid/content/Intent;III)V
        66: goto          95
        69: astore_3
        70: aload_0
        71: checkcast     #177                // class android/content/Context
        74: aload_3
        75: iconst_0
        76: iconst_2
        77: aconst_null
        78: invokestatic  #830                // Method org/fossify/commons/extensions/ContextKt.showErrorToast$default:(Landroid/content/Context;Ljava/lang/Exception;IILjava/lang/Object;)V
        81: goto          95
        84: aload_2
        85: iconst_0
        86: invokestatic  #755                // Method java/lang/Boolean.valueOf:(Z)Ljava/lang/Boolean;
        89: invokeinterface #759,  2          // InterfaceMethod kotlin/jvm/functions/Function1.invoke:(Ljava/lang/Object;)Ljava/lang/Object;
        94: pop
        95: return
      Exception table:
         from    to  target type
            31    66    69   Class java/lang/Exception

  public final void trashSDK30Uris(java.util.List<? extends android.net.Uri>, boolean, kotlin.jvm.functions.Function1<? super java.lang.Boolean, kotlin.Unit>);
    Code:
         0: aload_1
         1: ldc_w         #1197               // String uris
         4: invokestatic  #77                 // Method kotlin/jvm/internal/Intrinsics.checkNotNullParameter:(Ljava/lang/Object;Ljava/lang/String;)V
         7: aload_3
         8: ldc_w         #1118               // String callback
        11: invokestatic  #77                 // Method kotlin/jvm/internal/Intrinsics.checkNotNullParameter:(Ljava/lang/Object;Ljava/lang/String;)V
        14: aload_0
        15: checkcast     #118                // class android/app/Activity
        18: invokestatic  #290                // Method org/fossify/commons/extensions/ActivityKt.hideKeyboard:(Landroid/app/Activity;)V
        21: invokestatic  #811                // Method org/fossify/commons/helpers/ConstantsKt.isRPlus:()Z
        24: ifeq          89
        27: aload_3
        28: putstatic     #918                // Field funAfterTrash30File:Lkotlin/jvm/functions/Function1;
        31: nop
        32: aload_0
        33: invokevirtual #893                // Method getContentResolver:()Landroid/content/ContentResolver;
        36: aload_1
        37: checkcast     #1199               // class java/util/Collection
        40: iload_2
        41: invokestatic  #1227               // Method android/provider/MediaStore.createTrashRequest:(Landroid/content/ContentResolver;Ljava/util/Collection;Z)Landroid/app/PendingIntent;
        44: invokevirtual #1211               // Method android/app/PendingIntent.getIntentSender:()Landroid/content/IntentSender;
        47: dup
        48: ldc_w         #1213               // String getIntentSender(...)
        51: invokestatic  #154                // Method kotlin/jvm/internal/Intrinsics.checkNotNullExpressionValue:(Ljava/lang/Object;Ljava/lang/String;)V
        54: astore        4
        56: aload_0
        57: aload         4
        59: sipush        304
        62: aconst_null
        63: iconst_0
        64: iconst_0
        65: iconst_0
        66: invokevirtual #1217               // Method startIntentSenderForResult:(Landroid/content/IntentSender;ILandroid/content/Intent;III)V
        69: goto          100
        72: astore        4
        74: aload_0
        75: checkcast     #177                // class android/content/Context
        78: aload         4
        80: iconst_0
        81: iconst_2
        82: aconst_null
        83: invokestatic  #830                // Method org/fossify/commons/extensions/ContextKt.showErrorToast$default:(Landroid/content/Context;Ljava/lang/Exception;IILjava/lang/Object;)V
        86: goto          100
        89: aload_3
        90: iconst_0
        91: invokestatic  #755                // Method java/lang/Boolean.valueOf:(Z)Ljava/lang/Boolean;
        94: invokeinterface #759,  2          // InterfaceMethod kotlin/jvm/functions/Function1.invoke:(Ljava/lang/Object;)Ljava/lang/Object;
        99: pop
       100: return
      Exception table:
         from    to  target type
            31    69    72   Class java/lang/Exception

  public final void updateSDK30Uris(java.util.List<? extends android.net.Uri>, kotlin.jvm.functions.Function1<? super java.lang.Boolean, kotlin.Unit>);
    Code:
         0: aload_1
         1: ldc_w         #1197               // String uris
         4: invokestatic  #77                 // Method kotlin/jvm/internal/Intrinsics.checkNotNullParameter:(Ljava/lang/Object;Ljava/lang/String;)V
         7: aload_2
         8: ldc_w         #1118               // String callback
        11: invokestatic  #77                 // Method kotlin/jvm/internal/Intrinsics.checkNotNullParameter:(Ljava/lang/Object;Ljava/lang/String;)V
        14: aload_0
        15: checkcast     #118                // class android/app/Activity
        18: invokestatic  #290                // Method org/fossify/commons/extensions/ActivityKt.hideKeyboard:(Landroid/app/Activity;)V
        21: invokestatic  #811                // Method org/fossify/commons/helpers/ConstantsKt.isRPlus:()Z
        24: ifeq          84
        27: aload_2
        28: putstatic     #907                // Field funAfterUpdate30File:Lkotlin/jvm/functions/Function1;
        31: nop
        32: aload_0
        33: invokevirtual #893                // Method getContentResolver:()Landroid/content/ContentResolver;
        36: aload_1
        37: checkcast     #1199               // class java/util/Collection
        40: invokestatic  #1233               // Method android/provider/MediaStore.createWriteRequest:(Landroid/content/ContentResolver;Ljava/util/Collection;)Landroid/app/PendingIntent;
        43: invokevirtual #1211               // Method android/app/PendingIntent.getIntentSender:()Landroid/content/IntentSender;
        46: dup
        47: ldc_w         #1213               // String getIntentSender(...)
        50: invokestatic  #154                // Method kotlin/jvm/internal/Intrinsics.checkNotNullExpressionValue:(Ljava/lang/Object;Ljava/lang/String;)V
        53: astore_3
        54: aload_0
        55: aload_3
        56: sipush        302
        59: aconst_null
        60: iconst_0
        61: iconst_0
        62: iconst_0
        63: invokevirtual #1217               // Method startIntentSenderForResult:(Landroid/content/IntentSender;ILandroid/content/Intent;III)V
        66: goto          95
        69: astore_3
        70: aload_0
        71: checkcast     #177                // class android/content/Context
        74: aload_3
        75: iconst_0
        76: iconst_2
        77: aconst_null
        78: invokestatic  #830                // Method org/fossify/commons/extensions/ContextKt.showErrorToast$default:(Landroid/content/Context;Ljava/lang/Exception;IILjava/lang/Object;)V
        81: goto          95
        84: aload_2
        85: iconst_0
        86: invokestatic  #755                // Method java/lang/Boolean.valueOf:(Z)Ljava/lang/Boolean;
        89: invokeinterface #759,  2          // InterfaceMethod kotlin/jvm/functions/Function1.invoke:(Ljava/lang/Object;)Ljava/lang/Object;
        94: pop
        95: return
      Exception table:
         from    to  target type
            31    66    69   Class java/lang/Exception

  public final void handleRecoverableSecurityException(kotlin.jvm.functions.Function1<? super java.lang.Boolean, kotlin.Unit>);
    Code:
         0: aload_1
         1: ldc_w         #1118               // String callback
         4: invokestatic  #77                 // Method kotlin/jvm/internal/Intrinsics.checkNotNullParameter:(Ljava/lang/Object;Ljava/lang/String;)V
         7: nop
         8: aload_1
         9: iconst_1
        10: invokestatic  #755                // Method java/lang/Boolean.valueOf:(Z)Ljava/lang/Boolean;
        13: invokeinterface #759,  2          // InterfaceMethod kotlin/jvm/functions/Function1.invoke:(Ljava/lang/Object;)Ljava/lang/Object;
        18: pop
        19: goto          102
        22: astore_2
        23: invokestatic  #514                // Method org/fossify/commons/helpers/ConstantsKt.isQPlus:()Z
        26: ifeq          91
        29: aload_1
        30: putstatic     #904                // Field funRecoverableSecurity:Lkotlin/jvm/functions/Function1;
        33: aload_2
        34: instanceof    #1239               // class android/app/RecoverableSecurityException
        37: ifeq          47
        40: aload_2
        41: checkcast     #1239               // class android/app/RecoverableSecurityException
        44: goto          48
        47: aconst_null
        48: dup
        49: ifnonnull     55
        52: pop
        53: aload_2
        54: athrow
        55: astore_3
        56: aload_3
        57: invokevirtual #1243               // Method android/app/RecoverableSecurityException.getUserAction:()Landroid/app/RemoteAction;
        60: invokevirtual #1249               // Method android/app/RemoteAction.getActionIntent:()Landroid/app/PendingIntent;
        63: invokevirtual #1211               // Method android/app/PendingIntent.getIntentSender:()Landroid/content/IntentSender;
        66: dup
        67: ldc_w         #1213               // String getIntentSender(...)
        70: invokestatic  #154                // Method kotlin/jvm/internal/Intrinsics.checkNotNullExpressionValue:(Ljava/lang/Object;Ljava/lang/String;)V
        73: astore        4
        75: aload_0
        76: aload         4
        78: sipush        301
        81: aconst_null
        82: iconst_0
        83: iconst_0
        84: iconst_0
        85: invokevirtual #1217               // Method startIntentSenderForResult:(Landroid/content/IntentSender;ILandroid/content/Intent;III)V
        88: goto          102
        91: aload_1
        92: iconst_0
        93: invokestatic  #755                // Method java/lang/Boolean.valueOf:(Z)Ljava/lang/Boolean;
        96: invokeinterface #759,  2          // InterfaceMethod kotlin/jvm/functions/Function1.invoke:(Ljava/lang/Object;)Ljava/lang/Object;
       101: pop
       102: return
      Exception table:
         from    to  target type
             7    19    22   Class java/lang/SecurityException

  public final void launchMediaManagementIntent(kotlin.jvm.functions.Function0<kotlin.Unit>);
    Code:
         0: aload_1
         1: ldc_w         #1118               // String callback
         4: invokestatic  #77                 // Method kotlin/jvm/internal/Intrinsics.checkNotNullParameter:(Ljava/lang/Object;Ljava/lang/String;)V
         7: new           #706                // class android/content/Intent
        10: dup
        11: ldc_w         #1260               // String android.settings.REQUEST_MANAGE_MEDIA
        14: invokespecial #808                // Method android/content/Intent."<init>":(Ljava/lang/String;)V
        17: astore_2
        18: aload_2
        19: astore_3
        20: iconst_0
        21: istore        4
        23: aload_3
        24: aload_0
        25: invokevirtual #149                // Method getPackageName:()Ljava/lang/String;
        28: invokedynamic #1263,  0           // InvokeDynamic #4:makeConcatWithConstants:(Ljava/lang/String;)Ljava/lang/String;
        33: astore        5
        35: iconst_0
        36: istore        6
        38: aload         5
        40: invokestatic  #1267               // Method android/net/Uri.parse:(Ljava/lang/String;)Landroid/net/Uri;
        43: invokevirtual #1107               // Method android/content/Intent.setData:(Landroid/net/Uri;)Landroid/content/Intent;
        46: pop
        47: nop
        48: aload_0
        49: aload_3
        50: sipush        303
        53: invokevirtual #826                // Method startActivityForResult:(Landroid/content/Intent;I)V
        56: goto          73
        59: astore        5
        61: aload_0
        62: checkcast     #177                // class android/content/Context
        65: aload         5
        67: iconst_0
        68: iconst_2
        69: aconst_null
        70: invokestatic  #830                // Method org/fossify/commons/extensions/ContextKt.showErrorToast$default:(Landroid/content/Context;Ljava/lang/Exception;IILjava/lang/Object;)V
        73: nop
        74: nop
        75: aload_1
        76: putstatic     #911                // Field funAfterManageMediaPermission:Lkotlin/jvm/functions/Function0;
        79: return
      Exception table:
         from    to  target type
            47    56    59   Class java/lang/Exception

  public final void copyMoveFilesTo(java.util.ArrayList<org.fossify.commons.models.FileDirItem>, java.lang.String, java.lang.String, boolean, boolean, boolean, kotlin.jvm.functions.Function1<? super java.lang.String, kotlin.Unit>);
    Code:
         0: aload_1
         1: ldc_w         #1276               // String fileDirItems
         4: invokestatic  #77                 // Method kotlin/jvm/internal/Intrinsics.checkNotNullParameter:(Ljava/lang/Object;Ljava/lang/String;)V
         7: aload_2
         8: ldc_w         #1278               // String source
        11: invokestatic  #77                 // Method kotlin/jvm/internal/Intrinsics.checkNotNullParameter:(Ljava/lang/Object;Ljava/lang/String;)V
        14: aload_3
        15: ldc_w         #1280               // String destination
        18: invokestatic  #77                 // Method kotlin/jvm/internal/Intrinsics.checkNotNullParameter:(Ljava/lang/Object;Ljava/lang/String;)V
        21: aload         7
        23: ldc_w         #1118               // String callback
        26: invokestatic  #77                 // Method kotlin/jvm/internal/Intrinsics.checkNotNullParameter:(Ljava/lang/Object;Ljava/lang/String;)V
        29: aload_2
        30: aload_3
        31: invokestatic  #720                // Method kotlin/jvm/internal/Intrinsics.areEqual:(Ljava/lang/Object;Ljava/lang/Object;)Z
        34: ifeq          51
        37: aload_0
        38: checkcast     #177                // class android/content/Context
        41: getstatic     #1283               // Field org/fossify/commons/R$string.source_and_destination_same:I
        44: iconst_0
        45: iconst_2
        46: aconst_null
        47: invokestatic  #856                // Method org/fossify/commons/extensions/ContextKt.toast$default:(Landroid/content/Context;IIILjava/lang/Object;)V
        50: return
        51: aload_0
        52: checkcast     #177                // class android/content/Context
        55: aload_3
        56: aconst_null
        57: iconst_2
        58: aconst_null
        59: invokestatic  #1287               // Method org/fossify/commons/extensions/Context_storageKt.getDoesFilePathExist$default:(Landroid/content/Context;Ljava/lang/String;Ljava/lang/String;ILjava/lang/Object;)Z
        62: ifne          79
        65: aload_0
        66: checkcast     #177                // class android/content/Context
        69: getstatic     #1290               // Field org/fossify/commons/R$string.invalid_destination:I
        72: iconst_0
        73: iconst_2
        74: aconst_null
        75: invokestatic  #856                // Method org/fossify/commons/extensions/ContextKt.toast$default:(Landroid/content/Context;IIILjava/lang/Object;)V
        78: return
        79: aload_0
        80: aload_3
        81: aload_0
        82: aload_3
        83: aload         7
        85: aload_1
        86: iload         4
        88: iload         5
        90: iload         6
        92: aload_2
        93: invokedynamic #1300,  0           // InvokeDynamic #5:invoke:(Lorg/fossify/commons/activities/BaseSimpleActivity;Ljava/lang/String;Lkotlin/jvm/functions/Function1;Ljava/util/ArrayList;ZZZLjava/lang/String;)Lkotlin/jvm/functions/Function1;
        98: invokevirtual #1302               // Method handleSAFDialog:(Ljava/lang/String;Lkotlin/jvm/functions/Function1;)Z
       101: pop
       102: return

  public final java.io.File getAlternativeFile(java.io.File);
    Code:
         0: aload_1
         1: ldc_w         #1310               // String file
         4: invokestatic  #77                 // Method kotlin/jvm/internal/Intrinsics.checkNotNullParameter:(Ljava/lang/Object;Ljava/lang/String;)V
         7: iconst_1
         8: istore_2
         9: aconst_null
        10: astore_3
        11: getstatic     #1315               // Field kotlin/jvm/internal/StringCompanionObject.INSTANCE:Lkotlin/jvm/internal/StringCompanionObject;
        14: pop
        15: ldc_w         #1317               // String %s(%d).%s
        18: astore        5
        20: iconst_3
        21: anewarray     #640                // class java/lang/Object
        24: astore        6
        26: aload         6
        28: iconst_0
        29: aload_1
        30: invokestatic  #1323               // Method kotlin/io/FilesKt.getNameWithoutExtension:(Ljava/io/File;)Ljava/lang/String;
        33: aastore
        34: aload         6
        36: iconst_1
        37: iload_2
        38: invokestatic  #1328               // Method java/lang/Integer.valueOf:(I)Ljava/lang/Integer;
        41: aastore
        42: aload         6
        44: iconst_2
        45: aload_1
        46: invokestatic  #1331               // Method kotlin/io/FilesKt.getExtension:(Ljava/io/File;)Ljava/lang/String;
        49: aastore
        50: aload         6
        52: astore        6
        54: aload         5
        56: aload         6
        58: aload         6
        60: arraylength
        61: invokestatic  #1337               // Method java/util/Arrays.copyOf:([Ljava/lang/Object;I)[Ljava/lang/Object;
        64: invokestatic  #1341               // Method java/lang/String.format:(Ljava/lang/String;[Ljava/lang/Object;)Ljava/lang/String;
        67: dup
        68: ldc_w         #1343               // String format(...)
        71: invokestatic  #154                // Method kotlin/jvm/internal/Intrinsics.checkNotNullExpressionValue:(Ljava/lang/Object;Ljava/lang/String;)V
        74: astore        4
        76: new           #1345               // class java/io/File
        79: dup
        80: aload_1
        81: invokevirtual #1348               // Method java/io/File.getParent:()Ljava/lang/String;
        84: aload         4
        86: invokespecial #1351               // Method java/io/File."<init>":(Ljava/lang/String;Ljava/lang/String;)V
        89: astore_3
        90: iinc          2, 1
        93: aload_0
        94: checkcast     #177                // class android/content/Context
        97: aload_3
        98: invokevirtual #1354               // Method java/io/File.getAbsolutePath:()Ljava/lang/String;
       101: dup
       102: ldc_w         #1356               // String getAbsolutePath(...)
       105: invokestatic  #154                // Method kotlin/jvm/internal/Intrinsics.checkNotNullExpressionValue:(Ljava/lang/Object;Ljava/lang/String;)V
       108: aconst_null
       109: iconst_2
       110: aconst_null
       111: invokestatic  #1287               // Method org/fossify/commons/extensions/Context_storageKt.getDoesFilePathExist$default:(Landroid/content/Context;Ljava/lang/String;Ljava/lang/String;ILjava/lang/Object;)Z
       114: ifne          11
       117: aload_3
       118: areturn

  public final void checkConflicts(java.util.ArrayList<org.fossify.commons.models.FileDirItem>, java.lang.String, int, java.util.LinkedHashMap<java.lang.String, java.lang.Integer>, kotlin.jvm.functions.Function1<? super java.util.LinkedHashMap<java.lang.String, java.lang.Integer>, kotlin.Unit>);
    Code:
         0: aload_1
         1: ldc_w         #1446               // String files
         4: invokestatic  #77                 // Method kotlin/jvm/internal/Intrinsics.checkNotNullParameter:(Ljava/lang/Object;Ljava/lang/String;)V
         7: aload_2
         8: ldc_w         #1447               // String destinationPath
        11: invokestatic  #77                 // Method kotlin/jvm/internal/Intrinsics.checkNotNullParameter:(Ljava/lang/Object;Ljava/lang/String;)V
        14: aload         4
        16: ldc_w         #1449               // String conflictResolutions
        19: invokestatic  #77                 // Method kotlin/jvm/internal/Intrinsics.checkNotNullParameter:(Ljava/lang/Object;Ljava/lang/String;)V
        22: aload         5
        24: ldc_w         #1118               // String callback
        27: invokestatic  #77                 // Method kotlin/jvm/internal/Intrinsics.checkNotNullParameter:(Ljava/lang/Object;Ljava/lang/String;)V
        30: iload_3
        31: aload_1
        32: invokevirtual #572                // Method java/util/ArrayList.size:()I
        35: if_icmpne     49
        38: aload         5
        40: aload         4
        42: invokeinterface #759,  2          // InterfaceMethod kotlin/jvm/functions/Function1.invoke:(Ljava/lang/Object;)Ljava/lang/Object;
        47: pop
        48: return
        49: aload_1
        50: iload_3
        51: invokevirtual #576                // Method java/util/ArrayList.get:(I)Ljava/lang/Object;
        54: dup
        55: ldc_w         #578                // String get(...)
        58: invokestatic  #154                // Method kotlin/jvm/internal/Intrinsics.checkNotNullExpressionValue:(Ljava/lang/Object;Ljava/lang/String;)V
        61: checkcast     #1375               // class org/fossify/commons/models/FileDirItem
        64: astore        6
        66: new           #1375               // class org/fossify/commons/models/FileDirItem
        69: dup
        70: aload_2
        71: aload         6
        73: invokevirtual #1452               // Method org/fossify/commons/models/FileDirItem.getName:()Ljava/lang/String;
        76: invokedynamic #1457,  0           // InvokeDynamic #7:makeConcatWithConstants:(Ljava/lang/String;Ljava/lang/String;)Ljava/lang/String;
        81: aload         6
        83: invokevirtual #1452               // Method org/fossify/commons/models/FileDirItem.getName:()Ljava/lang/String;
        86: aload         6
        88: invokevirtual #1460               // Method org/fossify/commons/models/FileDirItem.isDirectory:()Z
        91: iconst_0
        92: lconst_0
        93: lconst_0
        94: lconst_0
        95: bipush        120
        97: aconst_null
        98: invokespecial #1463               // Method org/fossify/commons/models/FileDirItem."<init>":(Ljava/lang/String;Ljava/lang/String;ZIJJJILkotlin/jvm/internal/DefaultConstructorMarker;)V
       101: astore        7
       103: aload_0
       104: aload         7
       106: aload_1
       107: aload         4
       109: aload_2
       110: aload         5
       112: iload_3
       113: invokedynamic #1471,  0           // InvokeDynamic #8:invoke:(Lorg/fossify/commons/activities/BaseSimpleActivity;Lorg/fossify/commons/models/FileDirItem;Ljava/util/ArrayList;Ljava/util/LinkedHashMap;Ljava/lang/String;Lkotlin/jvm/functions/Function1;I)Lkotlin/jvm/functions/Function0;
       118: invokestatic  #1474               // Method org/fossify/commons/helpers/ConstantsKt.ensureBackgroundThread:(Lkotlin/jvm/functions/Function0;)V
       121: return

  public final void handlePermission(int, kotlin.jvm.functions.Function1<? super java.lang.Boolean, kotlin.Unit>);
    Code:
         0: aload_2
         1: ldc_w         #1118               // String callback
         4: invokestatic  #77                 // Method kotlin/jvm/internal/Intrinsics.checkNotNullParameter:(Ljava/lang/Object;Ljava/lang/String;)V
         7: aload_0
         8: aconst_null
         9: putfield      #55                 // Field actionOnPermission:Lkotlin/jvm/functions/Function1;
        12: aload_0
        13: checkcast     #177                // class android/content/Context
        16: iload_1
        17: invokestatic  #1482               // Method org/fossify/commons/extensions/ContextKt.hasPermission:(Landroid/content/Context;I)Z
        20: ifeq          37
        23: aload_2
        24: iconst_1
        25: invokestatic  #755                // Method java/lang/Boolean.valueOf:(Z)Ljava/lang/Boolean;
        28: invokeinterface #759,  2          // InterfaceMethod kotlin/jvm/functions/Function1.invoke:(Ljava/lang/Object;)Ljava/lang/Object;
        33: pop
        34: goto          73
        37: aload_0
        38: iconst_1
        39: putfield      #61                 // Field isAskingPermissions:Z
        42: aload_0
        43: aload_2
        44: putfield      #55                 // Field actionOnPermission:Lkotlin/jvm/functions/Function1;
        47: aload_0
        48: checkcast     #118                // class android/app/Activity
        51: iconst_1
        52: anewarray     #690                // class java/lang/String
        55: astore_3
        56: aload_3
        57: iconst_0
        58: aload_0
        59: checkcast     #177                // class android/content/Context
        62: iload_1
        63: invokestatic  #1486               // Method org/fossify/commons/extensions/ContextKt.getPermissionString:(Landroid/content/Context;I)Ljava/lang/String;
        66: aastore
        67: aload_3
        68: bipush        100
        70: invokestatic  #1492               // Method androidx/core/app/ActivityCompat.requestPermissions:(Landroid/app/Activity;[Ljava/lang/String;I)V
        73: return

  public final void handlePartialMediaPermissions(java.util.Collection<java.lang.Integer>, boolean, kotlin.jvm.functions.Function1<? super java.lang.Boolean, kotlin.Unit>);
    Code:
         0: aload_1
         1: ldc_w         #1498               // String permissionIds
         4: invokestatic  #77                 // Method kotlin/jvm/internal/Intrinsics.checkNotNullParameter:(Ljava/lang/Object;Ljava/lang/String;)V
         7: aload_3
         8: ldc_w         #1118               // String callback
        11: invokestatic  #77                 // Method kotlin/jvm/internal/Intrinsics.checkNotNullParameter:(Ljava/lang/Object;Ljava/lang/String;)V
        14: aload_0
        15: aconst_null
        16: putfield      #55                 // Field actionOnPermission:Lkotlin/jvm/functions/Function1;
        19: invokestatic  #1501               // Method org/fossify/commons/helpers/ConstantsKt.isUpsideDownCakePlus:()Z
        22: ifeq          216
        25: aload_0
        26: checkcast     #177                // class android/content/Context
        29: bipush        23
        31: invokestatic  #1482               // Method org/fossify/commons/extensions/ContextKt.hasPermission:(Landroid/content/Context;I)Z
        34: ifeq          55
        37: iload_2
        38: ifne          55
        41: aload_3
        42: iconst_1
        43: invokestatic  #755                // Method java/lang/Boolean.valueOf:(Z)Ljava/lang/Boolean;
        46: invokeinterface #759,  2          // InterfaceMethod kotlin/jvm/functions/Function1.invoke:(Ljava/lang/Object;)Ljava/lang/Object;
        51: pop
        52: goto          399
        55: aload_0
        56: iconst_1
        57: putfield      #61                 // Field isAskingPermissions:Z
        60: aload_0
        61: aload_3
        62: putfield      #55                 // Field actionOnPermission:Lkotlin/jvm/functions/Function1;
        65: aload_0
        66: checkcast     #118                // class android/app/Activity
        69: aload_1
        70: checkcast     #658                // class java/lang/Iterable
        73: astore        4
        75: astore        13
        77: iconst_0
        78: istore        5
        80: aload         4
        82: astore        6
        84: new           #569                // class java/util/ArrayList
        87: dup
        88: aload         4
        90: bipush        10
        92: invokestatic  #1371               // Method kotlin/collections/CollectionsKt.collectionSizeOrDefault:(Ljava/lang/Iterable;I)I
        95: invokespecial #1373               // Method java/util/ArrayList."<init>":(I)V
        98: checkcast     #1199               // class java/util/Collection
       101: astore        7
       103: iconst_0
       104: istore        8
       106: aload         6
       108: invokeinterface #662,  1          // InterfaceMethod java/lang/Iterable.iterator:()Ljava/util/Iterator;
       113: astore        9
       115: aload         9
       117: invokeinterface #667,  1          // InterfaceMethod java/util/Iterator.hasNext:()Z
       122: ifeq          172
       125: aload         9
       127: invokeinterface #671,  1          // InterfaceMethod java/util/Iterator.next:()Ljava/lang/Object;
       132: astore        10
       134: aload         7
       136: aload         10
       138: checkcast     #580                // class java/lang/Number
       141: invokevirtual #583                // Method java/lang/Number.intValue:()I
       144: istore        11
       146: astore        14
       148: iconst_0
       149: istore        12
       151: aload_0
       152: checkcast     #177                // class android/content/Context
       155: iload         11
       157: invokestatic  #1486               // Method org/fossify/commons/extensions/ContextKt.getPermissionString:(Landroid/content/Context;I)Ljava/lang/String;
       160: aload         14
       162: swap
       163: invokeinterface #1390,  2         // InterfaceMethod java/util/Collection.add:(Ljava/lang/Object;)Z
       168: pop
       169: goto          115
       172: aload         7
       174: checkcast     #1392               // class java/util/List
       177: nop
       178: aload         13
       180: swap
       181: checkcast     #1199               // class java/util/Collection
       184: astore        4
       186: nop
       187: iconst_0
       188: istore        5
       190: aload         4
       192: astore        6
       194: aload         6
       196: iconst_0
       197: anewarray     #690                // class java/lang/String
       200: invokeinterface #1505,  2         // InterfaceMethod java/util/Collection.toArray:([Ljava/lang/Object;)[Ljava/lang/Object;
       205: checkcast     #1507               // class "[Ljava/lang/String;"
       208: bipush        100
       210: invokestatic  #1492               // Method androidx/core/app/ActivityCompat.requestPermissions:(Landroid/app/Activity;[Ljava/lang/String;I)V
       213: goto          399
       216: aload_0
       217: checkcast     #177                // class android/content/Context
       220: aload_1
       221: invokestatic  #1511               // Method org/fossify/commons/extensions/ContextKt.hasAllPermissions:(Landroid/content/Context;Ljava/util/Collection;)Z
       224: ifeq          241
       227: aload_3
       228: iconst_1
       229: invokestatic  #755                // Method java/lang/Boolean.valueOf:(Z)Ljava/lang/Boolean;
       232: invokeinterface #759,  2          // InterfaceMethod kotlin/jvm/functions/Function1.invoke:(Ljava/lang/Object;)Ljava/lang/Object;
       237: pop
       238: goto          399
       241: aload_0
       242: iconst_1
       243: putfield      #61                 // Field isAskingPermissions:Z
       246: aload_0
       247: aload_3
       248: putfield      #55                 // Field actionOnPermission:Lkotlin/jvm/functions/Function1;
       251: aload_0
       252: checkcast     #118                // class android/app/Activity
       255: aload_1
       256: checkcast     #658                // class java/lang/Iterable
       259: astore        4
       261: astore        13
       263: iconst_0
       264: istore        5
       266: aload         4
       268: astore        6
       270: new           #569                // class java/util/ArrayList
       273: dup
       274: aload         4
       276: bipush        10
       278: invokestatic  #1371               // Method kotlin/collections/CollectionsKt.collectionSizeOrDefault:(Ljava/lang/Iterable;I)I
       281: invokespecial #1373               // Method java/util/ArrayList."<init>":(I)V
       284: checkcast     #1199               // class java/util/Collection
       287: astore        7
       289: iconst_0
       290: istore        8
       292: aload         6
       294: invokeinterface #662,  1          // InterfaceMethod java/lang/Iterable.iterator:()Ljava/util/Iterator;
       299: astore        9
       301: aload         9
       303: invokeinterface #667,  1          // InterfaceMethod java/util/Iterator.hasNext:()Z
       308: ifeq          358
       311: aload         9
       313: invokeinterface #671,  1          // InterfaceMethod java/util/Iterator.next:()Ljava/lang/Object;
       318: astore        10
       320: aload         7
       322: aload         10
       324: checkcast     #580                // class java/lang/Number
       327: invokevirtual #583                // Method java/lang/Number.intValue:()I
       330: istore        11
       332: astore        14
       334: iconst_0
       335: istore        12
       337: aload_0
       338: checkcast     #177                // class android/content/Context
       341: iload         11
       343: invokestatic  #1486               // Method org/fossify/commons/extensions/ContextKt.getPermissionString:(Landroid/content/Context;I)Ljava/lang/String;
       346: aload         14
       348: swap
       349: invokeinterface #1390,  2         // InterfaceMethod java/util/Collection.add:(Ljava/lang/Object;)Z
       354: pop
       355: goto          301
       358: aload         7
       360: checkcast     #1392               // class java/util/List
       363: nop
       364: aload         13
       366: swap
       367: checkcast     #1199               // class java/util/Collection
       370: astore        4
       372: nop
       373: iconst_0
       374: istore        5
       376: aload         4
       378: astore        6
       380: aload         6
       382: iconst_0
       383: anewarray     #690                // class java/lang/String
       386: invokeinterface #1505,  2         // InterfaceMethod java/util/Collection.toArray:([Ljava/lang/Object;)[Ljava/lang/Object;
       391: checkcast     #1507               // class "[Ljava/lang/String;"
       394: bipush        100
       396: invokestatic  #1492               // Method androidx/core/app/ActivityCompat.requestPermissions:(Landroid/app/Activity;[Ljava/lang/String;I)V
       399: return

  public static void handlePartialMediaPermissions$default(org.fossify.commons.activities.BaseSimpleActivity, java.util.Collection, boolean, kotlin.jvm.functions.Function1, int, java.lang.Object);
    Code:
         0: aload         5
         2: ifnull        16
         5: new           #366                // class java/lang/UnsupportedOperationException
         8: dup
         9: ldc_w         #1525               // String Super calls with default arguments not supported in this target, function: handlePartialMediaPermissions
        12: invokespecial #370                // Method java/lang/UnsupportedOperationException."<init>":(Ljava/lang/String;)V
        15: athrow
        16: iload         4
        18: iconst_2
        19: iand
        20: ifeq          25
        23: iconst_0
        24: istore_2
        25: aload_0
        26: aload_1
        27: iload_2
        28: aload_3
        29: invokevirtual #1527               // Method handlePartialMediaPermissions:(Ljava/util/Collection;ZLkotlin/jvm/functions/Function1;)V
        32: return

  public final void handleNotificationPermission(kotlin.jvm.functions.Function1<? super java.lang.Boolean, kotlin.Unit>);
    Code:
         0: aload_1
         1: ldc_w         #1118               // String callback
         4: invokestatic  #77                 // Method kotlin/jvm/internal/Intrinsics.checkNotNullParameter:(Ljava/lang/Object;Ljava/lang/String;)V
         7: invokestatic  #308                // Method org/fossify/commons/helpers/ConstantsKt.isTiramisuPlus:()Z
        10: ifne          27
        13: aload_1
        14: iconst_1
        15: invokestatic  #755                // Method java/lang/Boolean.valueOf:(Z)Ljava/lang/Boolean;
        18: invokeinterface #759,  2          // InterfaceMethod kotlin/jvm/functions/Function1.invoke:(Ljava/lang/Object;)Ljava/lang/Object;
        23: pop
        24: goto          39
        27: aload_0
        28: bipush        17
        30: aload_1
        31: invokedynamic #1536,  0           // InvokeDynamic #9:invoke:(Lkotlin/jvm/functions/Function1;)Lkotlin/jvm/functions/Function1;
        36: invokevirtual #1538               // Method handlePermission:(ILkotlin/jvm/functions/Function1;)V
        39: return

  public void onRequestPermissionsResult(int, java.lang.String[], int[]);
    Code:
         0: aload_2
         1: ldc_w         #1542               // String permissions
         4: invokestatic  #77                 // Method kotlin/jvm/internal/Intrinsics.checkNotNullParameter:(Ljava/lang/Object;Ljava/lang/String;)V
         7: aload_3
         8: ldc_w         #1544               // String grantResults
        11: invokestatic  #77                 // Method kotlin/jvm/internal/Intrinsics.checkNotNullParameter:(Ljava/lang/Object;Ljava/lang/String;)V
        14: aload_0
        15: iload_1
        16: aload_2
        17: aload_3
        18: invokespecial #1546               // Method org/fossify/commons/activities/EdgeToEdgeActivity.onRequestPermissionsResult:(I[Ljava/lang/String;[I)V
        21: aload_0
        22: iconst_0
        23: putfield      #61                 // Field isAskingPermissions:Z
        26: iload_1
        27: bipush        100
        29: if_icmpne     85
        32: aload_3
        33: arraylength
        34: ifne          41
        37: iconst_1
        38: goto          42
        41: iconst_0
        42: ifne          49
        45: iconst_1
        46: goto          50
        49: iconst_0
        50: ifeq          85
        53: aload_0
        54: getfield      #55                 // Field actionOnPermission:Lkotlin/jvm/functions/Function1;
        57: dup
        58: ifnull        84
        61: aload_3
        62: iconst_0
        63: iaload
        64: ifne          71
        67: iconst_1
        68: goto          72
        71: iconst_0
        72: invokestatic  #755                // Method java/lang/Boolean.valueOf:(Z)Ljava/lang/Boolean;
        75: invokeinterface #759,  2          // InterfaceMethod kotlin/jvm/functions/Function1.invoke:(Ljava/lang/Object;)Ljava/lang/Object;
        80: pop
        81: goto          85
        84: pop
        85: return

  public final org.fossify.commons.interfaces.CopyMoveListener getCopyMoveListener();
    Code:
         0: aload_0
         1: getfield      #36                 // Field copyMoveListener:Lorg/fossify/commons/interfaces/CopyMoveListener;
         4: areturn

  public final void checkAppOnSDCard();
    Code:
         0: aload_0
         1: checkcast     #177                // class android/content/Context
         4: invokestatic  #183                // Method org/fossify/commons/extensions/ContextKt.getBaseConfig:(Landroid/content/Context;)Lorg/fossify/commons/helpers/BaseConfig;
         7: invokevirtual #1554               // Method org/fossify/commons/helpers/BaseConfig.getWasAppOnSDShown:()Z
        10: ifne          65
        13: aload_0
        14: checkcast     #118                // class android/app/Activity
        17: invokestatic  #1558               // Method org/fossify/commons/extensions/ActivityKt.isAppInstalledOnSDCard:(Landroid/app/Activity;)Z
        20: ifeq          65
        23: aload_0
        24: checkcast     #177                // class android/content/Context
        27: invokestatic  #183                // Method org/fossify/commons/extensions/ContextKt.getBaseConfig:(Landroid/content/Context;)Lorg/fossify/commons/helpers/BaseConfig;
        30: iconst_1
        31: invokevirtual #1561               // Method org/fossify/commons/helpers/BaseConfig.setWasAppOnSDShown:(Z)V
        34: new           #1563               // class org/fossify/commons/dialogs/ConfirmationDialog
        37: dup
        38: aload_0
        39: checkcast     #118                // class android/app/Activity
        42: ldc           #14                 // String
        44: getstatic     #1566               // Field org/fossify/commons/R$string.app_on_sd_card:I
        47: getstatic     #1569               // Field org/fossify/commons/R$string.ok:I
        50: iconst_0
        51: iconst_0
        52: aconst_null
        53: invokedynamic #1576,  0           // InvokeDynamic #10:invoke:()Lkotlin/jvm/functions/Function0;
        58: bipush        96
        60: aconst_null
        61: invokespecial #1579               // Method org/fossify/commons/dialogs/ConfirmationDialog."<init>":(Landroid/app/Activity;Ljava/lang/String;IIIZLjava/lang/String;Lkotlin/jvm/functions/Function0;ILkotlin/jvm/internal/DefaultConstructorMarker;)V
        64: pop
        65: return

  public final void exportSettings(java.util.LinkedHashMap<java.lang.String, java.lang.Object>);
    Code:
         0: aload_1
         1: ldc_w         #1582               // String configItems
         4: invokestatic  #77                 // Method kotlin/jvm/internal/Intrinsics.checkNotNullParameter:(Ljava/lang/Object;Ljava/lang/String;)V
         7: aload_0
         8: aload_1
         9: putfield      #25                 // Field configItemsToExport:Ljava/util/LinkedHashMap;
        12: new           #1584               // class org/fossify/commons/dialogs/ExportSettingsDialog
        15: dup
        16: aload_0
        17: aload_0
        18: invokespecial #1587               // Method getExportSettingsFilename:()Ljava/lang/String;
        21: iconst_1
        22: aload_0
        23: invokedynamic #1599,  0           // InvokeDynamic #11:invoke:(Lorg/fossify/commons/activities/BaseSimpleActivity;)Lkotlin/jvm/functions/Function2;
        28: invokespecial #1602               // Method org/fossify/commons/dialogs/ExportSettingsDialog."<init>":(Lorg/fossify/commons/activities/BaseSimpleActivity;Ljava/lang/String;ZLkotlin/jvm/functions/Function2;)V
        31: pop
        32: return

  protected final void launchSetDefaultDialerIntent();
    Code:
         0: invokestatic  #514                // Method org/fossify/commons/helpers/ConstantsKt.isQPlus:()Z
         3: ifeq          67
         6: aload_0
         7: ldc_w         #1635               // class android/app/role/RoleManager
        10: invokevirtual #1639               // Method getSystemService:(Ljava/lang/Class;)Ljava/lang/Object;
        13: checkcast     #1635               // class android/app/role/RoleManager
        16: astore_1
        17: aload_1
        18: dup
        19: invokestatic  #782                // Method kotlin/jvm/internal/Intrinsics.checkNotNull:(Ljava/lang/Object;)V
        22: ldc_w         #1641               // String android.app.role.DIALER
        25: invokevirtual #1645               // Method android/app/role/RoleManager.isRoleAvailable:(Ljava/lang/String;)Z
        28: ifeq          148
        31: aload_1
        32: ldc_w         #1641               // String android.app.role.DIALER
        35: invokevirtual #1648               // Method android/app/role/RoleManager.isRoleHeld:(Ljava/lang/String;)Z
        38: ifne          148
        41: aload_1
        42: ldc_w         #1641               // String android.app.role.DIALER
        45: invokevirtual #1652               // Method android/app/role/RoleManager.createRequestRoleIntent:(Ljava/lang/String;)Landroid/content/Intent;
        48: dup
        49: ldc_w         #1654               // String createRequestRoleIntent(...)
        52: invokestatic  #154                // Method kotlin/jvm/internal/Intrinsics.checkNotNullExpressionValue:(Ljava/lang/Object;Ljava/lang/String;)V
        55: astore_2
        56: aload_0
        57: aload_2
        58: sipush        1007
        61: invokevirtual #826                // Method startActivityForResult:(Landroid/content/Intent;I)V
        64: goto          148
        67: new           #706                // class android/content/Intent
        70: dup
        71: ldc_w         #1656               // String android.telecom.action.CHANGE_DEFAULT_DIALER
        74: invokespecial #808                // Method android/content/Intent."<init>":(Ljava/lang/String;)V
        77: ldc_w         #1658               // String android.telecom.extra.CHANGE_DEFAULT_DIALER_PACKAGE_NAME
        80: aload_0
        81: invokevirtual #149                // Method getPackageName:()Ljava/lang/String;
        84: invokevirtual #1032               // Method android/content/Intent.putExtra:(Ljava/lang/String;Ljava/lang/String;)Landroid/content/Intent;
        87: astore_2
        88: aload_2
        89: astore_3
        90: iconst_0
        91: istore        4
        93: nop
        94: aload_0
        95: aload_3
        96: invokestatic  #782                // Method kotlin/jvm/internal/Intrinsics.checkNotNull:(Ljava/lang/Object;)V
        99: aload_3
       100: sipush        1007
       103: invokevirtual #826                // Method startActivityForResult:(Landroid/content/Intent;I)V
       106: goto          141
       109: astore        5
       111: aload_0
       112: checkcast     #177                // class android/content/Context
       115: getstatic     #1661               // Field org/fossify/commons/R$string.no_app_found:I
       118: iconst_0
       119: iconst_2
       120: aconst_null
       121: invokestatic  #856                // Method org/fossify/commons/extensions/ContextKt.toast$default:(Landroid/content/Context;IIILjava/lang/Object;)V
       124: goto          141
       127: astore        5
       129: aload_0
       130: checkcast     #177                // class android/content/Context
       133: aload         5
       135: iconst_0
       136: iconst_2
       137: aconst_null
       138: invokestatic  #830                // Method org/fossify/commons/extensions/ContextKt.showErrorToast$default:(Landroid/content/Context;Ljava/lang/Exception;IILjava/lang/Object;)V
       141: nop
       142: aload_2
       143: astore_1
       144: aload_1
       145: invokestatic  #782                // Method kotlin/jvm/internal/Intrinsics.checkNotNull:(Ljava/lang/Object;)V
       148: return
      Exception table:
         from    to  target type
            93   106   109   Class android/content/ActivityNotFoundException
            93   106   127   Class java/lang/Exception

  public final void setDefaultCallerIdApp();
    Code:
         0: aload_0
         1: ldc_w         #1635               // class android/app/role/RoleManager
         4: invokevirtual #1639               // Method getSystemService:(Ljava/lang/Class;)Ljava/lang/Object;
         7: checkcast     #1635               // class android/app/role/RoleManager
        10: astore_1
        11: aload_1
        12: ldc_w         #1670               // String android.app.role.CALL_SCREENING
        15: invokevirtual #1645               // Method android/app/role/RoleManager.isRoleAvailable:(Ljava/lang/String;)Z
        18: ifeq          54
        21: aload_1
        22: ldc_w         #1670               // String android.app.role.CALL_SCREENING
        25: invokevirtual #1648               // Method android/app/role/RoleManager.isRoleHeld:(Ljava/lang/String;)Z
        28: ifne          54
        31: aload_1
        32: ldc_w         #1670               // String android.app.role.CALL_SCREENING
        35: invokevirtual #1652               // Method android/app/role/RoleManager.createRequestRoleIntent:(Ljava/lang/String;)Landroid/content/Intent;
        38: dup
        39: ldc_w         #1654               // String createRequestRoleIntent(...)
        42: invokestatic  #154                // Method kotlin/jvm/internal/Intrinsics.checkNotNullExpressionValue:(Ljava/lang/Object;Ljava/lang/String;)V
        45: astore_2
        46: aload_0
        47: aload_2
        48: sipush        1010
        51: invokevirtual #826                // Method startActivityForResult:(Landroid/content/Intent;I)V
        54: return

  public static final kotlin.jvm.functions.Function1 access$getFunAfterSAFPermission$cp();
    Code:
         0: getstatic     #258                // Field funAfterSAFPermission:Lkotlin/jvm/functions/Function1;
         3: areturn

  public static final void access$setFunAfterSAFPermission$cp(kotlin.jvm.functions.Function1);
    Code:
         0: aload_0
         1: putstatic     #258                // Field funAfterSAFPermission:Lkotlin/jvm/functions/Function1;
         4: return

  public static final kotlin.jvm.functions.Function1 access$getFunAfterSdk30Action$cp();
    Code:
         0: getstatic     #749                // Field funAfterSdk30Action:Lkotlin/jvm/functions/Function1;
         3: areturn

  public static final void access$setFunAfterSdk30Action$cp(kotlin.jvm.functions.Function1);
    Code:
         0: aload_0
         1: putstatic     #749                // Field funAfterSdk30Action:Lkotlin/jvm/functions/Function1;
         4: return

  public static final kotlin.jvm.functions.Function1 access$getFunAfterUpdate30File$cp();
    Code:
         0: getstatic     #907                // Field funAfterUpdate30File:Lkotlin/jvm/functions/Function1;
         3: areturn

  public static final void access$setFunAfterUpdate30File$cp(kotlin.jvm.functions.Function1);
    Code:
         0: aload_0
         1: putstatic     #907                // Field funAfterUpdate30File:Lkotlin/jvm/functions/Function1;
         4: return

  public static final kotlin.jvm.functions.Function1 access$getFunAfterTrash30File$cp();
    Code:
         0: getstatic     #918                // Field funAfterTrash30File:Lkotlin/jvm/functions/Function1;
         3: areturn

  public static final void access$setFunAfterTrash30File$cp(kotlin.jvm.functions.Function1);
    Code:
         0: aload_0
         1: putstatic     #918                // Field funAfterTrash30File:Lkotlin/jvm/functions/Function1;
         4: return

  public static final kotlin.jvm.functions.Function1 access$getFunRecoverableSecurity$cp();
    Code:
         0: getstatic     #904                // Field funRecoverableSecurity:Lkotlin/jvm/functions/Function1;
         3: areturn

  public static final void access$setFunRecoverableSecurity$cp(kotlin.jvm.functions.Function1);
    Code:
         0: aload_0
         1: putstatic     #904                // Field funRecoverableSecurity:Lkotlin/jvm/functions/Function1;
         4: return

  public static final kotlin.jvm.functions.Function0 access$getFunAfterManageMediaPermission$cp();
    Code:
         0: getstatic     #911                // Field funAfterManageMediaPermission:Lkotlin/jvm/functions/Function0;
         3: areturn

  public static final void access$setFunAfterManageMediaPermission$cp(kotlin.jvm.functions.Function0);
    Code:
         0: aload_0
         1: putstatic     #911                // Field funAfterManageMediaPermission:Lkotlin/jvm/functions/Function0;
         4: return

  static {};
    Code:
         0: new           #2051               // class org/fossify/commons/activities/BaseSimpleActivity$Companion
         3: dup
         4: aconst_null
         5: invokespecial #2054               // Method org/fossify/commons/activities/BaseSimpleActivity$Companion."<init>":(Lkotlin/jvm/internal/DefaultConstructorMarker;)V
         8: putstatic     #2058               // Field Companion:Lorg/fossify/commons/activities/BaseSimpleActivity$Companion;
        11: bipush        8
        13: putstatic     #2061               // Field $stable:I
        16: return
}
